Workbook

Sheet Program
A1: All times UAE time | B1: Click on the +/- icon on left trail to expand/collapse details of sessions
B2: Rooms 1 | C2: Room 2 | D2: Room 3 | E2: Room 4 | F2: Room 5 | G2: Room 6 | H2: Room 7 | I2: Room 8 | J2: Room 9 | K2: Room 10 | L2: Room 11 | M2: Room 12 | N2: Room 13 | O2: Room 14
A3: 46202
A4: 10:00 - 13:30 | B4: tut 1 | C4: tut 2 | D4: tut 3 | E4: wk1101 | F4: wk2001 | G4: wk2301 | H4: wk0900 | I4: wk1900 | J4: wk2100 | K4: wk2200 | L4: wk0100 | N4: Web4All
B5: =IFERROR(__xludf.DUMMYFUNCTION("TEXTJOIN(CHAR(10), TRUE,FILTER(Tutorials!$E:$E,Tutorials!$A:$A=B4))"),"Temporal Information Retrieval And Question Answering in the Age of LLMs Bhawna Piryani, Avishek Anand and Adam Jatowt") -> Temporal Information Retrieval And Question Answering in the Age of LLMs Bhawna Piryani, Avishek Anand and Adam Jatowt | C5: =IFERROR(__xludf.DUMMYFUNCTION("TEXTJOIN(CHAR(10), TRUE,FILTER(Tutorials!$E:$E,Tutorials!$A:$A=C4))"),"Out-of-distribution Generalized Generative AI Xin Wang, Yuwei Zhou, Zirui Pan and Wenwu Zhu") -> Out-of-distribution Generalized Generative AI Xin Wang, Yuwei Zhou, Zirui Pan and Wenwu Zhu | D5: =IFERROR(__xludf.DUMMYFUNCTION("TEXTJOIN(CHAR(10), TRUE,FILTER(Tutorials!$E:$E,Tutorials!$A:$A=D4))"),"Towards a Responsible Web: Economic Perspectives on Fairness in Information Retrieval Chen Xu, Clara Rus, Yuanna Liu, Marleen de Jonge, Jun Xu and Maarten de Rijke") -> Towards a Responsible Web: Economic Perspectives on Fairness in Information Retrieval Chen Xu, Clara Rus, Yuanna Liu, Marleen de Jonge, Jun Xu and Maarten de Rijke | E5: =IFERROR(__xludf.DUMMYFUNCTION("TEXTJOIN(CHAR(10), TRUE,FILTER(Workshops!$F:$F,Workshops!$A:$A=E4))"),"(LARS) part 1 - LLM & Agents for Recommendation Systems Keerthi Gopalakrishnan, Qi Xu, Aysenur Inan, Zhigang Hua, Shuang Yang and Luyi Ma https://llmandagents4recsys.github.io/") -> (LARS) part 1 - LLM & Agents for Recommendation Systems Keerthi Gopalakrishnan, Qi Xu, Aysenur Inan, Zhigang Hua, Shuang Yang and Luyi Ma https://llmandagents4recsys.github.io/ | F5: =IFERROR(__xludf.DUMMYFUNCTION("TEXTJOIN(CHAR(10), TRUE,FILTER(Workshops!$F:$F,Workshops!$A:$A=F4))"),"(WebAds) part 1 - Emerging Trends in Web Advertising Ehsan Toreini and Muadh Al Kalbani https://samsunginternet.github.io/webads26/") -> (WebAds) part 1 - Emerging Trends in Web Advertising Ehsan Toreini and Muadh Al Kalbani https://samsunginternet.github.io/webads26/ | G5: =IFERROR(__xludf.DUMMYFUNCTION("TEXTJOIN(CHAR(10), TRUE,FILTER(Workshops!$F:$F,Workshops!$A:$A=G4))"),"(ZABAPAD) part 1 - Zero-knowledge Proof and Blockchain for Web 4.0: Advancing the Post-quantum and Decentralized Era Shiho Kim, Ho Suk, Roberto Di Pietro, Davor Svetinovic, KyungHi Chang, Madhusudan Singh and Rakesh Shrestha https://zabapad.github.io") -> (ZABAPAD) part 1 - Zero-knowledge Proof and Blockchain for Web 4.0: Advancing the Post-quantum and Decentralized Era Shiho Kim, Ho Suk, Roberto Di Pietro, Davor Svetinovic, KyungHi Chang, Madhusudan Singh and Rakesh Shrestha https://zabapad.github.io | H5: =IFERROR(__xludf.DUMMYFUNCTION("TEXTJOIN(CHAR(10), TRUE,FILTER(Workshops!$F:$F,Workshops!$A:$A=H4))"),"(GLOW) - Graph-enhanced LLMs for Trustworthy Web Data Management Gianluca Bonifazi, Stefano Cirillo, Eliana Pastor and Luca Virgili https://glow-workshop.github.io/www2026/") -> (GLOW) - Graph-enhanced LLMs for Trustworthy Web Data Management Gianluca Bonifazi, Stefano Cirillo, Eliana Pastor and Luca Virgili https://glow-workshop.github.io/www2026/ | I5: =IFERROR(__xludf.DUMMYFUNCTION("TEXTJOIN(CHAR(10), TRUE,FILTER(Workshops!$F:$F,Workshops!$A:$A=I4))"),"(TML) - International Workshop on Trustworthy Multimodal Learning for Social Media Analysis Jingwei Sun,G uosheng Lin, Fengmao Lv, Tao Liang, Junlin Fang and Jianli Wang https://ttthhl.github.io/www2026-workshop/") -> (TML) - International Workshop on Trustworthy Multimodal Learning for Social Media Analysis Jingwei Sun,G uosheng Lin, Fengmao Lv, Tao Liang, Junlin Fang and Jianli Wang https://ttthhl.github.io/www2026-workshop/ | J5: =IFERROR(__xludf.DUMMYFUNCTION("TEXTJOIN(CHAR(10), TRUE,FILTER(Workshops!$F:$F,Workshops!$A:$A=J4))"),"(WebAndTheCity) - 12th International Smart City Workshop – Data-Driven Smart Cities Leonidas Anthopoulos, Marijn Janssen and Vishanth Weerakkody https://webandthecity.home.blog/") -> (WebAndTheCity) - 12th International Smart City Workshop – Data-Driven Smart Cities Leonidas Anthopoulos, Marijn Janssen and Vishanth Weerakkody https://webandthecity.home.blog/ | K5: =IFERROR(__xludf.DUMMYFUNCTION("TEXTJOIN(CHAR(10), TRUE,FILTER(Workshops!$F:$F,Workshops!$A:$A=K4))"),"(WebST) - The 2nd International Workshop on Spatio-Temporal Data Mining from the Web Yuxuan Liang, Hao Xue, Ming Jin, Fei Wang, Qingxiang Liu, Qingsong Wen, Shirui Pan and Flora Salim https://webst2026.netlify.app/") -> (WebST) - The 2nd International Workshop on Spatio-Temporal Data Mining from the Web Yuxuan Liang, Hao Xue, Ming Jin, Fei Wang, Qingxiang Liu, Qingsong Wen, Shirui Pan and Flora Salim https://webst2026.netlify.app/ | L5: =IFERROR(__xludf.DUMMYFUNCTION("TEXTJOIN(CHAR(10), TRUE,FILTER(Workshops!$F:$F,Workshops!$A:$A=L4))"),"(AAIMVT) - 1st Workshop on Applied AI and Multimodal Visualization Technologies Cesar Sanin, Edward Szczerbicki and Md Rafiqul Islam https://rafiqulislamcse24.wixsite.com/aaimvt-26") -> (AAIMVT) - 1st Workshop on Applied AI and Multimodal Visualization Technologies Cesar Sanin, Edward Szczerbicki and Md Rafiqul Islam https://rafiqulislamcse24.wixsite.com/aaimvt-26 | N5: https://www.w4a.info/2026/
A6: 13:00 - 14:00 | B6: Break
A7: 14:00- 17:30 | B7: tut 6 | C7: tut 9 | D7: tut 10 | E7: wk1102 | F7: wk2002 | G7: wk2302 | H7: wk1500 | I7: wk1300 | J7: wk0400 | K7: wk1400 | N7: Web4All
B8: =IFERROR(__xludf.DUMMYFUNCTION("TEXTJOIN(CHAR(10), TRUE,FILTER(Tutorials!$E:$E,Tutorials!$A:$A=B7))"),"Quantum-Safe, Efficient, and AI-Enhanced Blockchains for the Web: A Cooperative Tutorial on Quantum Computing, Blockchain Applications, and Data Standards Dongping Liu, Aoyu Zhang and Luyao Zhang") -> Quantum-Safe, Efficient, and AI-Enhanced Blockchains for the Web: A Cooperative Tutorial on Quantum Computing, Blockchain Applications, and Data Standards Dongping Liu, Aoyu Zhang and Luyao Zhang | C8: =IFERROR(__xludf.DUMMYFUNCTION("TEXTJOIN(CHAR(10), TRUE,FILTER(Tutorials!$E:$E,Tutorials!$A:$A=C7))"),"Bandits, LLMs, and Agentic Web Djallel Bouneffouf and Raphael Feraud") -> Bandits, LLMs, and Agentic Web Djallel Bouneffouf and Raphael Feraud | D8: =IFERROR(__xludf.DUMMYFUNCTION("TEXTJOIN(CHAR(10), TRUE,FILTER(Tutorials!$E:$E,Tutorials!$A:$A=D7))"),"Unstructured to Structured: Building Knowledge Graphs from Documents for Web Applications Qiang Sun, Yihao Ding, Sirui Li and Wei Liu") -> Unstructured to Structured: Building Knowledge Graphs from Documents for Web Applications Qiang Sun, Yihao Ding, Sirui Li and Wei Liu | E8: =IFERROR(__xludf.DUMMYFUNCTION("TEXTJOIN(CHAR(10), TRUE,FILTER(Workshops!$F:$F,Workshops!$A:$A=E7))"),"(LARS) part 2 - LLM & Agents for Recommendation Systems Keerthi Gopalakrishnan, Qi Xu, Aysenur Inan, Zhigang Hua, Shuang Yang and Luyi Ma https://llmandagents4recsys.github.io/") -> (LARS) part 2 - LLM & Agents for Recommendation Systems Keerthi Gopalakrishnan, Qi Xu, Aysenur Inan, Zhigang Hua, Shuang Yang and Luyi Ma https://llmandagents4recsys.github.io/ | F8: =IFERROR(__xludf.DUMMYFUNCTION("TEXTJOIN(CHAR(10), TRUE,FILTER(Workshops!$F:$F,Workshops!$A:$A=F7))"),"(WebAds) part 2 - Emerging Trends in Web Advertising Ehsan Toreini and Muadh Al Kalbani https://samsunginternet.github.io/webads26/") -> (WebAds) part 2 - Emerging Trends in Web Advertising Ehsan Toreini and Muadh Al Kalbani https://samsunginternet.github.io/webads26/ | G8: =IFERROR(__xludf.DUMMYFUNCTION("TEXTJOIN(CHAR(10), TRUE,FILTER(Workshops!$F:$F,Workshops!$A:$A=G7))"),"(ZABAPAD) part 2 - Zero-knowledge Proof and Blockchain for Web 4.0: Advancing the Post-quantum and Decentralized Era Shiho Kim, Ho Suk, Roberto Di Pietro, Davor Svetinovic, KyungHi Chang, Madhusudan Singh and Rakesh Shrestha https://zabapad.github.io") -> (ZABAPAD) part 2 - Zero-knowledge Proof and Blockchain for Web 4.0: Advancing the Post-quantum and Decentralized Era Shiho Kim, Ho Suk, Roberto Di Pietro, Davor Svetinovic, KyungHi Chang, Madhusudan Singh and Rakesh Shrestha https://zabapad.github.io | H8: =IFERROR(__xludf.DUMMYFUNCTION("TEXTJOIN(CHAR(10), TRUE,FILTER(Workshops!$F:$F,Workshops!$A:$A=H7))"),"(SemTech) - 4th International Workshop on AI and Semantic Technologies for the Scientific, Technical, and Legal Web Rima Dessi', Jeenu Joy, Danilo Dessi', Francesco Osborne and Hidir Aras https://semtech4stld.github.io/") -> (SemTech) - 4th International Workshop on AI and Semantic Technologies for the Scientific, Technical, and Legal Web Rima Dessi', Jeenu Joy, Danilo Dessi', Francesco Osborne and Hidir Aras https://semtech4stld.github.io/ | I8: =IFERROR(__xludf.DUMMYFUNCTION("TEXTJOIN(CHAR(10), TRUE,FILTER(Workshops!$F:$F,Workshops!$A:$A=I7))"),"(PromptEng) - Third International Workshop on Prompt Engineering for Pre-Trained Language Models Damien Graux, Sébastien Montella and Hajira Jabeen https://prompteng-ws.github.io/2026/") -> (PromptEng) - Third International Workshop on Prompt Engineering for Pre-Trained Language Models Damien Graux, Sébastien Montella and Hajira Jabeen https://prompteng-ws.github.io/2026/ | J8: =IFERROR(__xludf.DUMMYFUNCTION("TEXTJOIN(CHAR(10), TRUE,FILTER(Workshops!$F:$F,Workshops!$A:$A=J7))"),"(BeyondFacts'26) - 6th International Workshop on Computational Methods for Online Discourse Analysis Stefan Dietze, Dimitar Dimitrov, Pavlos Fafalios and Konstantin Todorov https://beyondfacts2026.wordpress.com/") -> (BeyondFacts'26) - 6th International Workshop on Computational Methods for Online Discourse Analysis Stefan Dietze, Dimitar Dimitrov, Pavlos Fafalios and Konstantin Todorov https://beyondfacts2026.wordpress.com/ | K8: =IFERROR(__xludf.DUMMYFUNCTION("TEXTJOIN(CHAR(10), TRUE,FILTER(Workshops!$F:$F,Workshops!$A:$A=K7))"),"(R2CASS) - The 2nd International Workshop on Social Science Meets Web Data: Reproducible and Reusable Computational Approaches Fakhri Momeni, Arnim Bleier, Danilo Dessi and Muhammad Taimoor Khan https://sites.google.com/view/r2cass/home") -> (R2CASS) - The 2nd International Workshop on Social Science Meets Web Data: Reproducible and Reusable Computational Approaches Fakhri Momeni, Arnim Bleier, Danilo Dessi and Muhammad Taimoor Khan https://sites.google.com/view/r2cass/home | N8: https://www.w4a.info/2026/
A10: 46203
A11: 10:00 - 13:30 | B11: tut 4 | C11: tut 7 | D11: tut 11 | E11: wk1000 | F11: wk0501 | G11: wk0601 | H11: wk1601 | I11: wk1801 | J11: wk0300 | K11: wk0200 | L11: wk1700 | M11: PhD Symposium Part 1 | N11: Web4All
B12: =IFERROR(__xludf.DUMMYFUNCTION("TEXTJOIN(CHAR(10), TRUE,FILTER(Tutorials!$E:$E,Tutorials!$A:$A=B11))"),"Next-Gen Code Development with Collaborative AI Agents Shweta Garg, Behrooz Omidvar-Tehrani, Shengyu Fu, Gauthier Guinet and Baishakhi Ray") -> Next-Gen Code Development with Collaborative AI Agents Shweta Garg, Behrooz Omidvar-Tehrani, Shengyu Fu, Gauthier Guinet and Baishakhi Ray | C12: =IFERROR(__xludf.DUMMYFUNCTION("TEXTJOIN(CHAR(10), TRUE,FILTER(Tutorials!$E:$E,Tutorials!$A:$A=C11))"),"Conversational Search: From Fundamentals to Frontiers in the Age of Agents Chuan Meng, Fengran Mo, Mohammad Aliannejadi, Jeff Dalton and Jian-Yun Nie") -> Conversational Search: From Fundamentals to Frontiers in the Age of Agents Chuan Meng, Fengran Mo, Mohammad Aliannejadi, Jeff Dalton and Jian-Yun Nie | D12: =IFERROR(__xludf.DUMMYFUNCTION("TEXTJOIN(CHAR(10), TRUE,FILTER(Tutorials!$E:$E,Tutorials!$A:$A=D11))"),"Foundations for the Agentic Web: Infrastructure, Economics, and Society Ramesh Raskar and Pradyumna Chari") -> Foundations for the Agentic Web: Infrastructure, Economics, and Society Ramesh Raskar and Pradyumna Chari | E12: =IFERROR(__xludf.DUMMYFUNCTION("TEXTJOIN(CHAR(10), TRUE,FILTER(Workshops!$F:$F,Workshops!$A:$A=E11))"),"(HCRS) - The 2nd Workshop on Human-Centered Recommender Systems Kaike Zhang, Jiakai Tang, Du Su, Shuchang Liu, Julian McAuley, Lina Yao, Qi Cao, Yue Feng and Fei Sun https://hcrec.github.io/") -> (HCRS) - The 2nd Workshop on Human-Centered Recommender Systems Kaike Zhang, Jiakai Tang, Du Su, Shuchang Liu, Julian McAuley, Lina Yao, Qi Cao, Yue Feng and Fei Sun https://hcrec.github.io/ | F12: =IFERROR(__xludf.DUMMYFUNCTION("TEXTJOIN(CHAR(10), TRUE,FILTER(Workshops!$F:$F,Workshops!$A:$A=F11))"),"(DHOW-MiLLA) part 1 - Joint Workshop on Diffusion of Harmful Content on Online Web and Countering Misinformation in the Age of LLMs and Agents Thomas Mandl, Haiming Liu, Gautam Kishore Shahi, Amit Kumar Jaiswal, Durgesh Nandini, Luis-Daniel Ibáñez, Junich"&"i Suga, Dai Yamamoto, Rahul Mishra, Rajakrishnan P. Rajkumar, Sagar Uprety, Sujit Kuma and Bornali Phukon https://dhow-workshop.github.io/2026/") -> (DHOW-MiLLA) part 1 - Joint Workshop on Diffusion of Harmful Content on Online Web and Countering Misinformation in the Age of LLMs and Agents Thomas Mandl, Haiming Liu, Gautam Kishore Shahi, Amit Kumar Jaiswal, Durgesh Nandini, Luis-Daniel Ibáñez, Junichi Suga, Dai Yamamoto, Rahul Mishra, Rajakrishnan P. Rajkumar, Sagar Uprety, Sujit Kuma and Bornali Phukon https://dhow-workshop.github.io/2026/ | G12: =IFERROR(__xludf.DUMMYFUNCTION("TEXTJOIN(CHAR(10), TRUE,FILTER(Workshops!$F:$F,Workshops!$A:$A=G11))"),"(FAAW) part 1 - International Workshop on Foundations and Architectures for the Agentic Web Abderrahmane Maaradji, Abul Ehtesham, Aditi Singh, Boualem Benatallah, Fatma Outay, Luca Muscariello, Pradyumna Chari, Ramesh Raskar, Sabrina Senatore and Yacine S"&"am https://faaw.univ-tours.fr/") -> (FAAW) part 1 - International Workshop on Foundations and Architectures for the Agentic Web Abderrahmane Maaradji, Abul Ehtesham, Aditi Singh, Boualem Benatallah, Fatma Outay, Luca Muscariello, Pradyumna Chari, Ramesh Raskar, Sabrina Senatore and Yacine Sam https://faaw.univ-tours.fr/ | H12: =IFERROR(__xludf.DUMMYFUNCTION("TEXTJOIN(CHAR(10), TRUE,FILTER(Workshops!$F:$F,Workshops!$A:$A=H11))"),"(TempWeb) part 1 - The 16th Temporal Web Analytics Workshop Marc Spaniol, France Omar Alonso and Ricardo Baeza-Yates https://temporalweb.net/") -> (TempWeb) part 1 - The 16th Temporal Web Analytics Workshop Marc Spaniol, France Omar Alonso and Ricardo Baeza-Yates https://temporalweb.net/ | I12: =IFERROR(__xludf.DUMMYFUNCTION("TEXTJOIN(CHAR(10), TRUE,FILTER(Workshops!$F:$F,Workshops!$A:$A=I11))"),"(TIME) part 1 - 2nd International Workshop on Transformative Insights in Multi-faceted Evaluation Lei Wang, Md Zakir Hossain, Tom Gedeon, Syed Mohammed Shamsul Islam. Rafiqul Islam. Yasmeen George and Shreya Ghosh https://time.griffith.edu.au/workshop/"&"time2026/") -> (TIME) part 1 - 2nd International Workshop on Transformative Insights in Multi-faceted Evaluation Lei Wang, Md Zakir Hossain, Tom Gedeon, Syed Mohammed Shamsul Islam. Rafiqul Islam. Yasmeen George and Shreya Ghosh https://time.griffith.edu.au/workshop/time2026/ | J12: =IFERROR(__xludf.DUMMYFUNCTION("TEXTJOIN(CHAR(10), TRUE,FILTER(Workshops!$F:$F,Workshops!$A:$A=J11))"),"(ALTARS 2026) - 4th Workshop on Augmented Intelligence in Technology-Assisted Review Systems Giorgio Maria Di Nunzio, Evangelos Kanoulas and Prasenjit Majumder https://altars2026.dei.unipd.it/") -> (ALTARS 2026) - 4th Workshop on Augmented Intelligence in Technology-Assisted Review Systems Giorgio Maria Di Nunzio, Evangelos Kanoulas and Prasenjit Majumder https://altars2026.dei.unipd.it/ | K12: =IFERROR(__xludf.DUMMYFUNCTION("TEXTJOIN(CHAR(10), TRUE,FILTER(Workshops!$F:$F,Workshops!$A:$A=K11))"),"(AiOfAi) - The Workshop on Adverse Impacts and Collateral Effects of Artificial Intelligence Technologies Esma Aïmeur, Rim Ben Salem, Dorsaf Sallami, Julita Vassileva and Nora Boulahia-Cuppens https://sites.google.com/view/aiofai-2026/home") -> (AiOfAi) - The Workshop on Adverse Impacts and Collateral Effects of Artificial Intelligence Technologies Esma Aïmeur, Rim Ben Salem, Dorsaf Sallami, Julita Vassileva and Nora Boulahia-Cuppens https://sites.google.com/view/aiofai-2026/home | L12: =IFERROR(__xludf.DUMMYFUNCTION("TEXTJOIN(CHAR(10), TRUE,FILTER(Workshops!$F:$F,Workshops!$A:$A=L11))"),"(TrustFM) - Trustworthy Foundation Models for Web Intelligence: Causal Perspectives and Challenges Haoang Chi Qi Wang Jiantong Jiang Jiangchao Yao Feng Liu Bo Han https://www-tfm-causal.github.io/www2026-workshop/") -> (TrustFM) - Trustworthy Foundation Models for Web Intelligence: Causal Perspectives and Challenges Haoang Chi Qi Wang Jiantong Jiang Jiangchao Yao Feng Liu Bo Han https://www-tfm-causal.github.io/www2026-workshop/ | M12: =IFERROR(__xludf.DUMMYFUNCTION("TEXTJOIN(CHAR(10), TRUE,FILTER('PhD Symposium'!$D:$D,'PhD Symposium'!$E:$E=M11))"),"Tutoring Large Language Models to be Domain-adaptive, Precise, and Safe Somnath Banerjee LeTCC-ZK: Smooth, Verifiable Distributed Inference via Spline-Coded Computing Ekaterina Pavlova Edge-Mamba: Efficient and Robust Security Evaluation for the Web of "&"Things via Selective State Spaces Chenchong Du Towards Conversational Dataset Discovery on the Web Lisa-Yao Gan Constructing the Cycle of Mastery: LLM-Empowered Intelligent Tutoring for Programming Education Junfeng Zhang ") -> Tutoring Large Language Models to be Domain-adaptive, Precise, and Safe Somnath Banerjee LeTCC-ZK: Smooth, Verifiable Distributed Inference via Spline-Coded Computing Ekaterina Pavlova Edge-Mamba: Efficient and Robust Security Evaluation for the Web of Things via Selective State Spaces Chenchong Du Towards Conversational Dataset Discovery on the Web Lisa-Yao Gan Constructing the Cycle of Mastery: LLM-Empowered Intelligent Tutoring for Programming Education Junfeng Zhang | N12: https://www.w4a.info/2026/
A13: 13:00 - 14:00 | B13: Break
A14: 14:00 - 17:30 | B14: tut 5 | C14: tut 12 | D14: tut 13 | E14: tut 14 | F14: wk0502 | G14: wk0602 | H14: wk1602 | I14: wk1802 | J14: wk0800 | K14: wk1200 | M14: PhD Symposium Part 2 | N14: Web4All
B15: =IFERROR(__xludf.DUMMYFUNCTION("TEXTJOIN(CHAR(10), TRUE,FILTER(Tutorials!$E:$E,Tutorials!$A:$A=B14))"),"LLM-Enhanced Web-Centric Spatio-Temporal Intelligence: Methods, Applications, and Frontier Research Zijian Zhang, Hao Miao, Yuxuan Liang, Yan Zhao and Irwin King") -> LLM-Enhanced Web-Centric Spatio-Temporal Intelligence: Methods, Applications, and Frontier Research Zijian Zhang, Hao Miao, Yuxuan Liang, Yan Zhao and Irwin King | C15: =IFERROR(__xludf.DUMMYFUNCTION("TEXTJOIN(CHAR(10), TRUE,FILTER(Tutorials!$E:$E,Tutorials!$A:$A=C14))"),"Generalist Model for Structured Data: Foundations, Frontiers and Applications Peng Cui, Xingxuan Zhang, Han-Jia Ye, Jintai Chen and Shuyang Li") -> Generalist Model for Structured Data: Foundations, Frontiers and Applications Peng Cui, Xingxuan Zhang, Han-Jia Ye, Jintai Chen and Shuyang Li | D15: =IFERROR(__xludf.DUMMYFUNCTION("TEXTJOIN(CHAR(10), TRUE,FILTER(Tutorials!$E:$E,Tutorials!$A:$A=D14))"),"Robust Graph Learning on the Web: Challenges, Methods, and Applications Xiang Ao, Yang Liu, Guansong Pang, Yuanhao Ding, Hezhe Qiao, Dawei Cheng and Qing He") -> Robust Graph Learning on the Web: Challenges, Methods, and Applications Xiang Ao, Yang Liu, Guansong Pang, Yuanhao Ding, Hezhe Qiao, Dawei Cheng and Qing He | E15: =IFERROR(__xludf.DUMMYFUNCTION("TEXTJOIN(CHAR(10), TRUE,FILTER(Tutorials!$E:$E,Tutorials!$A:$A=E14))"),"Responsible Prompting on the Web: Governance, Mini-Evaluation, and Readiness with ChatGPT Manali Sharma and Ayush Garg") -> Responsible Prompting on the Web: Governance, Mini-Evaluation, and Readiness with ChatGPT Manali Sharma and Ayush Garg | F15: =IFERROR(__xludf.DUMMYFUNCTION("TEXTJOIN(CHAR(10), TRUE,FILTER(Workshops!$F:$F,Workshops!$A:$A=F14))"),"(DHOW-MiLLA) part 2 - Joint Workshop on Diffusion of Harmful Content on Online Web and Countering Misinformation in the Age of LLMs and Agents Thomas Mandl, Haiming Liu, Gautam Kishore Shahi, Amit Kumar Jaiswal, Durgesh Nandini, Luis-Daniel Ibáñez, Junich"&"i Suga, Dai Yamamoto, Rahul Mishra, Rajakrishnan P. Rajkumar, Sagar Uprety, Sujit Kuma and Bornali Phukon https://dhow-workshop.github.io/2026/") -> (DHOW-MiLLA) part 2 - Joint Workshop on Diffusion of Harmful Content on Online Web and Countering Misinformation in the Age of LLMs and Agents Thomas Mandl, Haiming Liu, Gautam Kishore Shahi, Amit Kumar Jaiswal, Durgesh Nandini, Luis-Daniel Ibáñez, Junichi Suga, Dai Yamamoto, Rahul Mishra, Rajakrishnan P. Rajkumar, Sagar Uprety, Sujit Kuma and Bornali Phukon https://dhow-workshop.github.io/2026/ | G15: =IFERROR(__xludf.DUMMYFUNCTION("TEXTJOIN(CHAR(10), TRUE,FILTER(Workshops!$F:$F,Workshops!$A:$A=G14))"),"(FAAW) part 2 - International Workshop on Foundations and Architectures for the Agentic Web Abderrahmane Maaradji, Abul Ehtesham, Aditi Singh, Boualem Benatallah, Fatma Outay, Luca Muscariello, Pradyumna Chari, Ramesh Raskar, Sabrina Senatore and Yacine S"&"am https://faaw.univ-tours.fr/") -> (FAAW) part 2 - International Workshop on Foundations and Architectures for the Agentic Web Abderrahmane Maaradji, Abul Ehtesham, Aditi Singh, Boualem Benatallah, Fatma Outay, Luca Muscariello, Pradyumna Chari, Ramesh Raskar, Sabrina Senatore and Yacine Sam https://faaw.univ-tours.fr/ | H15: =IFERROR(__xludf.DUMMYFUNCTION("TEXTJOIN(CHAR(10), TRUE,FILTER(Workshops!$F:$F,Workshops!$A:$A=H14))"),"(TempWeb) part 2 - The 16th Temporal Web Analytics Workshop Marc Spaniol, France Omar Alonso and Ricardo Baeza-Yates https://temporalweb.net/") -> (TempWeb) part 2 - The 16th Temporal Web Analytics Workshop Marc Spaniol, France Omar Alonso and Ricardo Baeza-Yates https://temporalweb.net/ | I15: =IFERROR(__xludf.DUMMYFUNCTION("TEXTJOIN(CHAR(10), TRUE,FILTER(Workshops!$F:$F,Workshops!$A:$A=I14))"),"(TIME) part 2 - 2nd International Workshop on Transformative Insights in Multi-faceted Evaluation Lei Wang, Md Zakir Hossain, Tom Gedeon, Syed Mohammed Shamsul Islam. Rafiqul Islam. Yasmeen George and Shreya Ghosh https://time.griffith.edu.au/workshop/"&"time2026/") -> (TIME) part 2 - 2nd International Workshop on Transformative Insights in Multi-faceted Evaluation Lei Wang, Md Zakir Hossain, Tom Gedeon, Syed Mohammed Shamsul Islam. Rafiqul Islam. Yasmeen George and Shreya Ghosh https://time.griffith.edu.au/workshop/time2026/ | J15: =IFERROR(__xludf.DUMMYFUNCTION("TEXTJOIN(CHAR(10), TRUE,FILTER(Workshops!$F:$F,Workshops!$A:$A=J14))"),"(FL@FM) - International Workshop on Federated Foundation Models for the Web 2026 Irwin King, Guodong Long, Zenglin Xu, Han Yu, Xiaoli Tang and Liping Yi https://federated-learning.org/fl@fm-www-2026/") -> (FL@FM) - International Workshop on Federated Foundation Models for the Web 2026 Irwin King, Guodong Long, Zenglin Xu, Han Yu, Xiaoli Tang and Liping Yi https://federated-learning.org/fl@fm-www-2026/ | K15: =IFERROR(__xludf.DUMMYFUNCTION("TEXTJOIN(CHAR(10), TRUE,FILTER(Workshops!$F:$F,Workshops!$A:$A=K14))"),"(MM4SG) - Fourth International Workshop on Multimodal Content Analysis for Social Good Usman Naseem, Surendrabikram Thapa, Roy Ka-Wei Lee and Mehwish Nasim https://sites.google.com/view/mm4sg-webconf26") -> (MM4SG) - Fourth International Workshop on Multimodal Content Analysis for Social Good Usman Naseem, Surendrabikram Thapa, Roy Ka-Wei Lee and Mehwish Nasim https://sites.google.com/view/mm4sg-webconf26 | M15: =IFERROR(__xludf.DUMMYFUNCTION("TEXTJOIN(CHAR(10), TRUE,FILTER('PhD Symposium'!$D:$D,'PhD Symposium'!$E:$E=M14))"),"Foundational Representations for Efficient Retrieval of Structured Tabular Data Inwon Kang Exploring Political Attitudes under Selective Media Consumption with Large Language Models Upasana Dutta How the Web Remembers Multilingual Collective Memory on W"&"ikipedia and in Large Language Models H. Laurie Lawson Can You Trust the Data Trust? An Ning Shen Introducing Temporal Dynamics to Proactive Recommender Systems for Email Outreach Čeněk Žid ") -> Foundational Representations for Efficient Retrieval of Structured Tabular Data Inwon Kang Exploring Political Attitudes under Selective Media Consumption with Large Language Models Upasana Dutta How the Web Remembers Multilingual Collective Memory on Wikipedia and in Large Language Models H. Laurie Lawson Can You Trust the Data Trust? An Ning Shen Introducing Temporal Dynamics to Proactive Recommender Systems for Email Outreach Čeněk Žid | N15: https://www.w4a.info/2026/
A18: 46204
A19: 10:00 - 10:30 | B19: Conference Opening
A20: 10:30 - 11:30 | B20: Keynote #1: Katrina Liggett
A21: 11:30 - 12:00 | B21: Break
A22: 12:00 - 13:30 | B22: Econ1 | C22: Graph1 | D22: Graph7 | E22: Search1 | F22: Semantics3 | G22: Social1 | H22: Systems1 | I22: Security3 | J22: Mining1 | K22: RecSys1 | L22: Industry1 | M22: Industry2 | N22: History1
B23: =IFERROR(__xludf.DUMMYFUNCTION("TEXTJOIN(CHAR(10), TRUE,FILTER('Sessions Counts'!$B:$B,'Sessions Counts'!$A:$A=B22))"),"Social Dynamics, Voting, and Consensus") -> Social Dynamics, Voting, and Consensus | C23: =IFERROR(__xludf.DUMMYFUNCTION("TEXTJOIN(CHAR(10), TRUE,FILTER('Sessions Counts'!$B:$B,'Sessions Counts'!$A:$A=C22))"),"Graph Foundation Models 1") -> Graph Foundation Models 1 | D23: =IFERROR(__xludf.DUMMYFUNCTION("TEXTJOIN(CHAR(10), TRUE,FILTER('Sessions Counts'!$B:$B,'Sessions Counts'!$A:$A=D22))"),"Anomaly Detection") -> Anomaly Detection | E23: =IFERROR(__xludf.DUMMYFUNCTION("TEXTJOIN(CHAR(10), TRUE,FILTER('Sessions Counts'!$B:$B,'Sessions Counts'!$A:$A=E22))"),"Zero-Shot & Graph RAG") -> Zero-Shot & Graph RAG | F23: =IFERROR(__xludf.DUMMYFUNCTION("TEXTJOIN(CHAR(10), TRUE,FILTER('Sessions Counts'!$B:$B,'Sessions Counts'!$A:$A=F22))"),"Logical Reasoning & Graph Understanding") -> Logical Reasoning & Graph Understanding | G23: =IFERROR(__xludf.DUMMYFUNCTION("TEXTJOIN(CHAR(10), TRUE,FILTER('Sessions Counts'!$B:$B,'Sessions Counts'!$A:$A=G22))"),"Opinion Dynamics and Misinformation") -> Opinion Dynamics and Misinformation | H23: =IFERROR(__xludf.DUMMYFUNCTION("TEXTJOIN(CHAR(10), TRUE,FILTER('Sessions Counts'!$B:$B,'Sessions Counts'!$A:$A=H22))"),"Client-Adaptive Federated Learning") -> Client-Adaptive Federated Learning | I23: =IFERROR(__xludf.DUMMYFUNCTION("TEXTJOIN(CHAR(10), TRUE,FILTER('Sessions Counts'!$B:$B,'Sessions Counts'!$A:$A=I22))"),"Fingerprinting") -> Fingerprinting | J23: =IFERROR(__xludf.DUMMYFUNCTION("TEXTJOIN(CHAR(10), TRUE,FILTER('Sessions Counts'!$B:$B,'Sessions Counts'!$A:$A=J22))"),"Sequence and Temporal Pattern Mining") -> Sequence and Temporal Pattern Mining | K23: =IFERROR(__xludf.DUMMYFUNCTION("TEXTJOIN(CHAR(10), TRUE,FILTER('Sessions Counts'!$B:$B,'Sessions Counts'!$A:$A=K22))"),"Multi-Behavior User Modeling") -> Multi-Behavior User Modeling | L23: =IFERROR(__xludf.DUMMYFUNCTION("TEXTJOIN(CHAR(10), TRUE,FILTER('Industry assignment'!$B:$B,'Industry assignment'!$A:$A=L22))"),"Financial Intelligence & Market Simulation") -> Financial Intelligence & Market Simulation | M23: =IFERROR(__xludf.DUMMYFUNCTION("TEXTJOIN(CHAR(10), TRUE,FILTER('Sessions Counts'!$B:$B,'Sessions Counts'!$A:$A=M22))"),"Generative & Next-Gen Recommendation Architectures") -> Generative & Next-Gen Recommendation Architectures
B24: =IFERROR(__xludf.DUMMYFUNCTION("TEXTJOIN(CHAR(10), TRUE,FILTER('Research assignment'!$D:$D,'Research assignment'!$F:$F=B22))"),"Opinion Dynamics with Multiple Adversaries Akhil Jalan and Marios Papachristou Aggregating Information and Preferences under Different Coordination Ability Qishen Han, Grant Schoenebeck, Biaoshuai Tao and Lirong Xia The Art of Two-Round Voting Qishen Ha"&"n, Grant Schoenebeck, Biaoshuai Tao and Lirong Xia The Price of Uncertainty for Social Consensus Yunzhe Bai and Alec Sun Social Deliberation: Democratic Deliberation Through Unbiased Social Interactions Dana Afazeli, Mohamad Latifian and Masoud Seddighi"&"n ") -> Opinion Dynamics with Multiple Adversaries Akhil Jalan and Marios Papachristou Aggregating Information and Preferences under Different Coordination Ability Qishen Han, Grant Schoenebeck, Biaoshuai Tao and Lirong Xia The Art of Two-Round Voting Qishen Han, Grant Schoenebeck, Biaoshuai Tao and Lirong Xia The Price of Uncertainty for Social Consensus Yunzhe Bai and Alec Sun Social Deliberation: Democratic Deliberation Through Unbiased Social Interactions Dana Afazeli, Mohamad Latifian and Masoud Seddighin | C24: =IFERROR(__xludf.DUMMYFUNCTION("TEXTJOIN(CHAR(10), TRUE,FILTER('Research assignment'!$D:$D,'Research assignment'!$F:$F=C22))"),"Topology-Aware Feature Sorting Enables Universal Modeling on Homophilic and Heterophilic Graphs Yi Wang, Jitao Zhao, Dongxiao He, Jia Li, Yuxiao Huang and Zhiyong Feng A Graph Foundation Model for Unified Anomaly Detection Renda Han, Xiaobao Wang, Luzhi "&"Wang, Wenxin Zhang, Guangzhen Yao and Hongxiang Liang RAG-GFM: Overcoming In-Memory Bottlenecks in Graph Foundation Models via Retrieval-Augmented Generation Haonan Yuan, Qingyun Sun, Jiacheng Tao, Xingcheng Fu and Jianxin Li Towards Graph Foundation Mo"&"del: Node Feature Transfer Invariant Modeling on General Graphs Jitao Zhao, Yi Wang, Yawen Li, Dongxiao He, Di Jin, Zhiyong Feng and Weixiong Zhang GraphRAG-R1: Graph Retrieval-Augmented Generation with Process-Constrained Reinforcement Learning Chuanyue"&" Yu, Kuo Zhao, Yuhan Li, Heng Chang, Mingjian Feng, Xiangzhe Jiang, Yufei Sun, Jia Li, Yuzhi Zhang, Qingyun Sun, Jianxin Li and Ziwei Zhang ") -> Topology-Aware Feature Sorting Enables Universal Modeling on Homophilic and Heterophilic Graphs Yi Wang, Jitao Zhao, Dongxiao He, Jia Li, Yuxiao Huang and Zhiyong Feng A Graph Foundation Model for Unified Anomaly Detection Renda Han, Xiaobao Wang, Luzhi Wang, Wenxin Zhang, Guangzhen Yao and Hongxiang Liang RAG-GFM: Overcoming In-Memory Bottlenecks in Graph Foundation Models via Retrieval-Augmented Generation Haonan Yuan, Qingyun Sun, Jiacheng Tao, Xingcheng Fu and Jianxin Li Towards Graph Foundation Model: Node Feature Transfer Invariant Modeling on General Graphs Jitao Zhao, Yi Wang, Yawen Li, Dongxiao He, Di Jin, Zhiyong Feng and Weixiong Zhang GraphRAG-R1: Graph Retrieval-Augmented Generation with Process-Constrained Reinforcement Learning Chuanyue Yu, Kuo Zhao, Yuhan Li, Heng Chang, Mingjian Feng, Xiangzhe Jiang, Yufei Sun, Jia Li, Yuzhi Zhang, Qingyun Sun, Jianxin Li and Ziwei Zhang | D24: =IFERROR(__xludf.DUMMYFUNCTION("TEXTJOIN(CHAR(10), TRUE,FILTER('Research assignment'!$D:$D,'Research assignment'!$F:$F=D22))"),"Unsupervised Subgraph Anomaly Detection based on Pattern Collaboration Sun Jiayang, Liu Shenghao, Deng Xianjun, Xiang Wei, Luo Meng, Zhang Qiankun and Zheng Dandan DP-DGAD: A Generalist Dynamic Graph Anomaly Detector with Dynamic Prototypes Jialun Zheng,"&" Jie Liu, Jiannong Cao, Xiao Wang, Hanchen Yang and Yankai Chen Anomaly Detection of Interaction Behaviors in Streaming Graphs Shuai Ren, Fan Zhang, Bolin Wang, Xiang Zhao and Zhihong Tian PAGE: Progressive Anomaly Generation Network for Semi-supervised"&" Graph Anomaly Detection Ting Guo, Dongyu Pei, Gangzhu Qiao, Kaixuan Yao and Da Wang Cross-Type Semantic Alignment for Multi-Type Anomaly Detection in Heterogeneous Graphs Di Jin, Xiao Huang, Xiaobao Wang, Fengyu Yan, Luzhi Wang and Hongxiang Liang ") -> Unsupervised Subgraph Anomaly Detection based on Pattern Collaboration Sun Jiayang, Liu Shenghao, Deng Xianjun, Xiang Wei, Luo Meng, Zhang Qiankun and Zheng Dandan DP-DGAD: A Generalist Dynamic Graph Anomaly Detector with Dynamic Prototypes Jialun Zheng, Jie Liu, Jiannong Cao, Xiao Wang, Hanchen Yang and Yankai Chen Anomaly Detection of Interaction Behaviors in Streaming Graphs Shuai Ren, Fan Zhang, Bolin Wang, Xiang Zhao and Zhihong Tian PAGE: Progressive Anomaly Generation Network for Semi-supervised Graph Anomaly Detection Ting Guo, Dongyu Pei, Gangzhu Qiao, Kaixuan Yao and Da Wang Cross-Type Semantic Alignment for Multi-Type Anomaly Detection in Heterogeneous Graphs Di Jin, Xiao Huang, Xiaobao Wang, Fengyu Yan, Luzhi Wang and Hongxiang Liang | E24: =IFERROR(__xludf.DUMMYFUNCTION("TEXTJOIN(CHAR(10), TRUE,FILTER('Research assignment'!$D:$D,'Research assignment'!$F:$F=E22))"),"QuiZSF: A Retrieval-Augmented Framework for Zero-Shot Time Series Forecasting Shichao Ma, Zhengyang Zhou, Qihe Huang, Binwu Wang and Yang Wang SDR-CIR: Semantic Debias Retrieval Framework for Training-Free Zero-Shot Composed Image Retrieval Yi Sun, Jinyu"&" Xu, Qing Xie, Jiachen Li, Yanchun Ma and Yongjian Liu FlowRAG: Continual Learning for Dynamic Retriever in Retrieval-Augmented Generation Senlei Zhang, Tongjun Shi, Dandan Song, Luan Zhang, Shuhao Zhang, Xiaofei Liao and Hai Jin DA-RAG: Dynamic Attribu"&"ted Community Search for Retrieval-Augmented Generation Xingyuan Zeng, Zuohan Wu, Yue Wang, Chen Zhang, Quanming Yao, Libin Zheng and Jian Yin HyperRAG: Reasoning N-ary Facts over Hypergraphs for Retrieval Augmented Generation Wen-Sheng Lien, Yu-Kai Chan"&", Hao-Lung Hsiao, Bo-Kai Ruan, Meng-Fen Chiang, Chien-An Chen, Yi-Ren Yeh and Hong-Han Shuai ") -> QuiZSF: A Retrieval-Augmented Framework for Zero-Shot Time Series Forecasting Shichao Ma, Zhengyang Zhou, Qihe Huang, Binwu Wang and Yang Wang SDR-CIR: Semantic Debias Retrieval Framework for Training-Free Zero-Shot Composed Image Retrieval Yi Sun, Jinyu Xu, Qing Xie, Jiachen Li, Yanchun Ma and Yongjian Liu FlowRAG: Continual Learning for Dynamic Retriever in Retrieval-Augmented Generation Senlei Zhang, Tongjun Shi, Dandan Song, Luan Zhang, Shuhao Zhang, Xiaofei Liao and Hai Jin DA-RAG: Dynamic Attributed Community Search for Retrieval-Augmented Generation Xingyuan Zeng, Zuohan Wu, Yue Wang, Chen Zhang, Quanming Yao, Libin Zheng and Jian Yin HyperRAG: Reasoning N-ary Facts over Hypergraphs for Retrieval Augmented Generation Wen-Sheng Lien, Yu-Kai Chan, Hao-Lung Hsiao, Bo-Kai Ruan, Meng-Fen Chiang, Chien-An Chen, Yi-Ren Yeh and Hong-Han Shuai | F24: =IFERROR(__xludf.DUMMYFUNCTION("TEXTJOIN(CHAR(10), TRUE,FILTER('Research assignment'!$D:$D,'Research assignment'!$F:$F=F22))"),"Unifying Deductive and Abductive Reasoning in Knowledge Graphs with Masked Diffusion Model Yisen Gao, Jiaxin Bai, Yi Huang, Xingcheng Fu, Qingyun Sun and Yangqiu Song Are LLMs Stable Formal Logic Translators in Logical Reasoning Across Linguistically Div"&"ersified Texts? Qingchuan Li, Jiatong Li, Zirui Liu, Mingyue Cheng, Yitong Zhou, Yuting Zeng, Qi Liu and Tongxuan Liu Matrix as Plan: Structured Logical Reasoning with Feedback-Driven Replanning Ke Chen, Jiandian Zeng, Zihao Peng, Guo Li, Guangxue Zhang "&"and Tian Wang GraphCogent: Mitigating LLMs' Working Memory Constraints via Multi-Agent Collaboration in Complex Graph Understanding Rongzheng Wang, Shuang Liang, Qizhi Chen, Yihong Huang, Muquan Li, Yizhuo Ma, Dongyang Zhang, Ke Qin and Man-Fai Leung La"&"rge Language Model for OWL Proofs Hui Yang, Jiaoyan Chen and Uli Sattler ") -> Unifying Deductive and Abductive Reasoning in Knowledge Graphs with Masked Diffusion Model Yisen Gao, Jiaxin Bai, Yi Huang, Xingcheng Fu, Qingyun Sun and Yangqiu Song Are LLMs Stable Formal Logic Translators in Logical Reasoning Across Linguistically Diversified Texts? Qingchuan Li, Jiatong Li, Zirui Liu, Mingyue Cheng, Yitong Zhou, Yuting Zeng, Qi Liu and Tongxuan Liu Matrix as Plan: Structured Logical Reasoning with Feedback-Driven Replanning Ke Chen, Jiandian Zeng, Zihao Peng, Guo Li, Guangxue Zhang and Tian Wang GraphCogent: Mitigating LLMs' Working Memory Constraints via Multi-Agent Collaboration in Complex Graph Understanding Rongzheng Wang, Shuang Liang, Qizhi Chen, Yihong Huang, Muquan Li, Yizhuo Ma, Dongyang Zhang, Ke Qin and Man-Fai Leung Large Language Model for OWL Proofs Hui Yang, Jiaoyan Chen and Uli Sattler | G24: =IFERROR(__xludf.DUMMYFUNCTION("TEXTJOIN(CHAR(10), TRUE,FILTER('Research assignment'!$D:$D,'Research assignment'!$F:$F=G22))"),"Rhythm of Opinion: Interpretable Hawkes-Graph Networks for Hierarchical Opinion Propagation Yulong Li, Zhixiang Lu, Peixin Guo, Simin Lai, Yuxuan Zhang, Haochen Xue, Xiwei Liu, Yichen Li, Zhaodong Wu, Feilong Tang, Mian Zhou, Chong Li, Imran Razzak, Qingx"&"ia Li and Jionglong Su PolicySim: An LLM-Based Agent Social Simulation Sandbox for Proactive Policy Optimization Renhong Huang, Ning Tang, Jiarong Xu, Yuxuan Cao, Qingqian Tu, Sheng Guo, Bo Zheng, Huiyuan Liu and Yang Yang Tracing Belief-Driven Thoughts"&" with Theory-of-Mind Agents: An Opinion Analysis Framework Jintao Wen, Yunfeng Ning, Hankun Kang, Xin Miao and Tieyun Qian DREAMS: A Social Exchange Theory-Informed Modeling of Misinformation Engagement on Social Media Lin Tian and Marian-Andrei Rizoiu "&"Cross-Platform Narrative Prediction: Leveraging Platform-Invariant Discourse Networks Patrick Gerard, Luca Luceri, Leonardo Blas and Emilio Ferrara ") -> Rhythm of Opinion: Interpretable Hawkes-Graph Networks for Hierarchical Opinion Propagation Yulong Li, Zhixiang Lu, Peixin Guo, Simin Lai, Yuxuan Zhang, Haochen Xue, Xiwei Liu, Yichen Li, Zhaodong Wu, Feilong Tang, Mian Zhou, Chong Li, Imran Razzak, Qingxia Li and Jionglong Su PolicySim: An LLM-Based Agent Social Simulation Sandbox for Proactive Policy Optimization Renhong Huang, Ning Tang, Jiarong Xu, Yuxuan Cao, Qingqian Tu, Sheng Guo, Bo Zheng, Huiyuan Liu and Yang Yang Tracing Belief-Driven Thoughts with Theory-of-Mind Agents: An Opinion Analysis Framework Jintao Wen, Yunfeng Ning, Hankun Kang, Xin Miao and Tieyun Qian DREAMS: A Social Exchange Theory-Informed Modeling of Misinformation Engagement on Social Media Lin Tian and Marian-Andrei Rizoiu Cross-Platform Narrative Prediction: Leveraging Platform-Invariant Discourse Networks Patrick Gerard, Luca Luceri, Leonardo Blas and Emilio Ferrara | H24: =IFERROR(__xludf.DUMMYFUNCTION("TEXTJOIN(CHAR(10), TRUE,FILTER('Research assignment'!$D:$D,'Research assignment'!$F:$F=H22))"),"FedBridge: Accelerating Edge-Assisted Federated Learning for Model-Heterogeneous Clients Kaibin Wang, Qiang He, Zeqian Dong, Ziteng Wei, Caslon Chua, Feifei Chen, Hai Jin and Yun Yang WinFLoRA: Incentivizing Client-Adaptive Aggregation in Federated LoRA "&"under Privacy Heterogeneity Mengsha Kou, Xiaoyu Xia, Ziqi Wang, Ibrahim Khalil, Ruikun Luo, Jingwen Zhou and Minhui Xue Beyond Class Boundaries: Federated Visual Primitive Sharing with Text-Guided Adaptation Yongqiang Huang, Yingyu Chen, Tao Wang, Zexin "&"Lu, Zerui Shao, Beibei Li and Yi Zhang CoLOR-DP: Conjugate Low-Rank Differential Privacy for Structure-Aware LoRA Fine-Tuning Kai Zhang, Yuxuan Xu, Wenxiang Lin, Chaoqun Hong, Pei-Wei Tsai, Xin Yuan and Minhui Xue CA-PFL: Client-adaptive Parameter-effic"&"ient Fine-tuning for Personalized Federated Learning Daixin Song, Hui Cai, Haojie Zhang, Biyun Sheng, Jian Zhou, Mang Ye and Fu Xiao ") -> FedBridge: Accelerating Edge-Assisted Federated Learning for Model-Heterogeneous Clients Kaibin Wang, Qiang He, Zeqian Dong, Ziteng Wei, Caslon Chua, Feifei Chen, Hai Jin and Yun Yang WinFLoRA: Incentivizing Client-Adaptive Aggregation in Federated LoRA under Privacy Heterogeneity Mengsha Kou, Xiaoyu Xia, Ziqi Wang, Ibrahim Khalil, Ruikun Luo, Jingwen Zhou and Minhui Xue Beyond Class Boundaries: Federated Visual Primitive Sharing with Text-Guided Adaptation Yongqiang Huang, Yingyu Chen, Tao Wang, Zexin Lu, Zerui Shao, Beibei Li and Yi Zhang CoLOR-DP: Conjugate Low-Rank Differential Privacy for Structure-Aware LoRA Fine-Tuning Kai Zhang, Yuxuan Xu, Wenxiang Lin, Chaoqun Hong, Pei-Wei Tsai, Xin Yuan and Minhui Xue CA-PFL: Client-adaptive Parameter-efficient Fine-tuning for Personalized Federated Learning Daixin Song, Hui Cai, Haojie Zhang, Biyun Sheng, Jian Zhou, Mang Ye and Fu Xiao | I24: =IFERROR(__xludf.DUMMYFUNCTION("TEXTJOIN(CHAR(10), TRUE,FILTER('Research assignment'!$D:$D,'Research assignment'!$F:$F=I22))"),"Reading Between the Lines: Towards Reliable Black-box LLM Fingerprinting via Zeroth-order Gradient Estimation Shuo Shao, Yiming Li, Hongwei Yao, Yifei Chen, Yuchen Yang and Zhan Qin Forge: A Robust Multi-tab Website Fingerprinting Attack via Blind Source"&" Separation Yitan Huang, Wei Qiao, Ding Wang, Meng Shen, Di Zhao, Linxu Li, Susu Cui, Bo Jiang, Zhigang Lu and Baoxu Liu HiFi-WF: Toward Realistic Website Fingerprinting with Multi-tab and Subpage Recognition Songyang Wu, Chuan Ma, Ming Ding, Long Yuan, "&"Biwen Chen, Yuwen Qian and Tao Xiang RoFiRe: Robust Website Fingerprinting on Real-World Tor Traffic via Improved Augmentation and Normalization Haeseung Jeon, Sujin Kim, Nate Mathews, Hosung Kang and Se Eun Oh Understanding Server-side Commercial Finge"&"rprinting Elisa Luo, Tom Ritter, Stefan Savage and Geoffrey M Voelker ") -> Reading Between the Lines: Towards Reliable Black-box LLM Fingerprinting via Zeroth-order Gradient Estimation Shuo Shao, Yiming Li, Hongwei Yao, Yifei Chen, Yuchen Yang and Zhan Qin Forge: A Robust Multi-tab Website Fingerprinting Attack via Blind Source Separation Yitan Huang, Wei Qiao, Ding Wang, Meng Shen, Di Zhao, Linxu Li, Susu Cui, Bo Jiang, Zhigang Lu and Baoxu Liu HiFi-WF: Toward Realistic Website Fingerprinting with Multi-tab and Subpage Recognition Songyang Wu, Chuan Ma, Ming Ding, Long Yuan, Biwen Chen, Yuwen Qian and Tao Xiang RoFiRe: Robust Website Fingerprinting on Real-World Tor Traffic via Improved Augmentation and Normalization Haeseung Jeon, Sujin Kim, Nate Mathews, Hosung Kang and Se Eun Oh Understanding Server-side Commercial Fingerprinting Elisa Luo, Tom Ritter, Stefan Savage and Geoffrey M Voelker | J24: =IFERROR(__xludf.DUMMYFUNCTION("TEXTJOIN(CHAR(10), TRUE,FILTER('Research assignment'!$D:$D,'Research assignment'!$F:$F=J22))"),"A Frequency-Aware Mixture of Heterogeneous Experts Framework for Knowledge Tracing Youheng Bai, Mingliang Hou, Teng Guo, Zitao Liu and Weiqi Luo Efficient High-Dimensional Time Series Forecasting with Transformers: A Channel Reordering Perspective Yuchen"&" Fang, Shiyu Wang, Yuxuan Liang, Zhou Ye, Yang Xiang, Yan Zhao and Kai Zheng Modeling Point-to-Point Dependency for High-Dimensional Long-Term Series Forecasting Xinyu Li, Kexi Chen, Ying Zheng, Zhiyi Yao, Yi Xie, Jihan Dai, Lei Bai, Jin Zhao, Jiajie She"&"n, Yunqi Cai, Hong Lu and Xin Wang Time-TK: A Multi-Offset Temporal Interaction Framework Combining Transformer and Kolmogorov-Arnold Networks for Time Series Forecasting Fan Zhang, Shiming Fan and Hua Wang FedDis: A Causal Disentanglement Framework for"&" Federated Traffic Prediction Chengyang Zhou, Zijian Zhang, Chunxu Zhang, Hao Miao, Yulin Zhang, Kedi Lyu and Juncheng Hu ") -> A Frequency-Aware Mixture of Heterogeneous Experts Framework for Knowledge Tracing Youheng Bai, Mingliang Hou, Teng Guo, Zitao Liu and Weiqi Luo Efficient High-Dimensional Time Series Forecasting with Transformers: A Channel Reordering Perspective Yuchen Fang, Shiyu Wang, Yuxuan Liang, Zhou Ye, Yang Xiang, Yan Zhao and Kai Zheng Modeling Point-to-Point Dependency for High-Dimensional Long-Term Series Forecasting Xinyu Li, Kexi Chen, Ying Zheng, Zhiyi Yao, Yi Xie, Jihan Dai, Lei Bai, Jin Zhao, Jiajie Shen, Yunqi Cai, Hong Lu and Xin Wang Time-TK: A Multi-Offset Temporal Interaction Framework Combining Transformer and Kolmogorov-Arnold Networks for Time Series Forecasting Fan Zhang, Shiming Fan and Hua Wang FedDis: A Causal Disentanglement Framework for Federated Traffic Prediction Chengyang Zhou, Zijian Zhang, Chunxu Zhang, Hao Miao, Yulin Zhang, Kedi Lyu and Juncheng Hu | K24: =IFERROR(__xludf.DUMMYFUNCTION("TEXTJOIN(CHAR(10), TRUE,FILTER('Research assignment'!$D:$D,'Research assignment'!$F:$F=K22))"),"ThinkRec: Thinking-based recommendation via LLM Qihang Yu, Kairui Fu, Zheqi Lv, Shengyu Zhang, Xinhui Wu, Chen Lin, Feng Wei, Bo Zheng and Fei Wu Iterative Semantic Reasoning from Individual to Group Interests for Generative Recommendation with LLMs Xiao"&"fei Zhu, Jinfei Chen, Feiyang Yuan and Yang Zhou Reinforcement Learning-Constrained Segmented User Modeling with Large Language Models for Recommendation Yu Xia, Qing Tan, He Chen, Jingyu Chen and Qian Dong Multi-Task Multi-Behavior Sequential Recommend"&"ation Weihao Du, Ziran Deng, Weike Pan and Zhong Ming RMBRec: Robust Multi-Behavior Recommendation towards Target Behaviors Miaomiao Cai, Zhijie Zhang, Junfeng Fang, Zhiyong Cheng, Xiang Wang and Meng Wang ") -> ThinkRec: Thinking-based recommendation via LLM Qihang Yu, Kairui Fu, Zheqi Lv, Shengyu Zhang, Xinhui Wu, Chen Lin, Feng Wei, Bo Zheng and Fei Wu Iterative Semantic Reasoning from Individual to Group Interests for Generative Recommendation with LLMs Xiaofei Zhu, Jinfei Chen, Feiyang Yuan and Yang Zhou Reinforcement Learning-Constrained Segmented User Modeling with Large Language Models for Recommendation Yu Xia, Qing Tan, He Chen, Jingyu Chen and Qian Dong Multi-Task Multi-Behavior Sequential Recommendation Weihao Du, Ziran Deng, Weike Pan and Zhong Ming RMBRec: Robust Multi-Behavior Recommendation towards Target Behaviors Miaomiao Cai, Zhijie Zhang, Junfeng Fang, Zhiyong Cheng, Xiang Wang and Meng Wang | L24: =IFERROR(__xludf.DUMMYFUNCTION("TEXTJOIN(CHAR(10), TRUE,FILTER('Industry assignment'!$D:$D,'Industry assignment'!$F:$F=L22))"),"FRiskGPT: A Generative Foundation Model for Financial Risk Detection Zhongjian Zhang, Mengmei Zhang, Dehua Xu, Rongjun Shi, Jianfeng Liu, Fuli Meng, Huajian Xu, Xiao Wang, Ruijia Wang, Junze Chen, Minwei Tang and Chuan Shi VeritasFi: An Adaptable, Multi-"&"tiered RAG Framework for Multi-modal Financial Question Answering Zhenghan Tai, Hanwei Wu, Qingchen Hu, Jijun Chi, Hailin He, Lei Ding, Tung Sum Thomas Kwok, Bohuai Xiao, Yuchen Hua, Suyuchen Wang, Peng Lu, Muzhi Li, Yihong Wu, Liheng Ma, Jerry Huang, Jia"&"yi Zhang, Gonghao Zhang, Chaolong Jiang, Jingrui Tian, Sicheng Lyu, Zeyu Li, Boyu Han, Fengran Mo, Xinyue Yu, Yufei Cui, Ling Zhou and Xinyu Wang When Agents Trade: Live Multi-Market Trading Arena for LLM Agents Lingfei Qian, Xueqing Peng, Hanley Smith, "&"Yi Han, Yueru He, Haohang Li, Yupeng Cao, Yangyang Yu, Guojun Xiong, Peng Lu, Yan Wang, Vincent Jim Zhang, Huan He, Alejandro Lopez-Lira, Jimin Huang, Jian-Yun Nie and Sophia Ananiadou Financial Wind Tunnel: A Retrieval-Augmented Market Simulator Bokai C"&"ao, Xueyuan Lin, Yiyan Qi, Chengjin Xu, Cehao Yang and Jian Guo FishFlow: A LLM-Empowered Dynamic Pricing Framework for Online Fleamarket Platform Kakam Chong, Xu Yan, Shuai Xiao, Ming Chen, Chen Ju, Fei Huang, Yuantao Gu, Shuguang Han and Jufeng Chen ") -> FRiskGPT: A Generative Foundation Model for Financial Risk Detection Zhongjian Zhang, Mengmei Zhang, Dehua Xu, Rongjun Shi, Jianfeng Liu, Fuli Meng, Huajian Xu, Xiao Wang, Ruijia Wang, Junze Chen, Minwei Tang and Chuan Shi VeritasFi: An Adaptable, Multi-tiered RAG Framework for Multi-modal Financial Question Answering Zhenghan Tai, Hanwei Wu, Qingchen Hu, Jijun Chi, Hailin He, Lei Ding, Tung Sum Thomas Kwok, Bohuai Xiao, Yuchen Hua, Suyuchen Wang, Peng Lu, Muzhi Li, Yihong Wu, Liheng Ma, Jerry Huang, Jiayi Zhang, Gonghao Zhang, Chaolong Jiang, Jingrui Tian, Sicheng Lyu, Zeyu Li, Boyu Han, Fengran Mo, Xinyue Yu, Yufei Cui, Ling Zhou and Xinyu Wang When Agents Trade: Live Multi-Market Trading Arena for LLM Agents Lingfei Qian, Xueqing Peng, Hanley Smith, Yi Han, Yueru He, Haohang Li, Yupeng Cao, Yangyang Yu, Guojun Xiong, Peng Lu, Yan Wang, Vincent Jim Zhang, Huan He, Alejandro Lopez-Lira, Jimin Huang, Jian-Yun Nie and Sophia Ananiadou Financial Wind Tunnel: A Retrieval-Augmented Market Simulator Bokai Cao, Xueyuan Lin, Yiyan Qi, Chengjin Xu, Cehao Yang and Jian Guo FishFlow: A LLM-Empowered Dynamic Pricing Framework for Online Fleamarket Platform Kakam Chong, Xu Yan, Shuai Xiao, Ming Chen, Chen Ju, Fei Huang, Yuantao Gu, Shuguang Han and Jufeng Chen | M24: =IFERROR(__xludf.DUMMYFUNCTION("TEXTJOIN(CHAR(10), TRUE,FILTER('Industry assignment'!$D:$D,'Industry assignment'!$F:$F=M22))"),"Hierarchical Semantic RL: Tackling the Problem of Dynamic Action Space for RL-based Recommendations Minmao Wang, Xingchen Liu, Shijie Yi, Likang Wu, Hongke Zhao, Fei Pan, Qingpeng Cai and Peng Jiang Beyond the Flat Sequence: Hierarchical and Preference-A"&"ware Generative Recommendations Zerui Chen, Heng Chang, Tianying Liu, Chuantian Zhou, Yi Cao, Jiandong Ding, Ming Liu and Bing Qin NEZHA: A Zero-sacrifice and Hyperspeed Decoding Architecture for Generative Recommendations Yejing Wang, Shengyu Zhou, Jiny"&"u Lu, Ziwei Liu, Langming Liu, Maolin Wang, Wenlin Zhang, Feng Li, Wenbo Su, Pengjie Wang, Jian Xu and Xiangyu Zhao OneTrans: Unified Feature Interaction and Sequence Modeling with One Transformer in Industrial Recommender Zhaoqi Zhang, Haolei Pei, Jun G"&"uo, Tianyu Wang, Yufei Feng, Hui Sun, Shaowei Liu and Aixin Sun GRADE: Personalized Multi-Task Fusion via Group-Relative Reinforcement Learning with Adaptive Dirichlet Exploration Tingfeng Hong, Pingye Ren, Xinlong Xiao, Chao Wang, Chenyi Lei, Wenwu Ou a"&"nd Han Li ") -> Hierarchical Semantic RL: Tackling the Problem of Dynamic Action Space for RL-based Recommendations Minmao Wang, Xingchen Liu, Shijie Yi, Likang Wu, Hongke Zhao, Fei Pan, Qingpeng Cai and Peng Jiang Beyond the Flat Sequence: Hierarchical and Preference-Aware Generative Recommendations Zerui Chen, Heng Chang, Tianying Liu, Chuantian Zhou, Yi Cao, Jiandong Ding, Ming Liu and Bing Qin NEZHA: A Zero-sacrifice and Hyperspeed Decoding Architecture for Generative Recommendations Yejing Wang, Shengyu Zhou, Jinyu Lu, Ziwei Liu, Langming Liu, Maolin Wang, Wenlin Zhang, Feng Li, Wenbo Su, Pengjie Wang, Jian Xu and Xiangyu Zhao OneTrans: Unified Feature Interaction and Sequence Modeling with One Transformer in Industrial Recommender Zhaoqi Zhang, Haolei Pei, Jun Guo, Tianyu Wang, Yufei Feng, Hui Sun, Shaowei Liu and Aixin Sun GRADE: Personalized Multi-Task Fusion via Group-Relative Reinforcement Learning with Adaptive Dirichlet Exploration Tingfeng Hong, Pingye Ren, Xinlong Xiao, Chao Wang, Chenyi Lei, Wenwu Ou and Han Li | N24: =IFERROR(__xludf.DUMMYFUNCTION("TEXTJOIN(CHAR(10), TRUE,FILTER('HoW assignment'!$D:$D,'HoW assignment'!$F:$F=N22))"),"Welcome by History of Web Chairs Wendy Hall and Oshani Seneviratne Seoul Test of Time Winner Presentation - LINE: Large-scale Information Network Embedding Jian Tang The Pendulum of Verbosity: The Evolution of Search from Blue Links to Agents Evgeniy Ga"&"brilovich ") -> Welcome by History of Web Chairs Wendy Hall and Oshani Seneviratne Seoul Test of Time Winner Presentation - LINE: Large-scale Information Network Embedding Jian Tang The Pendulum of Verbosity: The Evolution of Search from Blue Links to Agents Evgeniy Gabrilovich
A25: 13:30 - 14:30 | B25: Posters and Demos Session 1
B26: Demos1 | C26: ShortPapers1 | D26: =IFERROR(__xludf.DUMMYFUNCTION("ARRAY_CONSTRAIN(TRANSPOSE(FILTER('All Counts'!B:B, RIGHT(TO_TEXT('All Counts'!B:B), 1)=""1"")), 1, 11)"),"EconPoster1") -> EconPoster1 | E26: =IFERROR(__xludf.DUMMYFUNCTION("""COMPUTED_VALUE"""),"GraphPoster1") -> GraphPoster1 | F26: =IFERROR(__xludf.DUMMYFUNCTION("""COMPUTED_VALUE"""),"SearchPoster1") -> SearchPoster1 | G26: =IFERROR(__xludf.DUMMYFUNCTION("""COMPUTED_VALUE"""),"SemanticsPoster1") -> SemanticsPoster1 | H26: =IFERROR(__xludf.DUMMYFUNCTION("""COMPUTED_VALUE"""),"SecurityPoster1") -> SecurityPoster1 | I26: =IFERROR(__xludf.DUMMYFUNCTION("""COMPUTED_VALUE"""),"SocialPoster1") -> SocialPoster1 | J26: =IFERROR(__xludf.DUMMYFUNCTION("""COMPUTED_VALUE"""),"SystemsPoster1") -> SystemsPoster1 | K26: =IFERROR(__xludf.DUMMYFUNCTION("""COMPUTED_VALUE"""),"RecSysPoster1") -> RecSysPoster1 | L26: =IFERROR(__xludf.DUMMYFUNCTION("""COMPUTED_VALUE"""),"MiningPoster1") -> MiningPoster1 | M26: =IFERROR(__xludf.DUMMYFUNCTION("""COMPUTED_VALUE"""),"IndustryPoster1") -> IndustryPoster1 | N26: =IFERROR(__xludf.DUMMYFUNCTION("""COMPUTED_VALUE"""),"Web4GoodPoster1") -> Web4GoodPoster1
B27: =IFERROR(__xludf.DUMMYFUNCTION("TEXTJOIN(CHAR(10), TRUE,FILTER(Demos!$D:$D,Demos!$E:$E=B26))"),"STIndex: A Context-Aware Multi-Dimensional Spatiotemporal Information Extraction System Wenxiao Zhang, Yu Liu, Qiang Sun, Yihao Ding, Sirui Li, Yanbing Liu, Jin B. Hong and Wei Liu SJBP: A Platform to Launch a Novel Jailbreak Attack on Large Language Mod"&"els Based on Content's Spatial Distribution Zhiyi Mou, Zeheng Qian, Tianfang Xiao, Wangze Ni, Weijie Sun, Lei Chen, Zhan Qin, Peng Cheng and Kui Ren Pattern Discovery with Wide-Lens Analysis and Sharp-Focus Validation Li Liu, Omar Alonso and Giorgio Ball"&"ardin DualMind: Towards Understanding Cognitive-Affective Cascades in Public Opinion Dissemination via Multi-Agent Simulation Enhao Huang, Tongtong Pan, Shuhuai Zhang, Qishu Jin, Liheng Zheng, Kaichun Hu, Yiming Li, Zhan Qin and Kui Ren RISE: A Retrieva"&"l-Augmented Generation Enhanced Immersive System for Education Guo Chen, Haowei Tang, Yan Wei, Yuming Wang, Haoyang Zhang, Yikang Hou, Maolin Zheng and Junjie Huang PromptX: A Cognitive Agent Platform with Long-term Memory Binhao Wang, Jianglin Huang, Xi"&"ao Hu, Shan Jiang, Maolin Wang, Ching-Ho Yang, Jian Jiang, Junhao Ye, Yaozu Cen, Rui Zeng, Yingtong Zhou, Yingjie Luo, Guanjie Wu, Wangzhong Xu, Feiyu Zhou and Xiangyu Zhao TrustResearcher: Automating Knowledge-Grounded and Transparent Research Ideation "&"with Multi-Agent Collaboration Jiawei Zhou, Ruicheng Zhu, Mengshi Chen, Jianwei Wang and Kai Wang Multimodal Peer Review Simulation with Actionable To-Do Recommendations for Community-Aware Manuscript Revisions Mengze Hong, Di Jiang, Weiwei Zhao, Yawen L"&"i, Yihang Wang, Xinyuan Luo, Yanjie Sun and Chen Jason Zhang ") -> STIndex: A Context-Aware Multi-Dimensional Spatiotemporal Information Extraction System Wenxiao Zhang, Yu Liu, Qiang Sun, Yihao Ding, Sirui Li, Yanbing Liu, Jin B. Hong and Wei Liu SJBP: A Platform to Launch a Novel Jailbreak Attack on Large Language Models Based on Content's Spatial Distribution Zhiyi Mou, Zeheng Qian, Tianfang Xiao, Wangze Ni, Weijie Sun, Lei Chen, Zhan Qin, Peng Cheng and Kui Ren Pattern Discovery with Wide-Lens Analysis and Sharp-Focus Validation Li Liu, Omar Alonso and Giorgio Ballardin DualMind: Towards Understanding Cognitive-Affective Cascades in Public Opinion Dissemination via Multi-Agent Simulation Enhao Huang, Tongtong Pan, Shuhuai Zhang, Qishu Jin, Liheng Zheng, Kaichun Hu, Yiming Li, Zhan Qin and Kui Ren RISE: A Retrieval-Augmented Generation Enhanced Immersive System for Education Guo Chen, Haowei Tang, Yan Wei, Yuming Wang, Haoyang Zhang, Yikang Hou, Maolin Zheng and Junjie Huang PromptX: A Cognitive Agent Platform with Long-term Memory Binhao Wang, Jianglin Huang, Xiao Hu, Shan Jiang, Maolin Wang, Ching-Ho Yang, Jian Jiang, Junhao Ye, Yaozu Cen, Rui Zeng, Yingtong Zhou, Yingjie Luo, Guanjie Wu, Wangzhong Xu, Feiyu Zhou and Xiangyu Zhao TrustResearcher: Automating Knowledge-Grounded and Transparent Research Ideation with Multi-Agent Collaboration Jiawei Zhou, Ruicheng Zhu, Mengshi Chen, Jianwei Wang and Kai Wang Multimodal Peer Review Simulation with Actionable To-Do Recommendations for Community-Aware Manuscript Revisions Mengze Hong, Di Jiang, Weiwei Zhao, Yawen Li, Yihang Wang, Xinyuan Luo, Yanjie Sun and Chen Jason Zhang | C27: =IFERROR(__xludf.DUMMYFUNCTION("TEXTJOIN(CHAR(10), TRUE,FILTER('ShortPapers assignment'!$D:$D,'ShortPapers assignment'!$E:$E=C26))"),"DOS: Dual-Flow Orthogonal Semantic IDs for Recommendation in Meituan Junwei Yin, Senjie Kou, Changhao Li, Shuli Wang, Yinqiu Huang, Xue Wei, Yinhua Zhu, Haitao Wang and Xingxing Wang RASTP: Representation-Aware Semantic Token Pruning for Generative Recom"&"mendation with Semantic Identifiers Tianyu Zhan, Kairui Fu, Zheqi Lv and Shengyu Zhang Few-shot and Zero-shot Audience Expansion with User and Task Model Pre-training on Tabular Data Siwei Qiang, Pengyu Li, Zhe Yu, Mengyao Sun, Jun Chen and Bo Zheng Lea"&"rning To Generate Effective Health Advertisements Yuval Saadaty and Elad Yom-Tov Decentralized in Name Only: The Centralization of DAO Labor Lingling Zhang, Morteza Zihayat and Ebrahim Bagheri A Reinforcement Learning Based Hyper-Parameter Generation Sy"&"stem Guided by LLM-Powered Virtual Users Changlin Qiu, Bang Lin, Tao Zhang and Chengfu Huo DualGR: Generative Retrieval with Long and Short-Term Interests Modeling Zhongchao Yi, Kai Feng, Xiaojian Ma, Yalong Wang, Yongqi Liu, Han Li, Zhengyang Zhou and Y"&"ang Wang Cascaded Verification Framework: A Progressive Approach for Mitigating Hallucinations in Large Language Models Shu Zhou, Yufei Song, Jinman Leng, Xin Wang, Tao Fan and Hao Wang Hidden-in-Plain-Text: A Benchmark for Social-Web Indirect Prompt In"&"jection in RAG Haoze Guo and Ziqi Wei Activation Caching for Retrieval-Augmented Generation Shu Zhou, Yufei Song, Jinman Leng, Xin Wang, Tao Fan and Hao Wang PH-EMO: Decoding Emotions from the Brain Inward – EEG-Grounded Multimodal Reasoning with LLMs K"&"ehong Liu, Yang Liu and Jiming Liu GPR: Empowering Generation with Graph-Pretrained Retriever Xiaochen Wang, Zongyu Wu, Yuan Zhong, Xiang Zhang, Suhang Wang and Fenglong Ma Graph Discrete Prompt Optimization for Knowledge Graph Question Answering Wooyou"&"ng Kim, Haemin Jung, Byeongjin Kim, Suhyeon Kwon and Wooju Kim WITHDRAWN 1/29/26, email from chairs -- Exploring Latent Preference with Interest-Guided Collaborative Expansion for Multimodal Recommendation Jiuqiang Li and Hongjun Wang Improving the Accu"&"racy of Community Detection on Signed Networks via Community Refinement and Contrastive Learning Hyunuk Shin, Hojin Kim, Chanyoung Lee, Yeon-Chang Lee and David Yoon Suk Kang AIMER: Affective Intention-guided Multimodal Emotion Reasoner for Visual Emotio"&"n Analysis in Social Media Yubeen Lee, Shinyu Park, Jiwon Park and Eunil Park SIR-Teach: Student-Implicit Reward Teaching Haochen You and Baojing Liu Generative Retrieval for E‑commerce: Jointly Learning Embedding and Codebook with Same Product Cluster "&"Songtao Fang, Zihao Xu, Shaowei Wei, Jin Zhang and Zhuojun Wang Rethink Web Service Resilience in Space: A Radiation-Aware and Sustainable Transmission Solution Long Chen, Hao Fang, Yi Ching Chou, Haoyuan Zhao, Xiaoyi Fan, Zhe Chen, Hengzhi Wang and Jian"&"gchuan Liu Access Controlled Website Interaction for Agentic AI with Delegated Critical Tasks Sunyoung Kim and Hokeun Kim Infer As You Train: A Symmetric Paradigm of Masked Generative for Click-Through Rate Prediction Moyu Zhang, Yujun Jin, Yun Chen, Ji"&"nxin Hu, Yu Zhang and Xiaoyi Zeng Learning Probabilistic Distributions for CTR Uncertainty Biho Kim Structure Over Scale: Diagnosing Liquidity Fragility in Concentrated-Liquidity AMMs Qiangqiang Liu, Runfa Jiang, Qian Huang, Frank Fan, Kunpeng Ren and W"&"ei Cai Fedivertex: a Graph Dataset based on Decentralized Social Media Marc Damie and Edwige Cyffers Cost Ratio Aware Algorithm for Representative Subset Selection Tong Cheng and Xueyan Tang ") -> DOS: Dual-Flow Orthogonal Semantic IDs for Recommendation in Meituan Junwei Yin, Senjie Kou, Changhao Li, Shuli Wang, Yinqiu Huang, Xue Wei, Yinhua Zhu, Haitao Wang and Xingxing Wang RASTP: Representation-Aware Semantic Token Pruning for Generative Recommendation with Semantic Identifiers Tianyu Zhan, Kairui Fu, Zheqi Lv and Shengyu Zhang Few-shot and Zero-shot Audience Expansion with User and Task Model Pre-training on Tabular Data Siwei Qiang, Pengyu Li, Zhe Yu, Mengyao Sun, Jun Chen and Bo Zheng Learning To Generate Effective Health Advertisements Yuval Saadaty and Elad Yom-Tov Decentralized in Name Only: The Centralization of DAO Labor Lingling Zhang, Morteza Zihayat and Ebrahim Bagheri A Reinforcement Learning Based Hyper-Parameter Generation System Guided by LLM-Powered Virtual Users Changlin Qiu, Bang Lin, Tao Zhang and Chengfu Huo DualGR: Generative Retrieval with Long and Short-Term Interests Modeling Zhongchao Yi, Kai Feng, Xiaojian Ma, Yalong Wang, Yongqi Liu, Han Li, Zhengyang Zhou and Yang Wang Cascaded Verification Framework: A Progressive Approach for Mitigating Hallucinations in Large Language Models Shu Zhou, Yufei Song, Jinman Leng, Xin Wang, Tao Fan and Hao Wang Hidden-in-Plain-Text: A Benchmark for Social-Web Indirect Prompt Injection in RAG Haoze Guo and Ziqi Wei Activation Caching for Retrieval-Augmented Generation Shu Zhou, Yufei Song, Jinman Leng, Xin Wang, Tao Fan and Hao Wang PH-EMO: Decoding Emotions from the Brain Inward – EEG-Grounded Multimodal Reasoning with LLMs Kehong Liu, Yang Liu and Jiming Liu GPR: Empowering Generation with Graph-Pretrained Retriever Xiaochen Wang, Zongyu Wu, Yuan Zhong, Xiang Zhang, Suhang Wang and Fenglong Ma Graph Discrete Prompt Optimization for Knowledge Graph Question Answering Wooyoung Kim, Haemin Jung, Byeongjin Kim, Suhyeon Kwon and Wooju Kim WITHDRAWN 1/29/26, email from chairs -- Exploring Latent Preference with Interest-Guided Collaborative Expansion for Multimodal Recommendation Jiuqiang Li and Hongjun Wang Improving the Accuracy of Community Detection on Signed Networks via Community Refinement and Contrastive Learning Hyunuk Shin, Hojin Kim, Chanyoung Lee, Yeon-Chang Lee and David Yoon Suk Kang AIMER: Affective Intention-guided Multimodal Emotion Reasoner for Visual Emotion Analysis in Social Media Yubeen Lee, Shinyu Park, Jiwon Park and Eunil Park SIR-Teach: Student-Implicit Reward Teaching Haochen You and Baojing Liu Generative Retrieval for E‑commerce: Jointly Learning Embedding and Codebook with Same Product Cluster Songtao Fang, Zihao Xu, Shaowei Wei, Jin Zhang and Zhuojun Wang Rethink Web Service Resilience in Space: A Radiation-Aware and Sustainable Transmission Solution Long Chen, Hao Fang, Yi Ching Chou, Haoyuan Zhao, Xiaoyi Fan, Zhe Chen, Hengzhi Wang and Jiangchuan Liu Access Controlled Website Interaction for Agentic AI with Delegated Critical Tasks Sunyoung Kim and Hokeun Kim Infer As You Train: A Symmetric Paradigm of Masked Generative for Click-Through Rate Prediction Moyu Zhang, Yujun Jin, Yun Chen, Jinxin Hu, Yu Zhang and Xiaoyi Zeng Learning Probabilistic Distributions for CTR Uncertainty Biho Kim Structure Over Scale: Diagnosing Liquidity Fragility in Concentrated-Liquidity AMMs Qiangqiang Liu, Runfa Jiang, Qian Huang, Frank Fan, Kunpeng Ren and Wei Cai Fedivertex: a Graph Dataset based on Decentralized Social Media Marc Damie and Edwige Cyffers Cost Ratio Aware Algorithm for Representative Subset Selection Tong Cheng and Xueyan Tang | D27: =IFERROR(__xludf.DUMMYFUNCTION("TEXTJOIN(CHAR(10), TRUE,FILTER('Research assignment'!$D:$D,'Research assignment'!$G:$G=D26))"),"Deterring A Small Collusion is All You Need Yotam Gafni Analysis of CEX-DEX Arbitrage Opportunities with Hidden Markov Models Bence Ladóczki LiquidityPool: Game-Theoretic Analysis of Stakeholder Revenue in Ranking-Dependent DeFi Qinde Chen, Huawei Huang"&" and Jian Zheng Allocating Chores with Restricted Additive Costs: Achieving EFX, MMS, and Efficiency Simultaneously Zehan Lin, Xiaowei Wu and Shengwei Zhou All-but-one MMS Allocation for Chores Jiawei Qiu, Xiaowei Wu, Cong Zhang and Shengwei Zhou Barte"&"r Exchange with Asymmetric Item Valuations Juan Luque, Sharmila Duppala, Michael Curry, John Dickerson and Aravind Srinivasan ") -> Deterring A Small Collusion is All You Need Yotam Gafni Analysis of CEX-DEX Arbitrage Opportunities with Hidden Markov Models Bence Ladóczki LiquidityPool: Game-Theoretic Analysis of Stakeholder Revenue in Ranking-Dependent DeFi Qinde Chen, Huawei Huang and Jian Zheng Allocating Chores with Restricted Additive Costs: Achieving EFX, MMS, and Efficiency Simultaneously Zehan Lin, Xiaowei Wu and Shengwei Zhou All-but-one MMS Allocation for Chores Jiawei Qiu, Xiaowei Wu, Cong Zhang and Shengwei Zhou Barter Exchange with Asymmetric Item Valuations Juan Luque, Sharmila Duppala, Michael Curry, John Dickerson and Aravind Srinivasan | E27: =IFERROR(__xludf.DUMMYFUNCTION("TEXTJOIN(CHAR(10), TRUE,FILTER('Research assignment'!$D:$D,'Research assignment'!$G:$G=E26))"),"Difference-based Sample Selection for Federated Graph Rationalization Linan Yue and Weibo Gao Class-Domain Incremental Learning on Graphs via Disentangled Knowledge Distillation Qin Tian, Chen Zhao, Xintao Wu, Dong Li, Minglai Shao, Xujiang Zhao and Wenj"&"un Wang Exploring Sequential Dynamics on Temporal Graphs via Composite Filtering Yuanyuan Xu, Danni Wu, Xuemin Lin, Dong Wen, Wenjie Zhang, Lei Chen and Ying Zhang Maximum Edge-based Quasi-Clique: Novel Iterative Frameworks Hongbo Xia, Shengxin Liu and "&"Zhaoquan Gu Scalable and Provable Biclique-Preserving Clustering: The Power of Counting-based Approaches Longlong Lin, Zeli Wang, Rong-Hua Li, Xiaohai Dai, Li Ni and Jin Zhao Graph Diffusion Evolution Model for Multi-Conditional Molecular Generation Xin"&"gcheng Fu, Lingyun Liu, Yisen Gao, Tianyu Chen, Qingyun Sun, Jianxin Li and Xianxian Li Integrated Mixture of Neighborhood and Community Experts for Graph-Based Fraud Detection Zhizhi Yu, Di Jin, Dongxiao He, Wenhuan Lu and Jianguo Wei FeedGuard: Online"&" Critic-Guided Reinforcement Learning with Privacy-Preserving Feedback for Recommendation Mengying Zhu, Feiyue Chen, Lifan Jiang, Mengyuan Yang, Yangyang Wu, Guanjie Cheng and Xiaolin Zheng HomeRun: Performing Curveball Trades quasi in Streaming for Fast"&" Null Modeling of Graphs, Hypergraphs, and Binary Matrices Michelle Contreras-Catalan and Matteo Riondato ") -> Difference-based Sample Selection for Federated Graph Rationalization Linan Yue and Weibo Gao Class-Domain Incremental Learning on Graphs via Disentangled Knowledge Distillation Qin Tian, Chen Zhao, Xintao Wu, Dong Li, Minglai Shao, Xujiang Zhao and Wenjun Wang Exploring Sequential Dynamics on Temporal Graphs via Composite Filtering Yuanyuan Xu, Danni Wu, Xuemin Lin, Dong Wen, Wenjie Zhang, Lei Chen and Ying Zhang Maximum Edge-based Quasi-Clique: Novel Iterative Frameworks Hongbo Xia, Shengxin Liu and Zhaoquan Gu Scalable and Provable Biclique-Preserving Clustering: The Power of Counting-based Approaches Longlong Lin, Zeli Wang, Rong-Hua Li, Xiaohai Dai, Li Ni and Jin Zhao Graph Diffusion Evolution Model for Multi-Conditional Molecular Generation Xingcheng Fu, Lingyun Liu, Yisen Gao, Tianyu Chen, Qingyun Sun, Jianxin Li and Xianxian Li Integrated Mixture of Neighborhood and Community Experts for Graph-Based Fraud Detection Zhizhi Yu, Di Jin, Dongxiao He, Wenhuan Lu and Jianguo Wei FeedGuard: Online Critic-Guided Reinforcement Learning with Privacy-Preserving Feedback for Recommendation Mengying Zhu, Feiyue Chen, Lifan Jiang, Mengyuan Yang, Yangyang Wu, Guanjie Cheng and Xiaolin Zheng HomeRun: Performing Curveball Trades quasi in Streaming for Fast Null Modeling of Graphs, Hypergraphs, and Binary Matrices Michelle Contreras-Catalan and Matteo Riondato | F27: =IFERROR(__xludf.DUMMYFUNCTION("TEXTJOIN(CHAR(10), TRUE,FILTER('Research assignment'!$D:$D,'Research assignment'!$G:$G=F26))"),"What Should I Cite? A RAG Benchmark for Academic Citation Prediction Leqi Zheng, Jiajun Zhang, Canzhi Chen, Chaokun Wang, Hongwei Li, Yuying Li, Yaoxin Mao, Shannan Yan, Zixin Song, Zhiyuan Feng, Zhaolu Kang, Zirong Chen, Hang Zhang, Qiang Liu, Liang Wang"&" and Ziyang Liu Med-R$^2$: Crafting Trustworthy LLM Physicians via Retrieval and Reasoning of Evidence-Based Medicine Lu Keer, Zheng Liang, Da Pan, Shusen Zhang, Guosheng Dong, Huang Leng, Bin Cui, Zhonghai Wu and Wentao Zhang Generalized Pseudo-Relevan"&"ce Feedback Yiteng Tu, Weihang Su, Yujia Zhou, Yiqun Liu, Fen Lin, Qin Liu and Qingyao Ai Rethinking the Hidden Risk of Reranking: Achieving Risk-aware Reranking with Information Gain for RAG with LLMs Zhizhao Liu, Zhihua Wen, Zhiliang Tian, Zhen Huang, "&"Miaorong Zhu, Zimian Wei, Yifu Gao, Liang Ding and Dongsheng Li NeocorRAG: Less Irrelevant Information, More Explicit Evidence, and More Effective Recall via Evidence Chains Shiyao Peng, Qianhe Zheng, Zhuodi Hao, Zichen Tang, Rongjin Li, Qing Huang, Jiay"&"u Huang, Jiacheng Liu, Yifan Zhu and Haihong E Pedestrian-Centric Discriminative and Fine-grained Semantic Mining for Text-based Person Retrieval Yuheng Liang, Haipeng Chen, Yu Liu, Yingda Lyu and Xue Wang ") -> What Should I Cite? A RAG Benchmark for Academic Citation Prediction Leqi Zheng, Jiajun Zhang, Canzhi Chen, Chaokun Wang, Hongwei Li, Yuying Li, Yaoxin Mao, Shannan Yan, Zixin Song, Zhiyuan Feng, Zhaolu Kang, Zirong Chen, Hang Zhang, Qiang Liu, Liang Wang and Ziyang Liu Med-R$^2$: Crafting Trustworthy LLM Physicians via Retrieval and Reasoning of Evidence-Based Medicine Lu Keer, Zheng Liang, Da Pan, Shusen Zhang, Guosheng Dong, Huang Leng, Bin Cui, Zhonghai Wu and Wentao Zhang Generalized Pseudo-Relevance Feedback Yiteng Tu, Weihang Su, Yujia Zhou, Yiqun Liu, Fen Lin, Qin Liu and Qingyao Ai Rethinking the Hidden Risk of Reranking: Achieving Risk-aware Reranking with Information Gain for RAG with LLMs Zhizhao Liu, Zhihua Wen, Zhiliang Tian, Zhen Huang, Miaorong Zhu, Zimian Wei, Yifu Gao, Liang Ding and Dongsheng Li NeocorRAG: Less Irrelevant Information, More Explicit Evidence, and More Effective Recall via Evidence Chains Shiyao Peng, Qianhe Zheng, Zhuodi Hao, Zichen Tang, Rongjin Li, Qing Huang, Jiayu Huang, Jiacheng Liu, Yifan Zhu and Haihong E Pedestrian-Centric Discriminative and Fine-grained Semantic Mining for Text-based Person Retrieval Yuheng Liang, Haipeng Chen, Yu Liu, Yingda Lyu and Xue Wang | G27: =IFERROR(__xludf.DUMMYFUNCTION("TEXTJOIN(CHAR(10), TRUE,FILTER('Research assignment'!$D:$D,'Research assignment'!$G:$G=G26))"),"Bridging Expert Reasoning and LLM Detection: A Knowledge-Driven Framework for Malicious Packages Wenbo Guo, Shiwen Song, Jiaxun Guo, Zhengzi Xu, Chengwei Liu, Haoran Ou, Mengmeng Ge and Yang Liu HingeMem: Boundary Guided Long-Term Memory with Query Adapt"&"ive Retrieval for Scalable Dialogues Yijie Zhong, Yunfan Gao and Haofen Wang LHG: LLM-enhanced and Heterogeneous Graph-induced for Unsupervised Social Event Detection Zitai Qiu, Rongwei Xu, Congbo Ma, Shan Xue, Jian Yang, Guanfeng Liu, Quan Z. Sheng, Ami"&"n Beheshti and Jia Wu Decoding Web Memorization: A Semantic Membership Inference Attack on LLMs Zhiyao Wu, Zi Liang and Haibo Hu Bridging Semantic Understanding and Popularity Bias with LLMs Renqiang Luo, Dong Zhang, Yupeng Gao, Wen Shi, Mingliang Hou, "&"Jiaying Liu, Zhe Wang and Shuo Yu Simple-Sampling and Hard-Mixup with Prototypes to Rebalance Contrastive Learning for Text Classification Mengyu Li, Yonghao Liu, Fausto Giunchiglia, Ximing Li, Xiaoyue Feng and Renchu Guan Traceable Latent Variable Disc"&"overy Based on Multi-Agent Collaboration Huaming Du, Tao Hu, Yijie Huang, Yu Zhao, Guisong Liu, Tao Gu, Gang Kou and Carl Yang DyLogNet: A Dynamic Multi-Relational Graph Framework for Log Anomaly Detection Xudong Zhao, Xiaolong Xu, Haolong Xiang, Tong Ga"&"o, Lianyong Qi, Amin Beheshti, Xuyun Zhang and Wanchun Dou ") -> Bridging Expert Reasoning and LLM Detection: A Knowledge-Driven Framework for Malicious Packages Wenbo Guo, Shiwen Song, Jiaxun Guo, Zhengzi Xu, Chengwei Liu, Haoran Ou, Mengmeng Ge and Yang Liu HingeMem: Boundary Guided Long-Term Memory with Query Adaptive Retrieval for Scalable Dialogues Yijie Zhong, Yunfan Gao and Haofen Wang LHG: LLM-enhanced and Heterogeneous Graph-induced for Unsupervised Social Event Detection Zitai Qiu, Rongwei Xu, Congbo Ma, Shan Xue, Jian Yang, Guanfeng Liu, Quan Z. Sheng, Amin Beheshti and Jia Wu Decoding Web Memorization: A Semantic Membership Inference Attack on LLMs Zhiyao Wu, Zi Liang and Haibo Hu Bridging Semantic Understanding and Popularity Bias with LLMs Renqiang Luo, Dong Zhang, Yupeng Gao, Wen Shi, Mingliang Hou, Jiaying Liu, Zhe Wang and Shuo Yu Simple-Sampling and Hard-Mixup with Prototypes to Rebalance Contrastive Learning for Text Classification Mengyu Li, Yonghao Liu, Fausto Giunchiglia, Ximing Li, Xiaoyue Feng and Renchu Guan Traceable Latent Variable Discovery Based on Multi-Agent Collaboration Huaming Du, Tao Hu, Yijie Huang, Yu Zhao, Guisong Liu, Tao Gu, Gang Kou and Carl Yang DyLogNet: A Dynamic Multi-Relational Graph Framework for Log Anomaly Detection Xudong Zhao, Xiaolong Xu, Haolong Xiang, Tong Gao, Lianyong Qi, Amin Beheshti, Xuyun Zhang and Wanchun Dou | H27: =IFERROR(__xludf.DUMMYFUNCTION("TEXTJOIN(CHAR(10), TRUE,FILTER('Research assignment'!$D:$D,'Research assignment'!$G:$G=H26))"),"SIsomap: Secure Collaborative Manifold Learning with Reducing Communication Costs Peizhao Zhou, Xiaojie Guo, Pinzhi Chen, Ranyang Liu, Lihai Nie, Tong Li and Zheli Liu PrivSplit: A Lossless Method for Prompt Privacy in Distributed Parameter-Efficient Fin"&"e-Tuning Wujia Niu, Lan Zhang, Haoran Cheng and Shen Li TGNN: Enhancing Pixel Tracking Detection via LLM-driven Annotation and GAT-powered Structural Representation Shenping Xiong, Xutong Wang, Ze Jin, Xinyu Liu, Haoqiang Wang, Zhen Chen, Ru Tan and Qixu"&" Liu DiSCoQR: Diffusion-Driven Semantic Compression for Robust Image Steganography in Standard QR Codes Lijing Ren and Denghui Zhang Netting Phish in the IPFS Ocean: Real-Time Monitoring and Characterization of Decentralized Phishing Campaigns Anas Kast"&"antin, Leonhard Balduf, Onur Ascigil, Saidu Sokoto, Björn Scheuermann, Andrzej Duda, Michał Król and Maciej Korczyński FraudShield: Knowledge Graph Empowered Defense for LLMs against Fraud Attacks Naen Xu, Jinghuai Zhang, Ping He, Chunyi Zhou, Jun Wang, "&"Zhihui Fu, Tianyu Du, Zhaoxiang Wang and Shouling Ji HyperDetector: Advanced Persistent Threat Detection via Hypergraph Neural Networks with Enhanced Global Perception Ziyue Wu, Nan Wang, Jiqiang Liu, Hairong Dong and Xibin Zhao Privacy-Friendly Adaptat"&"ion of Vision Transformers for Communication and Latency-Efficient Private Inference Zhi Pang, Bo Feng, Meng Luo, Chenhao Liu, Shuwang Xu, Kai Zhao, Yadi Wu and Bo Zeng MGFFD-VLM: Multi-Granularity Prompt Learning for Face Forgery Detection with VLM Tao "&"Chen, Jingyi Zhang, Decheng Liu and Chunlei Peng ") -> SIsomap: Secure Collaborative Manifold Learning with Reducing Communication Costs Peizhao Zhou, Xiaojie Guo, Pinzhi Chen, Ranyang Liu, Lihai Nie, Tong Li and Zheli Liu PrivSplit: A Lossless Method for Prompt Privacy in Distributed Parameter-Efficient Fine-Tuning Wujia Niu, Lan Zhang, Haoran Cheng and Shen Li TGNN: Enhancing Pixel Tracking Detection via LLM-driven Annotation and GAT-powered Structural Representation Shenping Xiong, Xutong Wang, Ze Jin, Xinyu Liu, Haoqiang Wang, Zhen Chen, Ru Tan and Qixu Liu DiSCoQR: Diffusion-Driven Semantic Compression for Robust Image Steganography in Standard QR Codes Lijing Ren and Denghui Zhang Netting Phish in the IPFS Ocean: Real-Time Monitoring and Characterization of Decentralized Phishing Campaigns Anas Kastantin, Leonhard Balduf, Onur Ascigil, Saidu Sokoto, Björn Scheuermann, Andrzej Duda, Michał Król and Maciej Korczyński FraudShield: Knowledge Graph Empowered Defense for LLMs against Fraud Attacks Naen Xu, Jinghuai Zhang, Ping He, Chunyi Zhou, Jun Wang, Zhihui Fu, Tianyu Du, Zhaoxiang Wang and Shouling Ji HyperDetector: Advanced Persistent Threat Detection via Hypergraph Neural Networks with Enhanced Global Perception Ziyue Wu, Nan Wang, Jiqiang Liu, Hairong Dong and Xibin Zhao Privacy-Friendly Adaptation of Vision Transformers for Communication and Latency-Efficient Private Inference Zhi Pang, Bo Feng, Meng Luo, Chenhao Liu, Shuwang Xu, Kai Zhao, Yadi Wu and Bo Zeng MGFFD-VLM: Multi-Granularity Prompt Learning for Face Forgery Detection with VLM Tao Chen, Jingyi Zhang, Decheng Liu and Chunlei Peng | I27: =IFERROR(__xludf.DUMMYFUNCTION("TEXTJOIN(CHAR(10), TRUE,FILTER('Research assignment'!$D:$D,'Research assignment'!$G:$G=I26))"),"Collusion-Aware Set-level Learning Framework for Detecting Spamming Activities Yuli Liu The Devil Within, The Cure Without: Securing Locally Private Graph Learning under Poisoning Longzhu He, Peng Tang, Li Sun and Sen Su H-NeiFi: Non-Invasive and Consen"&"sus-Efficient Multi-Agent Opinion Guidance Shijun Guo, Haoran Xu, Yaming Yang, Ziyu Guan, Wei Zhao, Zhang Xinyi and Song Yishan FairGE: Fairness-Aware Graph Encoding in Incomplete Social Networks Renqiang Luo, Huafei Huang, Tao Tang, Jing Ren, Ziqi Xu, M"&"ingliang Hou, Enyan Dai and Feng Xia Explaining Synergistic Effects in Social Recommendations Yicong Li, Shan Jin, Qi Liu, Shuo Wang, Jiaying Liu, Shuo Yu, Qiang Zhang, Kuanjiu Zhou and Feng Xia Graph Adversarial Defense via Hilbert-Schmidt Independence"&" Criterion against Influence Maximization Attacks Yuxing Guo, Jianqing Liang, Kaixuan Yao, Zhihao Guo and Jiye Liang ") -> Collusion-Aware Set-level Learning Framework for Detecting Spamming Activities Yuli Liu The Devil Within, The Cure Without: Securing Locally Private Graph Learning under Poisoning Longzhu He, Peng Tang, Li Sun and Sen Su H-NeiFi: Non-Invasive and Consensus-Efficient Multi-Agent Opinion Guidance Shijun Guo, Haoran Xu, Yaming Yang, Ziyu Guan, Wei Zhao, Zhang Xinyi and Song Yishan FairGE: Fairness-Aware Graph Encoding in Incomplete Social Networks Renqiang Luo, Huafei Huang, Tao Tang, Jing Ren, Ziqi Xu, Mingliang Hou, Enyan Dai and Feng Xia Explaining Synergistic Effects in Social Recommendations Yicong Li, Shan Jin, Qi Liu, Shuo Wang, Jiaying Liu, Shuo Yu, Qiang Zhang, Kuanjiu Zhou and Feng Xia Graph Adversarial Defense via Hilbert-Schmidt Independence Criterion against Influence Maximization Attacks Yuxing Guo, Jianqing Liang, Kaixuan Yao, Zhihao Guo and Jiye Liang | J27: =IFERROR(__xludf.DUMMYFUNCTION("TEXTJOIN(CHAR(10), TRUE,FILTER('Research assignment'!$D:$D,'Research assignment'!$G:$G=J26))"),"Smaller but Better: ​​Plasticity-Preserving Continual Learning for Embedded AI​ Chenxin Mao, Haibo Liu, Zhenzhe Zheng, Fan Wu and Guihai Chen Macro-Micro Collaborative Learning for Logical Data Center Microservice Indicators Forecasting Mohan Gao, Zhemen"&"g Yu, Yang Luo, Lintao Ma, Yinbo Sun, Yuchen Fang and Xiaofeng Gao Task-Aware Cloud-End Offloading for Vision-Language Model Serving via Dynamic Modality-Specific Adapter Scheduling Zian Wang, Ziyi Wang, Jie Xing, Yaya Wei, Ziyan Zhong and Lanshan Zhang "&" SkyCL: Swift Continuous Learning with Kinship-Awareness for Multi-Drone Video Analytics under Drastic Drift Yuanzheng Tan, Qing Li, Jiaqi Cui, Jun Peng, Gareth Tyson, Zhenhui Yuan, Tingting Yang and Yong Jiang Meteor: High-Performance Control Message De"&"livery for Large-Scale Clouds Gongming Zhao, Baoqing Wang, Min Chen, Hongli Xu, Jiawei Liu, Xuwei Yang, Liguang Xie, Yongqiang Yang and Ying Xiong MASI: Memory-Adaptive Inference Framework for Spiking Neural Networks on Edge Devices Di Yu, Helin Zheng, C"&"hangze Lv, Xin Du, Linshan Jiang, Xiang Liu, Gang Pan and Shuiguang Deng FedRGL: Federated Riemannian Graph Learning in Mixed-Curvature Spaces with Ricci-Gated Convolution Haizhou Du, Haolin Wu, Zijie Zhu and Zicheng Shi MoE-LC: General-Purpose Lossless"&" Compression for Multi-modal Data via Entropy-Aware Multi-Experts Zeyi Lu, Xiaoxiao Ma, Yujun Huang, Minxiao Chen, Bin Chen and Shu-Tao Xia ") -> Smaller but Better: ​​Plasticity-Preserving Continual Learning for Embedded AI​ Chenxin Mao, Haibo Liu, Zhenzhe Zheng, Fan Wu and Guihai Chen Macro-Micro Collaborative Learning for Logical Data Center Microservice Indicators Forecasting Mohan Gao, Zhemeng Yu, Yang Luo, Lintao Ma, Yinbo Sun, Yuchen Fang and Xiaofeng Gao Task-Aware Cloud-End Offloading for Vision-Language Model Serving via Dynamic Modality-Specific Adapter Scheduling Zian Wang, Ziyi Wang, Jie Xing, Yaya Wei, Ziyan Zhong and Lanshan Zhang SkyCL: Swift Continuous Learning with Kinship-Awareness for Multi-Drone Video Analytics under Drastic Drift Yuanzheng Tan, Qing Li, Jiaqi Cui, Jun Peng, Gareth Tyson, Zhenhui Yuan, Tingting Yang and Yong Jiang Meteor: High-Performance Control Message Delivery for Large-Scale Clouds Gongming Zhao, Baoqing Wang, Min Chen, Hongli Xu, Jiawei Liu, Xuwei Yang, Liguang Xie, Yongqiang Yang and Ying Xiong MASI: Memory-Adaptive Inference Framework for Spiking Neural Networks on Edge Devices Di Yu, Helin Zheng, Changze Lv, Xin Du, Linshan Jiang, Xiang Liu, Gang Pan and Shuiguang Deng FedRGL: Federated Riemannian Graph Learning in Mixed-Curvature Spaces with Ricci-Gated Convolution Haizhou Du, Haolin Wu, Zijie Zhu and Zicheng Shi MoE-LC: General-Purpose Lossless Compression for Multi-modal Data via Entropy-Aware Multi-Experts Zeyi Lu, Xiaoxiao Ma, Yujun Huang, Minxiao Chen, Bin Chen and Shu-Tao Xia | K27: =IFERROR(__xludf.DUMMYFUNCTION("TEXTJOIN(CHAR(10), TRUE,FILTER('Research assignment'!$D:$D,'Research assignment'!$G:$G=K26))"),"Quantum-enhanced Representation Learning and Matching Learning for Recommendation Anchen Li and Elena Casiraghi From Entity Reliability to Clean Feedback: An Entity-Aware Denoising Framework Beyond Interaction-Level Signals Ze Liu, Xianquan Wang, Shuoche"&"n Liu, Jie Ma, Huibo Xu, Yupeng Han, Kai Zhang and Jun Zhou Thorki: Decoupling General and Personalized Knowledge with Collaborative Fusion for Personalized Federated Learning Qiang He, Rui Chen, Yicheng Liu, Sheng Zhong, Haipeng Dai, Feifei Chen, Hai Ji"&"n and Yun Yang Large Language Models-Enhanced Semantic Diffusion for User-Centric Recommendation Xian Mo, Yijun Hu and Jun Pang Not All Information Brings Benefits: Personalization-Driven Agent Debate for Conversational Recommendation Pengfei Zhang, Guo"&"jia An, Jin Huang, Yuhan Yang, Yang Yang and Jie Zou FairFS: Addressing Deep Feature Selection Biases for Recommender System Xianquan Wang, Zhaocheng Du, Jieming Zhu, Qinglin Jia, Zhenhua Dong and Kai Zhang Tail-Aware Data Augmentation for Long-Tail Seq"&"uential Recommendation Yizhou Dang, Zhifu Wei, Minhan Huang, Lianbo Ma, Jianzhe Zhao, Guibing Guo and Xingwei Wang Off-Policy Learning with Limited Supply Koichi Tanaka, Ren Kishimoto, Bushun Kawagishi, Yusuke Narita, Yasuo Yamamoto, Nobuyuki Shimizu and"&" Yuta Saito S2CDR: Smoothing-Sharpening Process Model for Cross-Domain Recommendation Xiaodong Li, Juwei Yue, Xinghua Zhang, Jiawei Sheng, Wenyuan Zhang, Taoyu Su, Zefeng Zhang and Tingwen Liu Multi-view Semantic Contrastive Alignment for Multimodal Rec"&"ommendation Jiuqiang Li and Hongjun Wang pFedDKS: Detached Knowledge Sharing for Personalized Federated Learning Haozhao Wang, Wenchao Xu, Jingzhi Wang, Yunfeng Fan, Xiaoquan Yi and Rui Zhang Adaptive Contrastive Learning in Sequential Recommendation ba"&"sed on Perturbation and Restoration Networks Yanbo Zhou, Bin Lü, Xu-Hua Yang, Xin-Li Xu and Boling Wang ") -> Quantum-enhanced Representation Learning and Matching Learning for Recommendation Anchen Li and Elena Casiraghi From Entity Reliability to Clean Feedback: An Entity-Aware Denoising Framework Beyond Interaction-Level Signals Ze Liu, Xianquan Wang, Shuochen Liu, Jie Ma, Huibo Xu, Yupeng Han, Kai Zhang and Jun Zhou Thorki: Decoupling General and Personalized Knowledge with Collaborative Fusion for Personalized Federated Learning Qiang He, Rui Chen, Yicheng Liu, Sheng Zhong, Haipeng Dai, Feifei Chen, Hai Jin and Yun Yang Large Language Models-Enhanced Semantic Diffusion for User-Centric Recommendation Xian Mo, Yijun Hu and Jun Pang Not All Information Brings Benefits: Personalization-Driven Agent Debate for Conversational Recommendation Pengfei Zhang, Guojia An, Jin Huang, Yuhan Yang, Yang Yang and Jie Zou FairFS: Addressing Deep Feature Selection Biases for Recommender System Xianquan Wang, Zhaocheng Du, Jieming Zhu, Qinglin Jia, Zhenhua Dong and Kai Zhang Tail-Aware Data Augmentation for Long-Tail Sequential Recommendation Yizhou Dang, Zhifu Wei, Minhan Huang, Lianbo Ma, Jianzhe Zhao, Guibing Guo and Xingwei Wang Off-Policy Learning with Limited Supply Koichi Tanaka, Ren Kishimoto, Bushun Kawagishi, Yusuke Narita, Yasuo Yamamoto, Nobuyuki Shimizu and Yuta Saito S2CDR: Smoothing-Sharpening Process Model for Cross-Domain Recommendation Xiaodong Li, Juwei Yue, Xinghua Zhang, Jiawei Sheng, Wenyuan Zhang, Taoyu Su, Zefeng Zhang and Tingwen Liu Multi-view Semantic Contrastive Alignment for Multimodal Recommendation Jiuqiang Li and Hongjun Wang pFedDKS: Detached Knowledge Sharing for Personalized Federated Learning Haozhao Wang, Wenchao Xu, Jingzhi Wang, Yunfeng Fan, Xiaoquan Yi and Rui Zhang Adaptive Contrastive Learning in Sequential Recommendation based on Perturbation and Restoration Networks Yanbo Zhou, Bin Lü, Xu-Hua Yang, Xin-Li Xu and Boling Wang | L27: =IFERROR(__xludf.DUMMYFUNCTION("TEXTJOIN(CHAR(10), TRUE,FILTER('Research assignment'!$D:$D,'Research assignment'!$G:$G=L26))"),"Cardinality is Not Enough: Super Host Detection via Segmented Cardinality Estimation Yilin Zhao, Jiawei Huang, Xianshi Su, Weihe Li, Xin Li, Yan Liu, Jiacheng Xie, Qichen Su, Jin Ye, Wanchun Jiang and Jianxin Wang Byte-token Enhanced Language Models for "&"Temporal Point Processes Analysis Quyu Kong, Yixuan Zhang, Yang Liu, Panrong Tong, Enqi Liu and Feng Zhou Dynamic Prototype-Augmented Stance Detection: Learning from the Seen to Reason about the Unseen Zhaodan Zhang, Jin Zhang and Jiafeng Guo Triple-R: "&"Iterative Query Rewriting and Refinement for Retrieval-Augmented Fake News Detection Jie Li, Jinrui Wang, Linmei Hu and Yuqiu Deng Expectation-Maximization Driven Contrastive Disentanglement for Generalized Category Discovery Weiyi Yang, Richong Zhang, J"&"unfan Chen, Jiawei Sheng and Lihong Wang KMLP: A Scalable Hybrid Architecture for Web-Scale Tabular Data Modeling Mingming Zhang, Pengfei Shi, Junbo Zhao, Ningtao Wang, Feng Zhao, Guandong Sun, Yulin Kang, Xing Fu, Zhiqing Xiao, Weiqiang Wang and Ruizhe "&"Gao Measuring and Enhancing Human Value Alignment in Zero-Shot Document-Level Claim Extraction Yuanzhen Hao and Desheng Wu ") -> Cardinality is Not Enough: Super Host Detection via Segmented Cardinality Estimation Yilin Zhao, Jiawei Huang, Xianshi Su, Weihe Li, Xin Li, Yan Liu, Jiacheng Xie, Qichen Su, Jin Ye, Wanchun Jiang and Jianxin Wang Byte-token Enhanced Language Models for Temporal Point Processes Analysis Quyu Kong, Yixuan Zhang, Yang Liu, Panrong Tong, Enqi Liu and Feng Zhou Dynamic Prototype-Augmented Stance Detection: Learning from the Seen to Reason about the Unseen Zhaodan Zhang, Jin Zhang and Jiafeng Guo Triple-R: Iterative Query Rewriting and Refinement for Retrieval-Augmented Fake News Detection Jie Li, Jinrui Wang, Linmei Hu and Yuqiu Deng Expectation-Maximization Driven Contrastive Disentanglement for Generalized Category Discovery Weiyi Yang, Richong Zhang, Junfan Chen, Jiawei Sheng and Lihong Wang KMLP: A Scalable Hybrid Architecture for Web-Scale Tabular Data Modeling Mingming Zhang, Pengfei Shi, Junbo Zhao, Ningtao Wang, Feng Zhao, Guandong Sun, Yulin Kang, Xing Fu, Zhiqing Xiao, Weiqiang Wang and Ruizhe Gao Measuring and Enhancing Human Value Alignment in Zero-Shot Document-Level Claim Extraction Yuanzhen Hao and Desheng Wu | M27: =IFERROR(__xludf.DUMMYFUNCTION("TEXTJOIN(CHAR(10), TRUE,FILTER('Industry assignment'!$D:$D,'Industry assignment'!$G:$G=M26))"),"OpenDigger: A Practical Framework for Assessing Community Health and Sustainability in Open Source Collaboration Platforms Wei Wang, Fanyu Han, Shengyu Zhao, Xuan Zhou, Weining Qian, Aoying Zhou, Xiaoya Xia, Liyun Yang, Rong Wang, Ning Jiang and Moming Du"&"an Bridging Visual Dynamics and Narrative Reasoning: Multimodal Large Language Models for Short Drama Quality Assessment Qingyang Liu, Jiangtong Li, Zelin Peng, Shaobo Wang, Zhaohe Liao, Shuochen Chang, Bingjie Gao, Haonan Zhao, Mu Liu, Jidong Jiang and "&"Li Niu Not All Candidates are Created Equal: A Heterogeneity-Aware Approach to Pre-ranking in Recommender Systems Pengfei Tong, Siyuan Chen, Chenwei Zhang, Bo Wang, Qi Pi, Pixun Li and Zuotao Liu Unbiased Multimodal Reranking for Long-Tail Short-Video S"&"earch Wenyi Xu, Feiran Zhu, Songyang Li, Renzhe Zhou, Chao Zhang, ChengLei Dai, Yuren Mao, Yunjun Gao and Yi Zhang ") -> OpenDigger: A Practical Framework for Assessing Community Health and Sustainability in Open Source Collaboration Platforms Wei Wang, Fanyu Han, Shengyu Zhao, Xuan Zhou, Weining Qian, Aoying Zhou, Xiaoya Xia, Liyun Yang, Rong Wang, Ning Jiang and Moming Duan Bridging Visual Dynamics and Narrative Reasoning: Multimodal Large Language Models for Short Drama Quality Assessment Qingyang Liu, Jiangtong Li, Zelin Peng, Shaobo Wang, Zhaohe Liao, Shuochen Chang, Bingjie Gao, Haonan Zhao, Mu Liu, Jidong Jiang and Li Niu Not All Candidates are Created Equal: A Heterogeneity-Aware Approach to Pre-ranking in Recommender Systems Pengfei Tong, Siyuan Chen, Chenwei Zhang, Bo Wang, Qi Pi, Pixun Li and Zuotao Liu Unbiased Multimodal Reranking for Long-Tail Short-Video Search Wenyi Xu, Feiran Zhu, Songyang Li, Renzhe Zhou, Chao Zhang, ChengLei Dai, Yuren Mao, Yunjun Gao and Yi Zhang | N27: =IFERROR(__xludf.DUMMYFUNCTION("TEXTJOIN(CHAR(10), TRUE,FILTER('Web4Good assignment'!$D:$D,'Web4Good assignment'!$G:$G=N26))"),"The Chatbot Knows It’s You: Dialogue Attribution in Unauthenticated Human–LLM Sessions Wenxuan Wang, Zirui Liu, Haoxuan Kou, Xuefeng Liu and Jiaxing Shen Toward Green Computing: General Carbon Intensity Forecasting via Dual Graph Empowered Time Series Fo"&"undation Model Xiaoyang Zhang, Taiqi Zhou, Fang He, Yang Deng and Dan Wang Egocentric Co-Pilot: Web-Native Smart-Glasses Agents for Assistive Egocentric AI Sicheng Yang, Yukai Huang, Weitong Cai, Shitong Sun, Fengyi Fang, You He, Yiqiao Xie, Jiankang Den"&"g, Hang Zhang, Jifei Song and Zhensong Zhang Green Industrial Engineering on the Web: Agent-Driven Ant Colony Optimization Tuning for Energy-Efficient 3D Pipe Routing Xuanhan Fan, Rui Ding, Haojie Liu, Jibin Zhou, Han Liu, Yuanman Li, Wei Wang and Mao Ye"&" Dynamic Min-Max Multi-Dimensional Reinforcement Backdoor Attacks and Orchestrated Closed-Loop Defense in Fairness-Aware Web Federated Finance Ruixiao Zhu, Kun Zhu, Nana Zhang, Qi Zhang and Changjun Jiang MultiHateLoc: Towards Temporal Localisation of M"&"ultimodal Hate Content in Online Videos Qiyue Sun, Tailin Chen, Yinghui Zhang, Yuchen Zhang, Jiangbei Yue, Jianbo Jiao and Zeyu Fu 'They've Stolen My GPL-Licensed Model!': Toward Standardized and Transparent Model Licensing Moming Duan, Rui Zhao, Linshan"&" Jiang, Nigel Shadbolt and Bingsheng He Community Fact-Checks Do Not Break Follower Loyalty Michelle Bobek and Nicolas Pröllochs Fair and Carbon-Aware LLM Routing for Web Services Tingting Li, Ziming Zhao, Zhaoxuan Li, Xiaofei Yue and Jiongchi Yu Towar"&"ds Fair Large Language Model-based Recommender Systems without Costly Retraining Jin Li, Huilin Gu, Shoujin Wang, Qi Zhang, Shui Yu, Chen Wang, Xiwei Xu and Fang Chen Enhancing Rare Event Detection via Counterfactual Generation with Exogenous Variables L"&"ili Tian, Dehui Du and Yikang Chen coTherapist: A Behavior-Aligned Small Language Model Framework to Support Mental Healthcare Experts Prottay Kumar Adhikary, Reena Rawat and Tanmoy Chakraborty Debating Truth: Debate-driven Claim Verification with Multi"&"ple Large Language Model Agents Haorui He, Yupeng Li, Dacheng Wen, Yang Chen, Reynold Cheng, Donglong Chen and Francis C. M. Lau Sustainable and Responsible ECG-Based AI Diagnostics: Masked Frequency Reconstruction with Peak-Aware Transformers Wei Wang, "&"Jian Chen, Junxin Chen, Zeling Xu, Yuntao Zou and Henry H. Y. Tong FairGU: Fairness-aware Graph Unlearning in Social Networks Renqiang Luo, Yongshuai Yang, Huafei Huang, Qing Qing, Mingliang Hou, Ziqi Xu, Yi Yu, Jingjing Zhou and Feng Xia ") -> The Chatbot Knows It’s You: Dialogue Attribution in Unauthenticated Human–LLM Sessions Wenxuan Wang, Zirui Liu, Haoxuan Kou, Xuefeng Liu and Jiaxing Shen Toward Green Computing: General Carbon Intensity Forecasting via Dual Graph Empowered Time Series Foundation Model Xiaoyang Zhang, Taiqi Zhou, Fang He, Yang Deng and Dan Wang Egocentric Co-Pilot: Web-Native Smart-Glasses Agents for Assistive Egocentric AI Sicheng Yang, Yukai Huang, Weitong Cai, Shitong Sun, Fengyi Fang, You He, Yiqiao Xie, Jiankang Deng, Hang Zhang, Jifei Song and Zhensong Zhang Green Industrial Engineering on the Web: Agent-Driven Ant Colony Optimization Tuning for Energy-Efficient 3D Pipe Routing Xuanhan Fan, Rui Ding, Haojie Liu, Jibin Zhou, Han Liu, Yuanman Li, Wei Wang and Mao Ye Dynamic Min-Max Multi-Dimensional Reinforcement Backdoor Attacks and Orchestrated Closed-Loop Defense in Fairness-Aware Web Federated Finance Ruixiao Zhu, Kun Zhu, Nana Zhang, Qi Zhang and Changjun Jiang MultiHateLoc: Towards Temporal Localisation of Multimodal Hate Content in Online Videos Qiyue Sun, Tailin Chen, Yinghui Zhang, Yuchen Zhang, Jiangbei Yue, Jianbo Jiao and Zeyu Fu 'They've Stolen My GPL-Licensed Model!': Toward Standardized and Transparent Model Licensing Moming Duan, Rui Zhao, Linshan Jiang, Nigel Shadbolt and Bingsheng He Community Fact-Checks Do Not Break Follower Loyalty Michelle Bobek and Nicolas Pröllochs Fair and Carbon-Aware LLM Routing for Web Services Tingting Li, Ziming Zhao, Zhaoxuan Li, Xiaofei Yue and Jiongchi Yu Towards Fair Large Language Model-based Recommender Systems without Costly Retraining Jin Li, Huilin Gu, Shoujin Wang, Qi Zhang, Shui Yu, Chen Wang, Xiwei Xu and Fang Chen Enhancing Rare Event Detection via Counterfactual Generation with Exogenous Variables Lili Tian, Dehui Du and Yikang Chen coTherapist: A Behavior-Aligned Small Language Model Framework to Support Mental Healthcare Experts Prottay Kumar Adhikary, Reena Rawat and Tanmoy Chakraborty Debating Truth: Debate-driven Claim Verification with Multiple Large Language Model Agents Haorui He, Yupeng Li, Dacheng Wen, Yang Chen, Reynold Cheng, Donglong Chen and Francis C. M. Lau Sustainable and Responsible ECG-Based AI Diagnostics: Masked Frequency Reconstruction with Peak-Aware Transformers Wei Wang, Jian Chen, Junxin Chen, Zeling Xu, Yuntao Zou and Henry H. Y. Tong FairGU: Fairness-aware Graph Unlearning in Social Networks Renqiang Luo, Yongshuai Yang, Huafei Huang, Qing Qing, Mingliang Hou, Ziqi Xu, Yi Yu, Jingjing Zhou and Feng Xia
A28: 14:30 - 15:30 | B28: Keynote #2: Mounia Lalmas
A29: 15:30 - 16:00 | B29: Break
A30: 16:00 - 17:30 | B30: Econ2 | C30: Graph2 | D30: Graph8 | E30: Search2 | F30: Semantics4 | G30: Social2 | H30: Systems2 | I30: Security4 | J30: Mining2 | K30: RecSys2 | L30: RecSys7 | M30: Industry3 | N30: History2
B31: =IFERROR(__xludf.DUMMYFUNCTION("TEXTJOIN(CHAR(10), TRUE,FILTER('Sessions Counts'!$B:$B,'Sessions Counts'!$A:$A=B30))"),"Auto-bidding and Budget Allocation in Online Advertising") -> Auto-bidding and Budget Allocation in Online Advertising | C31: =IFERROR(__xludf.DUMMYFUNCTION("TEXTJOIN(CHAR(10), TRUE,FILTER('Sessions Counts'!$B:$B,'Sessions Counts'!$A:$A=C30))"),"Attacks & Explainability") -> Attacks & Explainability | D31: =IFERROR(__xludf.DUMMYFUNCTION("TEXTJOIN(CHAR(10), TRUE,FILTER('Sessions Counts'!$B:$B,'Sessions Counts'!$A:$A=D30))"),"Dynamics and Temporal") -> Dynamics and Temporal | E31: =IFERROR(__xludf.DUMMYFUNCTION("TEXTJOIN(CHAR(10), TRUE,FILTER('Sessions Counts'!$B:$B,'Sessions Counts'!$A:$A=E30))"),"Agents & Reasoning") -> Agents & Reasoning | F31: =IFERROR(__xludf.DUMMYFUNCTION("TEXTJOIN(CHAR(10), TRUE,FILTER('Sessions Counts'!$B:$B,'Sessions Counts'!$A:$A=F30))"),"Knowledge Editing & Maintenance") -> Knowledge Editing & Maintenance | G31: =IFERROR(__xludf.DUMMYFUNCTION("TEXTJOIN(CHAR(10), TRUE,FILTER('Sessions Counts'!$B:$B,'Sessions Counts'!$A:$A=G30))"),"Information Diffusion and Influence") -> Information Diffusion and Influence | H31: =IFERROR(__xludf.DUMMYFUNCTION("TEXTJOIN(CHAR(10), TRUE,FILTER('Sessions Counts'!$B:$B,'Sessions Counts'!$A:$A=H30))"),"Efficient and Privacy-Aware Federated Learning") -> Efficient and Privacy-Aware Federated Learning | I31: =IFERROR(__xludf.DUMMYFUNCTION("TEXTJOIN(CHAR(10), TRUE,FILTER('Sessions Counts'!$B:$B,'Sessions Counts'!$A:$A=I30))"),"Security & Privacy for Federated Systems") -> Security & Privacy for Federated Systems | J31: =IFERROR(__xludf.DUMMYFUNCTION("TEXTJOIN(CHAR(10), TRUE,FILTER('Sessions Counts'!$B:$B,'Sessions Counts'!$A:$A=J30))"),"Multimodal Web Content Representation and Understanding") -> Multimodal Web Content Representation and Understanding | K31: =IFERROR(__xludf.DUMMYFUNCTION("TEXTJOIN(CHAR(10), TRUE,FILTER('Sessions Counts'!$B:$B,'Sessions Counts'!$A:$A=K30))"),"Cross-Domain Recommendation") -> Cross-Domain Recommendation | L31: =IFERROR(__xludf.DUMMYFUNCTION("TEXTJOIN(CHAR(10), TRUE,FILTER('Sessions Counts'!$B:$B,'Sessions Counts'!$A:$A=L30))"),"Causal & Counterfactual Recommendation") -> Causal & Counterfactual Recommendation | M31: =IFERROR(__xludf.DUMMYFUNCTION("TEXTJOIN(CHAR(10), TRUE,FILTER('Sessions Counts'!$B:$B,'Sessions Counts'!$A:$A=M30))"),"Core Recommendation & CTR Optimization") -> Core Recommendation & CTR Optimization
B32: =IFERROR(__xludf.DUMMYFUNCTION("TEXTJOIN(CHAR(10), TRUE,FILTER('Research assignment'!$D:$D,'Research assignment'!$F:$F=B30))"),"Auto-bidding under Return-on-Spend Constraints with Uncertainty Quantification Jiale Han, Chun Gan, Chengcheng Zhang, Jie He, Zhangang Lin, Ching Law and Xiaowu Dai DARA: Few-shot Budget Allocation in Online Advertising via In-Context Decision Making wit"&"h RL-Finetuned LLMs Mingxuan Song, Yusen Huo, Bohan Zhou, Shenglin Yin, Zhen Xiao, Jieyi Long, Zhilin Zhang and Chuan Yu LBM: Hierarchical Large Auto-Bidding Model via Reasoning and Acting Yewen Li, Zhiyi Lyu, Peng Jiang, Qingpeng Cai, Fei Pan, Bo An and"&" Peng Jiang Platform Competition in the Autobidding World Gagan Aggarwal, Andres Perlroth, Ariel Schvartzman Cohenca and Mingfei Zhao AHBid: An Adaptable Hierarchical Bidding Framework for Cross-Channel Advertising Xinxin Yang, Yangyang Tang, Yikun Zhou"&", Yaolei Liu, Yun Li and Bo Yang ") -> Auto-bidding under Return-on-Spend Constraints with Uncertainty Quantification Jiale Han, Chun Gan, Chengcheng Zhang, Jie He, Zhangang Lin, Ching Law and Xiaowu Dai DARA: Few-shot Budget Allocation in Online Advertising via In-Context Decision Making with RL-Finetuned LLMs Mingxuan Song, Yusen Huo, Bohan Zhou, Shenglin Yin, Zhen Xiao, Jieyi Long, Zhilin Zhang and Chuan Yu LBM: Hierarchical Large Auto-Bidding Model via Reasoning and Acting Yewen Li, Zhiyi Lyu, Peng Jiang, Qingpeng Cai, Fei Pan, Bo An and Peng Jiang Platform Competition in the Autobidding World Gagan Aggarwal, Andres Perlroth, Ariel Schvartzman Cohenca and Mingfei Zhao AHBid: An Adaptable Hierarchical Bidding Framework for Cross-Channel Advertising Xinxin Yang, Yangyang Tang, Yikun Zhou, Yaolei Liu, Yun Li and Bo Yang | C32: =IFERROR(__xludf.DUMMYFUNCTION("TEXTJOIN(CHAR(10), TRUE,FILTER('Research assignment'!$D:$D,'Research assignment'!$F:$F=C30))"),"Unveiling Backdoor Propagation in Graphs: Neuron-Centric Defense Mechanisms Di Jin, Bingdao Feng, Xiaobao Wang, Yuxiang Zhang, Zechuan Zhang, Liang Yang, Dongxiao He and Zhen Wang Identification of Influential Node Group in Attributed Graph through Expla"&"ining Graph Neural Network Xiao Tan, Tongtong Su, Jiayi Wu, Yan Zhang, Binghui Xu, Dian Shen, Meng Wang and Beilun Wang Can LLMs Fool Graph Learning? Exploring Universal Adversarial Attacks on Text-Attributed Graphs Zihui Chen, Yuling Wang, Pengfei Jiao,"&" Kai Wu, Xiao Wang, Xiang Ao and Dalin Zhang A^2GBD: Attack-Agnostic Graph Backdoor Defense Chenxu Du, Yang Liu, Xingtong Yu, Zhuoer Xu, Yang Liu and Tianrui Li Towards Robust Heterogeneous Graph Explanations under Structural Perturbations Yifan Lu, Pen"&"gfei Jiao, Xuan Guo, Ziyun Zou, Yiwei Wang, Mengzhou Gao, Huaming Wu and Imran Razzak ") -> Unveiling Backdoor Propagation in Graphs: Neuron-Centric Defense Mechanisms Di Jin, Bingdao Feng, Xiaobao Wang, Yuxiang Zhang, Zechuan Zhang, Liang Yang, Dongxiao He and Zhen Wang Identification of Influential Node Group in Attributed Graph through Explaining Graph Neural Network Xiao Tan, Tongtong Su, Jiayi Wu, Yan Zhang, Binghui Xu, Dian Shen, Meng Wang and Beilun Wang Can LLMs Fool Graph Learning? Exploring Universal Adversarial Attacks on Text-Attributed Graphs Zihui Chen, Yuling Wang, Pengfei Jiao, Kai Wu, Xiao Wang, Xiang Ao and Dalin Zhang A^2GBD: Attack-Agnostic Graph Backdoor Defense Chenxu Du, Yang Liu, Xingtong Yu, Zhuoer Xu, Yang Liu and Tianrui Li Towards Robust Heterogeneous Graph Explanations under Structural Perturbations Yifan Lu, Pengfei Jiao, Xuan Guo, Ziyun Zou, Yiwei Wang, Mengzhou Gao, Huaming Wu and Imran Razzak | D32: =IFERROR(__xludf.DUMMYFUNCTION("TEXTJOIN(CHAR(10), TRUE,FILTER('Research assignment'!$D:$D,'Research assignment'!$F:$F=D30))"),"Riemannian Liquid Spatio-Temporal Graph Network Liangsi Lu, Jingchao Wang, Zhaorong Dai, Hanqian Liu and Yang Shi Diffusion-based Kriging Model with Graph-enhanced Attention Mingtao Zhang, Guoli Yang, Zhanxing Zhu, Guangyin Jin, Mengzhu Wang and Xiaoying"&" Bai Graph Retention Networks for Dynamic Graphs Qian Chang, Xia Li, Xiufeng Cheng, Runsong Jia, Jinqing Yang, Guoping Hu and Ciprian Doru Giurcaneanu Network Dismantling via Reverse Dismantling: Static and Dynamic Algorithms Jinyu Duan, Sijin Wang, Fan"&" Zhang, Xiang Zhao, Wenjie Zhang and Zhihong Tian Zero-Shot Forecasting of Network Dynamics through Weight Flow Matching Shihe Zhou, Ruikun Li, Huandong Wang and Yong Li ") -> Riemannian Liquid Spatio-Temporal Graph Network Liangsi Lu, Jingchao Wang, Zhaorong Dai, Hanqian Liu and Yang Shi Diffusion-based Kriging Model with Graph-enhanced Attention Mingtao Zhang, Guoli Yang, Zhanxing Zhu, Guangyin Jin, Mengzhu Wang and Xiaoying Bai Graph Retention Networks for Dynamic Graphs Qian Chang, Xia Li, Xiufeng Cheng, Runsong Jia, Jinqing Yang, Guoping Hu and Ciprian Doru Giurcaneanu Network Dismantling via Reverse Dismantling: Static and Dynamic Algorithms Jinyu Duan, Sijin Wang, Fan Zhang, Xiang Zhao, Wenjie Zhang and Zhihong Tian Zero-Shot Forecasting of Network Dynamics through Weight Flow Matching Shihe Zhou, Ruikun Li, Huandong Wang and Yong Li | E32: =IFERROR(__xludf.DUMMYFUNCTION("TEXTJOIN(CHAR(10), TRUE,FILTER('Research assignment'!$D:$D,'Research assignment'!$F:$F=E30))"),"Difficulty-Aware Agentic Orchestration for Query-Specific Multi-Agent Workflows Jinwei Su, Qizhen Lan, Yinghui Xia, Lifan Sun, Weiyou Tian, Tianyu Shi and Lewei He Toward Generalized Web Agent Training: A Deep Dive into Entropy-Balanced Reinforcement Lea"&"rning Guanting Dong, Licheng Bao, Zhongyuan Wang, Kangzhi Zhao, Xiaoxi Li, Jiajie Jin, Jinghan Yang, Hangyu Mao, Fuzheng Zhang, Kun Gai, Guorui Zhou, Yutao Zhu, Ji-Rong Wen and Zhicheng Dou QChunker: Learning Question-Aware Text Chunking for Domain RAG v"&"ia Multi-Agent Debate Jihao Zhao, Daixuan Li, Pengfei Li, Shuaishuai Zu, Biao Qin and Hongyan Liu DeepAgent: A General Reasoning Agent with Scalable Toolsets Xiaoxi Li, Wenxiang Jiao, Jiarui Jin, Guanting Dong, Jiajie Jin, Yinuo Wang, Hao Wang, Yutao Zhu"&", Ji-Rong Wen, Yuan Lu and Zhicheng Dou Reasoning by Exploration: A Unified Approach to Retrieval and Generation over Graphs Haoyu Han, Kai Guo, Harry Shomer, Yu Wang, Yucheng Chu, Hang Li, Li Ma and Jiliang Tang ") -> Difficulty-Aware Agentic Orchestration for Query-Specific Multi-Agent Workflows Jinwei Su, Qizhen Lan, Yinghui Xia, Lifan Sun, Weiyou Tian, Tianyu Shi and Lewei He Toward Generalized Web Agent Training: A Deep Dive into Entropy-Balanced Reinforcement Learning Guanting Dong, Licheng Bao, Zhongyuan Wang, Kangzhi Zhao, Xiaoxi Li, Jiajie Jin, Jinghan Yang, Hangyu Mao, Fuzheng Zhang, Kun Gai, Guorui Zhou, Yutao Zhu, Ji-Rong Wen and Zhicheng Dou QChunker: Learning Question-Aware Text Chunking for Domain RAG via Multi-Agent Debate Jihao Zhao, Daixuan Li, Pengfei Li, Shuaishuai Zu, Biao Qin and Hongyan Liu DeepAgent: A General Reasoning Agent with Scalable Toolsets Xiaoxi Li, Wenxiang Jiao, Jiarui Jin, Guanting Dong, Jiajie Jin, Yinuo Wang, Hao Wang, Yutao Zhu, Ji-Rong Wen, Yuan Lu and Zhicheng Dou Reasoning by Exploration: A Unified Approach to Retrieval and Generation over Graphs Haoyu Han, Kai Guo, Harry Shomer, Yu Wang, Yucheng Chu, Hang Li, Li Ma and Jiliang Tang | F32: =IFERROR(__xludf.DUMMYFUNCTION("TEXTJOIN(CHAR(10), TRUE,FILTER('Research assignment'!$D:$D,'Research assignment'!$F:$F=F30))"),"EMSEdit: Efficient Multi-Step Meta-Learning-based Model Editing Xiaopeng Li, Shasha Li, Xi Wang, Shezheng Song, Bin Ji, Shangwen Wang, Jun Ma, Xiaodong Liu, Mina Liu and Jie Yu CASE: Conflict-assessed Knowledge-sensitive Neuron Tuning for Lifelong Model "&"Editing Zhange Zhang, Yuqing Ma, Yulong Wang, Tianbo Wang, Jiakai Wang, Simin Li and Xianglong Liu RAIE:Region-Aware Incremental Preference Editing with LoRA for LLM-based Recommendation Jin Zeng, Yupeng Qi, Hui Li, Chengming Li, Ziyu Lyu, Lixin Cui and "&"Lu Bai Towards Meta-Cognitive Knowledge Editing for Multimodal LLMs Zhaoyu Fan, Kaihang Pan, Mingze Zhou, Bosheng Qin, Juncheng Li, Shengyu Zhang, Wenqiao Zhang, Siliang Tang, Fei Wu and Yueting Zhuang WiNELL: Wikipedia Never-Ending Updating with LLM Ag"&"ents Revanth Gangi Reddy, Tanay Dixit, Jiaxin Qin, Cheng Qian, Daniel Lee, Jiawei Han, Kevin Small, Xing Fan, Ruhi Sarikaya and Heng Ji ") -> EMSEdit: Efficient Multi-Step Meta-Learning-based Model Editing Xiaopeng Li, Shasha Li, Xi Wang, Shezheng Song, Bin Ji, Shangwen Wang, Jun Ma, Xiaodong Liu, Mina Liu and Jie Yu CASE: Conflict-assessed Knowledge-sensitive Neuron Tuning for Lifelong Model Editing Zhange Zhang, Yuqing Ma, Yulong Wang, Tianbo Wang, Jiakai Wang, Simin Li and Xianglong Liu RAIE:Region-Aware Incremental Preference Editing with LoRA for LLM-based Recommendation Jin Zeng, Yupeng Qi, Hui Li, Chengming Li, Ziyu Lyu, Lixin Cui and Lu Bai Towards Meta-Cognitive Knowledge Editing for Multimodal LLMs Zhaoyu Fan, Kaihang Pan, Mingze Zhou, Bosheng Qin, Juncheng Li, Shengyu Zhang, Wenqiao Zhang, Siliang Tang, Fei Wu and Yueting Zhuang WiNELL: Wikipedia Never-Ending Updating with LLM Agents Revanth Gangi Reddy, Tanay Dixit, Jiaxin Qin, Cheng Qian, Daniel Lee, Jiawei Han, Kevin Small, Xing Fan, Ruhi Sarikaya and Heng Ji | G32: =IFERROR(__xludf.DUMMYFUNCTION("TEXTJOIN(CHAR(10), TRUE,FILTER('Research assignment'!$D:$D,'Research assignment'!$F:$F=G30))"),"Many Hands Make Light Work: Group-based Information Diffusion Prediction over Long-Context Cascades Zihan Feng, Yajun Yang, Xin Huang, Xin Wang, Hong Gao and Qinghua Hu Multi-task Inference of Diffusion Networks Ting Gan, Kudereti Kuerban, Qian Yan, Ling"&" Han, Zhigao Zheng and Hao Huang Playing Close to the Vest: Competitive Information Propagation in Partially Observed Dual-Population Mean-Field Games Dun Tan, Lixing Chen, Bo Zhang, Hongfu Liu, Hao Peng, Shenghong Li, Yang Bai and Pan Zhou LLM-Driven S"&"emantic ID for Information Diffusion Prediction Haoshuang Liu, Zihan Feng, Yajun Yang, Xin Wang, Hong Gao and Qinghua Hu DynaFLUX: Implicit Dynamics-Preserving Reinforcement Learning for Topology-Free Influence Maximization Daiyunke Zhang, Ting Deng, Tia"&"nchen Zhu, Shuai Ma, Daqing Li, Mingtian Peng and Feng Tian ") -> Many Hands Make Light Work: Group-based Information Diffusion Prediction over Long-Context Cascades Zihan Feng, Yajun Yang, Xin Huang, Xin Wang, Hong Gao and Qinghua Hu Multi-task Inference of Diffusion Networks Ting Gan, Kudereti Kuerban, Qian Yan, Ling Han, Zhigao Zheng and Hao Huang Playing Close to the Vest: Competitive Information Propagation in Partially Observed Dual-Population Mean-Field Games Dun Tan, Lixing Chen, Bo Zhang, Hongfu Liu, Hao Peng, Shenghong Li, Yang Bai and Pan Zhou LLM-Driven Semantic ID for Information Diffusion Prediction Haoshuang Liu, Zihan Feng, Yajun Yang, Xin Wang, Hong Gao and Qinghua Hu DynaFLUX: Implicit Dynamics-Preserving Reinforcement Learning for Topology-Free Influence Maximization Daiyunke Zhang, Ting Deng, Tianchen Zhu, Shuai Ma, Daqing Li, Mingtian Peng and Feng Tian | H32: =IFERROR(__xludf.DUMMYFUNCTION("TEXTJOIN(CHAR(10), TRUE,FILTER('Research assignment'!$D:$D,'Research assignment'!$F:$F=H30))"),"FedSRD: Sparsify-Reconstruct-Decompose for Communication-Efficient Federated Large Language Models Fine-Tuning Guochen Yan, Luyuan Xie, Qingni Shen, Yuejian Fang and Zhonghai Wu Personalized Federated Fine-Tuning for LLMs via Data-Driven Heterogeneous Mo"&"del Architectures Yicheng Zhang, Zhen Qin, Zhaomin Wu, Jian Hou and Shuiguang Deng EcoTune: Edge-Cloud Collaborative Model Adaptation for Budget-Constrained On-Device SLM Personalization Gong Chen, Mingkai Lin, Xiaobin Hong, Wenzhong Li and Sanglu Lu Fe"&"dDiG: Frequency-Guided Diffusion Diversity for Generalizable Federated Time Series Classification Haoran Shi, Junru Zhang, Cheng Peng, Xiaoli Tang, Longtao Huang and Han Yu FedAKD: Federated Adaptive Knowledge Distillation via Global Knowledge Calibratio"&"n and Decoupling Yingchao Wang, Wenqi Niu and Hanpo Hou ") -> FedSRD: Sparsify-Reconstruct-Decompose for Communication-Efficient Federated Large Language Models Fine-Tuning Guochen Yan, Luyuan Xie, Qingni Shen, Yuejian Fang and Zhonghai Wu Personalized Federated Fine-Tuning for LLMs via Data-Driven Heterogeneous Model Architectures Yicheng Zhang, Zhen Qin, Zhaomin Wu, Jian Hou and Shuiguang Deng EcoTune: Edge-Cloud Collaborative Model Adaptation for Budget-Constrained On-Device SLM Personalization Gong Chen, Mingkai Lin, Xiaobin Hong, Wenzhong Li and Sanglu Lu FedDiG: Frequency-Guided Diffusion Diversity for Generalizable Federated Time Series Classification Haoran Shi, Junru Zhang, Cheng Peng, Xiaoli Tang, Longtao Huang and Han Yu FedAKD: Federated Adaptive Knowledge Distillation via Global Knowledge Calibration and Decoupling Yingchao Wang, Wenqi Niu and Hanpo Hou | I32: =IFERROR(__xludf.DUMMYFUNCTION("TEXTJOIN(CHAR(10), TRUE,FILTER('Research assignment'!$D:$D,'Research assignment'!$F:$F=I30))"),"Unveiling and Mitigating Untargeted Poisoning Attacks on Federated Knowledge Graph Embedding Wenzheng Jiang, Ke Liang, Wenke Huang, Xiongtao Zhang, Zhenxing Xu, Guancheng Wan, Cheston Tan, Flint Xiaofeng Fan and Ji Wang Reconstructing Training Data from "&"Adapter-based Federated Large Language Models Silong Chen, Yuchuan Luo, Guilin Deng, Yi Liu, Ming Xu, Shaojing Fu and Xiaohua Jia Xemis: Fair and Robust Privacy-Preserving Data Trading based on Distributed Noise Sharing Xinxin Xing, Yizhong Liu, Ruonan C"&"hen, Banghong Qin, Wangjie Qiu, Jianwei Liu, Qianhong Wu, Willy Susilo and Robert H. Deng Federated Latent Factor Learning for Privacy-Preserving Spatio-Temporal Signal Recovery Chengjun Yu, Di Wu, Yi He, Jia Chen and Xin Luo Beyond Denial-of-Service: T"&"he Puppeteer's Attack for Fine-Grained Control in Ranking-Based Federated Learning Zhihao Chen, Zirui Gong, Jianting Ning, Yanjun Zhang and Leo Yu Zhang ") -> Unveiling and Mitigating Untargeted Poisoning Attacks on Federated Knowledge Graph Embedding Wenzheng Jiang, Ke Liang, Wenke Huang, Xiongtao Zhang, Zhenxing Xu, Guancheng Wan, Cheston Tan, Flint Xiaofeng Fan and Ji Wang Reconstructing Training Data from Adapter-based Federated Large Language Models Silong Chen, Yuchuan Luo, Guilin Deng, Yi Liu, Ming Xu, Shaojing Fu and Xiaohua Jia Xemis: Fair and Robust Privacy-Preserving Data Trading based on Distributed Noise Sharing Xinxin Xing, Yizhong Liu, Ruonan Chen, Banghong Qin, Wangjie Qiu, Jianwei Liu, Qianhong Wu, Willy Susilo and Robert H. Deng Federated Latent Factor Learning for Privacy-Preserving Spatio-Temporal Signal Recovery Chengjun Yu, Di Wu, Yi He, Jia Chen and Xin Luo Beyond Denial-of-Service: The Puppeteer's Attack for Fine-Grained Control in Ranking-Based Federated Learning Zhihao Chen, Zirui Gong, Jianting Ning, Yanjun Zhang and Leo Yu Zhang | J32: =IFERROR(__xludf.DUMMYFUNCTION("TEXTJOIN(CHAR(10), TRUE,FILTER('Research assignment'!$D:$D,'Research assignment'!$F:$F=J30))"),"Hermes the Polyglot: A Unified Framework to Enhance Expressiveness for Multimodal Interlingual Subtitling Chaoqun Cui, Shijing Wang, Liangbin Huang, Qingqing Gu, Zhaolong Huang, Xiao Zeng and Wenji Mao BHGap: A Deep Iterative Prompting and Multi-stage Al"&"ignment Framework for Dynamic Facial Expression Recognition Yichi Zhang, Yunqi Han, Jiayue Ding and Liangyu Chen MuVaC: A Variational Causal Framework for Multimodal Sarcasm Understanding in Dialogues Diandian Guo, Fangfang Yuan, Cong Cao, Xixun Lin, Chu"&"an Zhou, Hao Peng, Yanan Cao and Yanbing Liu CCAF: Coarse-to-fine Cross-Modal Alignment and Fusion for Multimodal Sentiment Analysis Xianbing Zhao, Shengzun Yang and Buzhou Tang ATGFB-MFF: Adaptive Text-Guided Fiber Bundle Feature Fusion with LLMs for M"&"ultimodal Sentiment Analysis and Emotion Recognition in Conversations Zhaowei Liu, Sheng Liu, Weiqing Yan, Peng Song, Yongchao Song and Rufei Gao ") -> Hermes the Polyglot: A Unified Framework to Enhance Expressiveness for Multimodal Interlingual Subtitling Chaoqun Cui, Shijing Wang, Liangbin Huang, Qingqing Gu, Zhaolong Huang, Xiao Zeng and Wenji Mao BHGap: A Deep Iterative Prompting and Multi-stage Alignment Framework for Dynamic Facial Expression Recognition Yichi Zhang, Yunqi Han, Jiayue Ding and Liangyu Chen MuVaC: A Variational Causal Framework for Multimodal Sarcasm Understanding in Dialogues Diandian Guo, Fangfang Yuan, Cong Cao, Xixun Lin, Chuan Zhou, Hao Peng, Yanan Cao and Yanbing Liu CCAF: Coarse-to-fine Cross-Modal Alignment and Fusion for Multimodal Sentiment Analysis Xianbing Zhao, Shengzun Yang and Buzhou Tang ATGFB-MFF: Adaptive Text-Guided Fiber Bundle Feature Fusion with LLMs for Multimodal Sentiment Analysis and Emotion Recognition in Conversations Zhaowei Liu, Sheng Liu, Weiqing Yan, Peng Song, Yongchao Song and Rufei Gao | K32: =IFERROR(__xludf.DUMMYFUNCTION("TEXTJOIN(CHAR(10), TRUE,FILTER('Research assignment'!$D:$D,'Research assignment'!$F:$F=K30))"),"Generative Data Transformation: From Mixed to Unified Data Jiaqing Zhang, Mingjia Yin, Hao Wang, Yuxin Tian, Yuyang Ye, Yawen Li, Wei Guo, Yong Liu and Enhong Chen Gaussian Mixture Flow Matching with Domain Alignment for Multi-Domain Sequential Recommend"&"ation Xiaoxin Ye, Chengkai Huang, Hongtao Huang and Lina Yao WeaveRec: An LLM-Based Cross-Domain Sequential Recommendation Framework with Model Merging Min Hou, Xin Liu, Le Wu, Chenyi He, Hao Liu, Zhi Li, Xin Li and Si Wei SemaCDR: LLM-Powered Transfera"&"ble Semantics for Cross-Domain Sequential Recommendation Chunxu Zhang, Shanqiang Huang, Zijian Zhang, Jiahong Liu, Linsong Yu, Ruiqi Wan, Bo Yang and Irwin King The Double-Edged Sword of Knowledge Transfer: Diagnosing and Curing Fairness Pathologies in C"&"ross-Domain Recommendation Yuhan Zhao, Weixin Chen, Li Chen and Weike Pan ") -> Generative Data Transformation: From Mixed to Unified Data Jiaqing Zhang, Mingjia Yin, Hao Wang, Yuxin Tian, Yuyang Ye, Yawen Li, Wei Guo, Yong Liu and Enhong Chen Gaussian Mixture Flow Matching with Domain Alignment for Multi-Domain Sequential Recommendation Xiaoxin Ye, Chengkai Huang, Hongtao Huang and Lina Yao WeaveRec: An LLM-Based Cross-Domain Sequential Recommendation Framework with Model Merging Min Hou, Xin Liu, Le Wu, Chenyi He, Hao Liu, Zhi Li, Xin Li and Si Wei SemaCDR: LLM-Powered Transferable Semantics for Cross-Domain Sequential Recommendation Chunxu Zhang, Shanqiang Huang, Zijian Zhang, Jiahong Liu, Linsong Yu, Ruiqi Wan, Bo Yang and Irwin King The Double-Edged Sword of Knowledge Transfer: Diagnosing and Curing Fairness Pathologies in Cross-Domain Recommendation Yuhan Zhao, Weixin Chen, Li Chen and Weike Pan | L32: =IFERROR(__xludf.DUMMYFUNCTION("TEXTJOIN(CHAR(10), TRUE,FILTER('Research assignment'!$D:$D,'Research assignment'!$F:$F=L30))"),"DiffGRM: Diffusion-based Generative Recommendation Model Zhao Liu, Yichen Zhu, Yiqing Yang, Xiao Lv, Guoping Tang, Rui Huang, Qiang Luo, Ruiming Tang and Guorui Zhou Modeling Endogenous Logic: Causal Neuro-Symbolic Reasoning Model for Explainable Multi-B"&"ehavior Recommendation Yuzhe Chen, Jie Cao, Youquan Wang, Haicheng Tao, Darko Vuković and Jia Wu MCLMR: A Model-Agnostic Causal Learning Framework for Multi-Behavior Recommendation Ranxu Zhang, Junjie Meng, Ying Sun, Ziqi Xu, Bing Yin, Hao Li, Yanyong Zh"&"ang and Chao Wang C-HyPOD: Causal Hyperbolic Learning with Prototype Orthogonal Disentanglement for Graph Out-of-Distribution Recommendation Jiahao Liang, Yutian Xiao, Haoran Yang, Zhiwen Yu, Jia-Nan Liu and Kaixiang Yang Causality Enhancement for Cross"&"-Domain Recommendation Zhibo Wu, Yunfan Wu, Yang Chang, Ping Yang and Yao Hu ") -> DiffGRM: Diffusion-based Generative Recommendation Model Zhao Liu, Yichen Zhu, Yiqing Yang, Xiao Lv, Guoping Tang, Rui Huang, Qiang Luo, Ruiming Tang and Guorui Zhou Modeling Endogenous Logic: Causal Neuro-Symbolic Reasoning Model for Explainable Multi-Behavior Recommendation Yuzhe Chen, Jie Cao, Youquan Wang, Haicheng Tao, Darko Vuković and Jia Wu MCLMR: A Model-Agnostic Causal Learning Framework for Multi-Behavior Recommendation Ranxu Zhang, Junjie Meng, Ying Sun, Ziqi Xu, Bing Yin, Hao Li, Yanyong Zhang and Chao Wang C-HyPOD: Causal Hyperbolic Learning with Prototype Orthogonal Disentanglement for Graph Out-of-Distribution Recommendation Jiahao Liang, Yutian Xiao, Haoran Yang, Zhiwen Yu, Jia-Nan Liu and Kaixiang Yang Causality Enhancement for Cross-Domain Recommendation Zhibo Wu, Yunfan Wu, Yang Chang, Ping Yang and Yao Hu | M32: =IFERROR(__xludf.DUMMYFUNCTION("TEXTJOIN(CHAR(10), TRUE,FILTER('Industry assignment'!$D:$D,'Industry assignment'!$F:$F=M30))"),"PI2I: A Personalized Item-Based Collaborative Filtering Retrieval Framework Shaoqing Wang, Yingcai Ma, Kairui Fu, Ziyang Wang, Dunxian Huang, Yuliang Yan and Jian Wu AliBoostV2: CTR-Growth Balanced Boosting Framework in Billion-Scale Recommendation Platf"&"orm Qijie Shen, Yuanchen Bei, Zihong Huang, Xixian Wang, Zhibo Xiao, Dimin Wang, Jialin Zhu, Yuning Jiang, Feiran Huang and Hao Chen BanditLP: Large-Scale Stochastic Optimization for Personalized Recommendations Phuc Nguyen, Benjamin Zelditch, Joyce Chen"&", Rohit K Patra and Changshuai Wei Unleashing the Potential of Sparse Attention on Long-term Behaviors for CTR Prediction Weijiang Lai, Beihong Jin, Di Zhang, Siru Chen, Jiongyan Zhang, Yuhang Gou, Jian Dong and Xingxing Wang Improving Multi Task Recomm"&"endations via Cross User Learning with a Hybrid Pointwise and Pairwise Ranking Loss Abhinav Naikawadi, Hedi Xia, Dafang He, Yichu Zhou, Xue Xia, Piyush Maheshwari, Bella Huang, Bowen Deng, James Li, Dhruvil Deven Badani and Yijie Dylan Wang ") -> PI2I: A Personalized Item-Based Collaborative Filtering Retrieval Framework Shaoqing Wang, Yingcai Ma, Kairui Fu, Ziyang Wang, Dunxian Huang, Yuliang Yan and Jian Wu AliBoostV2: CTR-Growth Balanced Boosting Framework in Billion-Scale Recommendation Platform Qijie Shen, Yuanchen Bei, Zihong Huang, Xixian Wang, Zhibo Xiao, Dimin Wang, Jialin Zhu, Yuning Jiang, Feiran Huang and Hao Chen BanditLP: Large-Scale Stochastic Optimization for Personalized Recommendations Phuc Nguyen, Benjamin Zelditch, Joyce Chen, Rohit K Patra and Changshuai Wei Unleashing the Potential of Sparse Attention on Long-term Behaviors for CTR Prediction Weijiang Lai, Beihong Jin, Di Zhang, Siru Chen, Jiongyan Zhang, Yuhang Gou, Jian Dong and Xingxing Wang Improving Multi Task Recommendations via Cross User Learning with a Hybrid Pointwise and Pairwise Ranking Loss Abhinav Naikawadi, Hedi Xia, Dafang He, Yichu Zhou, Xue Xia, Piyush Maheshwari, Bella Huang, Bowen Deng, James Li, Dhruvil Deven Badani and Yijie Dylan Wang | N32: =IFERROR(__xludf.DUMMYFUNCTION("TEXTJOIN(CHAR(10), TRUE,FILTER('HoW assignment'!$D:$D,'HoW assignment'!$F:$F=N30))"),"On the historic roots of Agentic AI in Semantic Web Services Axel Polleres From Lexical and Semantic to Predictive Search: Evolution or Involution? Ricardo Baeza-Yates Evolving Notions of Success on the Web: From Retrieval to Experience Mounia Lalmas P"&"anel Yoelle Maarek, Ricardo Baeza-Yates, Wendy Hall moderated by Oshani Seneviratne ") -> On the historic roots of Agentic AI in Semantic Web Services Axel Polleres From Lexical and Semantic to Predictive Search: Evolution or Involution? Ricardo Baeza-Yates Evolving Notions of Success on the Web: From Retrieval to Experience Mounia Lalmas Panel Yoelle Maarek, Ricardo Baeza-Yates, Wendy Hall moderated by Oshani Seneviratne
A33: 17:30 - 18:30 | B33: Posters and Demos Session 2
B34: Demos2 | C34: ShortPapers2 | D34: EconPoster2 | E34: GraphPoster2 | F34: SearchPoster2 | G34: SemanticsPoster2 | H34: SecurityPoster2 | I34: SocialPoster2 | J34: SystemsPoster2 | K34: RecSysPoster2 | L34: MiningPoster2 | M34: IndustryPoster2 | N34: Web4GoodPoster2
B35: =IFERROR(__xludf.DUMMYFUNCTION("TEXTJOIN(CHAR(10), TRUE,FILTER(Demos!$D:$D,Demos!$E:$E=B34))"),"Lang2Plan: An LLM-Powered Multi-Agent System for Building Layout Planning Fangyong Pan, Xi Chen, Weiqi Xu, Yifeng Xu and Haofen Wang NGCAPTCHA: A CAPTCHA Bridging the Past and the Future Ziqi Ding, Shangzhi Xu, Wei Song and Yuekang Li G-SEIR: A Graph-En"&"hanced Epidemic Forecasting System for Dengue Intervention Cheng-Ru Chou, Shou-Po Tsai, Jing-Zhe Huang, Hsu-Han Tu, Pei-Xuan Li and Hsun-Ping Hsieh SAMPLE: A Spatial/Channel-wise Attention GCN with MLP and Periodic Linear Encoding for Land Boundary Demar"&"cation System Min-Huan Tsai, Cheng-Ru Chou, Chia Chen Tsai, Yu-Yin Wang, Pei-Xuan Li, Hsun-Ping Hsieh and Tzu-Chang Lee A Large Language Model-based Agent for Automated Machine Learning Workflow Construction Yutian Xu, Yanhao Wang, Hui Li, Shengjie Xia a"&"nd Shengtian Min Deep Research Comparator: A Platform For Fine-grained Human Annotations of Deep Research Agents Prahaladh Chandrahasan, Jiahe Jin, Zhihan Zhang, Tevin Wang, Andy Tang, Lucy Mo, Morteza Ziyadi, Leonardo F.R. Ribeiro, Zimeng Qiu, Markus Dr"&"eyer, Akari Asai and Chenyan Xiong Docs2Synth: A Synthetic Data Tuned Retriever Framework for Documents Understanding Yihao Ding, Qiang Sun, Puzhen Wu, Sirui Li, Siwen Luo and Wei Liu GCAgent: Enhancing Group Chat Communication through Dialogue Agents S"&"ystem Zijie Meng, Zheyong Xie, Zheyu Ye, Chonggang Lu, Zuozhu Liu, Zihan Niu, Yao Hu and Shaosheng Cao ") -> Lang2Plan: An LLM-Powered Multi-Agent System for Building Layout Planning Fangyong Pan, Xi Chen, Weiqi Xu, Yifeng Xu and Haofen Wang NGCAPTCHA: A CAPTCHA Bridging the Past and the Future Ziqi Ding, Shangzhi Xu, Wei Song and Yuekang Li G-SEIR: A Graph-Enhanced Epidemic Forecasting System for Dengue Intervention Cheng-Ru Chou, Shou-Po Tsai, Jing-Zhe Huang, Hsu-Han Tu, Pei-Xuan Li and Hsun-Ping Hsieh SAMPLE: A Spatial/Channel-wise Attention GCN with MLP and Periodic Linear Encoding for Land Boundary Demarcation System Min-Huan Tsai, Cheng-Ru Chou, Chia Chen Tsai, Yu-Yin Wang, Pei-Xuan Li, Hsun-Ping Hsieh and Tzu-Chang Lee A Large Language Model-based Agent for Automated Machine Learning Workflow Construction Yutian Xu, Yanhao Wang, Hui Li, Shengjie Xia and Shengtian Min Deep Research Comparator: A Platform For Fine-grained Human Annotations of Deep Research Agents Prahaladh Chandrahasan, Jiahe Jin, Zhihan Zhang, Tevin Wang, Andy Tang, Lucy Mo, Morteza Ziyadi, Leonardo F.R. Ribeiro, Zimeng Qiu, Markus Dreyer, Akari Asai and Chenyan Xiong Docs2Synth: A Synthetic Data Tuned Retriever Framework for Documents Understanding Yihao Ding, Qiang Sun, Puzhen Wu, Sirui Li, Siwen Luo and Wei Liu GCAgent: Enhancing Group Chat Communication through Dialogue Agents System Zijie Meng, Zheyong Xie, Zheyu Ye, Chonggang Lu, Zuozhu Liu, Zihan Niu, Yao Hu and Shaosheng Cao | C35: =IFERROR(__xludf.DUMMYFUNCTION("TEXTJOIN(CHAR(10), TRUE,FILTER('ShortPapers assignment'!$D:$D,'ShortPapers assignment'!$E:$E=C34))"),"Let It Try First: Uncertainty-Guided Retrieval Switching for Retrieval-Augmented Question Answering Xiaohai Wang, Yu Liang, Wei Zhou and Sixing Wu DiffusionGS: Generative Search with Query Conditioned Diffusion in Kuaishou Qinyao Li, Xiaoyang Zheng, Qiha"&"ng Zhao, Ke Xu, Zhongbo Sun, Chao Wang, Chenyi Lei, Han Li and Wenwu Ou LLM Reasoning for Cold-Start Item Recommendation Shijun Li, Yu Wang, Jin Wang, Ying Li, Joydeep Ghosh and Anne Cocos Hierarchical Layer Attention with Contrastive Learning for Robus"&"t Audio Deepfake Detection Zhili Nicholas Liang, Soyeon Caren Han, Qizhou Wang and Christopher Leckie Online Bidding Algorithms with Strict Return on Spend (ROS) Constraint Rahul Vaze and Abhishek Sinha OMGRec: One-time Matching-based Generative Rerank "&"with Permutation-level Modeling in E-commerce Junwei Xu, Zhibo Xiao, Chuxin Chen, Chengyu Lai, Qijie Shen, Jiuning Lin, Dimin Wang, Jialin Zhu and Xiao-Ping Zhang LPEdit: Locality-Preserving Knowledge Editing for MultiModal Large Language Models Tianyu Z"&"hang, Junfeng Fang, Houcheng Jiang, Xingyu Zhu, Xiang Wang and Xiangnan He Img2KG: Ontology-Driven Correction of Visual Triples Christina Kanetou and Yannis Tzitzikas A Life‑Cycle Assessment of the Hidden Environmental Cost of Selfies Tilen Hliš, Urška "&"Butolen, Iztok Fister and Iztok Fister We May Not Need Much Visual Encoding of Web Data for Question Answering Tan Yue, Qiong Wu and Dongyan Zhao CityVerse: A Unified Data Framework for Evaluating Large Language Models in Urban Computing Yaqiao Zhu, Hon"&"gkai Wen, Mark Birkin and Man Luo An Improved Combinatorial Algorithm for Edge-Colored Clustering in Hypergraphs Seongjune Han and Nate Veldt BitHeteroNet: A Heterogeneous Network Benchmark for Enhanced Anomaly Detection in Bitcoin Transactions Zheng Go"&"ng, Shuheng Shen, Changhua Meng and Ying Sun Feature-PI: A Data Repository for Learning-based Feature Importance Estimation Yin Lou BiCare: Bi-Objective Set Similarity with Box Embeddings for Safe and Effective Healthcare Decision Support Guofang Ma, Pe"&"ngxiang Zhan, Haoze Huang and Yanchao Tan ReMi-ReMath: A Reverse-Mutual Reasoning Framework for Enhancing Mathematical Thinking in Small Language Models Dae Kyoo Kim, Sang Kyu Moon and Eunil Park Beyond Isolated Clients: Integrating Graph-Based Embeddin"&"gs into Event Sequence Models Harry Proshian, Nikita Severin, Sergey Nikolenko, Ivan Kireev, Andrey Savchenko, Ivan Sergeev, Maria Postnova and Ilya Makarov GlotWeb: Web Indexing for Minority Languages Abdullah Al Sefat, Amir Hossein Kargaran, François Y"&"von and Hinrich Schütze Graph Poisoning for Node Rank Manipulation Seyed Mohammad Hosseini, Radin Hamidi Rad, Morteza Zihayat and Ebrahim Bagheri P-Aligner: Pre-Aligning LLMs via Principled Instruction Synthesis Feifan Song, Bofei Gao, Yifan Song, Yi Li"&"u, Weimin Xiong, Yuyang Song, Tianyu Liu, Guoyin Wang and Houfeng Wang Interaction-level Membership Inference Attack for Recommender Systems via Cluster-based User Modeling Danyang Zong, Kaike Zhang, Qi Cao, Du Su and Fei Sun CytoCrowd: A Multi-Annotato"&"r Benchmark Dataset for Cytology Image Analysis Yonghao Si, Xingyuan Zeng, Zhao Chen, Libin Zheng, Caleb Chen Cao, Chen Lei and Jian Yin FilterRec: An Intent-Aware Framework for Dynamic Filter Recommendation Dingxian Wang, Jiacheng Dong, Jiaqi Deng, Jing"&" Long, Ted Liu, George Barelas, Arya Taylor, Spyros Kapnissis, Frank Yang, Andrew Rabinovich and Guandong Xu MCP vs RAG vs NLWeb vs HTML: A Comparison of the Effectiveness and Efficiency of Different Agent Interfaces to the Web Aaron Steiner, Ralph Peete"&"rs and Christian Bizer SIT-KGED: Simply Inject Topology into LLM for Knowledge Graph Error Detection Ting Li, Xingyi Mao, Yipeng Yu and Liang Yao ") -> Let It Try First: Uncertainty-Guided Retrieval Switching for Retrieval-Augmented Question Answering Xiaohai Wang, Yu Liang, Wei Zhou and Sixing Wu DiffusionGS: Generative Search with Query Conditioned Diffusion in Kuaishou Qinyao Li, Xiaoyang Zheng, Qihang Zhao, Ke Xu, Zhongbo Sun, Chao Wang, Chenyi Lei, Han Li and Wenwu Ou LLM Reasoning for Cold-Start Item Recommendation Shijun Li, Yu Wang, Jin Wang, Ying Li, Joydeep Ghosh and Anne Cocos Hierarchical Layer Attention with Contrastive Learning for Robust Audio Deepfake Detection Zhili Nicholas Liang, Soyeon Caren Han, Qizhou Wang and Christopher Leckie Online Bidding Algorithms with Strict Return on Spend (ROS) Constraint Rahul Vaze and Abhishek Sinha OMGRec: One-time Matching-based Generative Rerank with Permutation-level Modeling in E-commerce Junwei Xu, Zhibo Xiao, Chuxin Chen, Chengyu Lai, Qijie Shen, Jiuning Lin, Dimin Wang, Jialin Zhu and Xiao-Ping Zhang LPEdit: Locality-Preserving Knowledge Editing for MultiModal Large Language Models Tianyu Zhang, Junfeng Fang, Houcheng Jiang, Xingyu Zhu, Xiang Wang and Xiangnan He Img2KG: Ontology-Driven Correction of Visual Triples Christina Kanetou and Yannis Tzitzikas A Life‑Cycle Assessment of the Hidden Environmental Cost of Selfies Tilen Hliš, Urška Butolen, Iztok Fister and Iztok Fister We May Not Need Much Visual Encoding of Web Data for Question Answering Tan Yue, Qiong Wu and Dongyan Zhao CityVerse: A Unified Data Framework for Evaluating Large Language Models in Urban Computing Yaqiao Zhu, Hongkai Wen, Mark Birkin and Man Luo An Improved Combinatorial Algorithm for Edge-Colored Clustering in Hypergraphs Seongjune Han and Nate Veldt BitHeteroNet: A Heterogeneous Network Benchmark for Enhanced Anomaly Detection in Bitcoin Transactions Zheng Gong, Shuheng Shen, Changhua Meng and Ying Sun Feature-PI: A Data Repository for Learning-based Feature Importance Estimation Yin Lou BiCare: Bi-Objective Set Similarity with Box Embeddings for Safe and Effective Healthcare Decision Support Guofang Ma, Pengxiang Zhan, Haoze Huang and Yanchao Tan ReMi-ReMath: A Reverse-Mutual Reasoning Framework for Enhancing Mathematical Thinking in Small Language Models Dae Kyoo Kim, Sang Kyu Moon and Eunil Park Beyond Isolated Clients: Integrating Graph-Based Embeddings into Event Sequence Models Harry Proshian, Nikita Severin, Sergey Nikolenko, Ivan Kireev, Andrey Savchenko, Ivan Sergeev, Maria Postnova and Ilya Makarov GlotWeb: Web Indexing for Minority Languages Abdullah Al Sefat, Amir Hossein Kargaran, François Yvon and Hinrich Schütze Graph Poisoning for Node Rank Manipulation Seyed Mohammad Hosseini, Radin Hamidi Rad, Morteza Zihayat and Ebrahim Bagheri P-Aligner: Pre-Aligning LLMs via Principled Instruction Synthesis Feifan Song, Bofei Gao, Yifan Song, Yi Liu, Weimin Xiong, Yuyang Song, Tianyu Liu, Guoyin Wang and Houfeng Wang Interaction-level Membership Inference Attack for Recommender Systems via Cluster-based User Modeling Danyang Zong, Kaike Zhang, Qi Cao, Du Su and Fei Sun CytoCrowd: A Multi-Annotator Benchmark Dataset for Cytology Image Analysis Yonghao Si, Xingyuan Zeng, Zhao Chen, Libin Zheng, Caleb Chen Cao, Chen Lei and Jian Yin FilterRec: An Intent-Aware Framework for Dynamic Filter Recommendation Dingxian Wang, Jiacheng Dong, Jiaqi Deng, Jing Long, Ted Liu, George Barelas, Arya Taylor, Spyros Kapnissis, Frank Yang, Andrew Rabinovich and Guandong Xu MCP vs RAG vs NLWeb vs HTML: A Comparison of the Effectiveness and Efficiency of Different Agent Interfaces to the Web Aaron Steiner, Ralph Peeters and Christian Bizer SIT-KGED: Simply Inject Topology into LLM for Knowledge Graph Error Detection Ting Li, Xingyi Mao, Yipeng Yu and Liang Yao | D35: =IFERROR(__xludf.DUMMYFUNCTION("TEXTJOIN(CHAR(10), TRUE,FILTER('Research assignment'!$D:$D,'Research assignment'!$G:$G=D34))"),"Online Rounding and Pricing Schemes for k-Rental Problems Hossein Nekouyan, Bo Sun, Raouf Boutaba and Xiaoqi Tan Online Advertising with Spatial Interactions Gagan Aggarwal, Yifan Wang and Mingfei Zhao Automated Deterministic Auction Design with Objecti"&"ve Decomposition Zhijian Duan, Haoran Sun, Yichong Xia, Siqiang Wang, Zhilin Zhang, Chuan Yu, Jian Xu and Xiaotie Deng The Query Complexity of Uniform Pricing Houshuang Chen, Yaonan Jin, Pinyan Lu and Chihao Zhang Determinants and Effects of Buy Box Sup"&"pression on Amazon Jeffrey Gleason, Shuo Zhang and Christo Wilson Additively Competitive Secretaries Mohammad Mahdian, Jieming Mao, Enze Sun, Kangning Wang and Yifan Wang Improving the Price of Anarchy via Predictions in Parallel-Link Networks George Ch"&"ristodoulou, Vasilis Christoforidis, Alkmini Sgouritsa and Ioannis Vlachos ") -> Online Rounding and Pricing Schemes for k-Rental Problems Hossein Nekouyan, Bo Sun, Raouf Boutaba and Xiaoqi Tan Online Advertising with Spatial Interactions Gagan Aggarwal, Yifan Wang and Mingfei Zhao Automated Deterministic Auction Design with Objective Decomposition Zhijian Duan, Haoran Sun, Yichong Xia, Siqiang Wang, Zhilin Zhang, Chuan Yu, Jian Xu and Xiaotie Deng The Query Complexity of Uniform Pricing Houshuang Chen, Yaonan Jin, Pinyan Lu and Chihao Zhang Determinants and Effects of Buy Box Suppression on Amazon Jeffrey Gleason, Shuo Zhang and Christo Wilson Additively Competitive Secretaries Mohammad Mahdian, Jieming Mao, Enze Sun, Kangning Wang and Yifan Wang Improving the Price of Anarchy via Predictions in Parallel-Link Networks George Christodoulou, Vasilis Christoforidis, Alkmini Sgouritsa and Ioannis Vlachos | E35: =IFERROR(__xludf.DUMMYFUNCTION("TEXTJOIN(CHAR(10), TRUE,FILTER('Research assignment'!$D:$D,'Research assignment'!$G:$G=E34))"),"TAWRMAC: A Novel Dynamic Graph Representation Learning Method Soheila Farokhi, Xiaojun Qi and Hamid Karimi negMIX: Negative Mixup for OOD Generalization in Open-Set Node Classification Junwei Gong, Xiao Shen, Zhihao Chen, Shirui Pan, Xiao Wang and Xi Zho"&"u UTAG: Leveraging LLM as a Unified Embedding Generator for Text-Attributed Graphs Mingqian Ding, Jianjun Li, Zhiyuan Ma, Liwei Zhang and Wenqi Yang Mitigating Dynamic Graph Distribution Shifts via Mixture of Variational Experts Qianyu Song, Chao Li, Ye"&"yu Yan, Hui Zhou, Zhongying Zhao and Qingtian Zeng Text-attributed Graph Condensation via Text Selection and Attribute Matching Haowei Han, Yuxiang Wang, Guojia Wan, Hao Wang, Shanshan Feng, Hao Huang, Jiawei Jiang and Xiao Yan Practical Group Steiner T"&"ree Algorithms for Web Applications with Many Groups Qicheng Shan, Yuxuan Yang and Gong Cheng GraphTARIF: Linear Graph Transformer with Augmented Rank and Improved Focus Zhaolin Hu, Kun Li, Hehe Fan and Yi Yang VSAL: A Vision Solver with Adaptive Layout"&"s for Graph Property Detection Jiahao Xie and Guangmo Tong Sustained Vertex Cover on Temporal Graphs Junqiang Peng, Tian Bai, Jingyang Zhao and Mingyu Xiao Dual-level Reweighting for Positive-Unlabeled Graph Classification Junghun Kim, Shihyung Park and"&" U Kang ") -> TAWRMAC: A Novel Dynamic Graph Representation Learning Method Soheila Farokhi, Xiaojun Qi and Hamid Karimi negMIX: Negative Mixup for OOD Generalization in Open-Set Node Classification Junwei Gong, Xiao Shen, Zhihao Chen, Shirui Pan, Xiao Wang and Xi Zhou UTAG: Leveraging LLM as a Unified Embedding Generator for Text-Attributed Graphs Mingqian Ding, Jianjun Li, Zhiyuan Ma, Liwei Zhang and Wenqi Yang Mitigating Dynamic Graph Distribution Shifts via Mixture of Variational Experts Qianyu Song, Chao Li, Yeyu Yan, Hui Zhou, Zhongying Zhao and Qingtian Zeng Text-attributed Graph Condensation via Text Selection and Attribute Matching Haowei Han, Yuxiang Wang, Guojia Wan, Hao Wang, Shanshan Feng, Hao Huang, Jiawei Jiang and Xiao Yan Practical Group Steiner Tree Algorithms for Web Applications with Many Groups Qicheng Shan, Yuxuan Yang and Gong Cheng GraphTARIF: Linear Graph Transformer with Augmented Rank and Improved Focus Zhaolin Hu, Kun Li, Hehe Fan and Yi Yang VSAL: A Vision Solver with Adaptive Layouts for Graph Property Detection Jiahao Xie and Guangmo Tong Sustained Vertex Cover on Temporal Graphs Junqiang Peng, Tian Bai, Jingyang Zhao and Mingyu Xiao Dual-level Reweighting for Positive-Unlabeled Graph Classification Junghun Kim, Shihyung Park and U Kang | F35: =IFERROR(__xludf.DUMMYFUNCTION("TEXTJOIN(CHAR(10), TRUE,FILTER('Research assignment'!$D:$D,'Research assignment'!$G:$G=F34))"),"Dual-Branch Multi-Granularity Network with Structured Contrastive Ranking for Cross-Modal Retrieval Zihao Chen, Chenyang Bu, Shengwei Ji and Xindong Wu Less is More: Compact Clue Selection for Efficient Retrieval-Augmented Generation Reasoning Qianchi Zh"&"ang, Hainan Zhang, Liang Pang, Yongxin Tong, Hongwei Zheng and Zhiming Zheng Déjà Vu of Strange Stickers! Enhancing Out-of-Distribution Robustness in Sticker Retrieval via Cross-Modal Intent Alignment Yu-An Liu, Ruqing Zhang, Jiafeng Guo, Changjiang Zhou"&", Fan Zhang and Yinhu Zhao SQL-Checker: Error Detection and Labeling for Text-to-SQL with Interpretability Analysis Xingyu Ma, Xin Tian, Lingxiang Wu, Xuepeng Wang, Xueming Tang and Jinqiao Wang To Search or Not to Search: Aligning the Decision Boundary"&" of Deep Search Agents via Causal Intervention Wenlin Zhang, Kuicai Dong, Junyi Li, Yingyi Zhang, Xiaopeng Li, Pengyue Jia, Yi Wen, Derong Xu, Maolin Wang, Yichao Wang, Yong Liu and Xiangyu Zhao XR: Cross-Modal Agents for Composed Image Retrieval Zhongyu"&" Yang, Wei Pang and Yingfang Yuan ") -> Dual-Branch Multi-Granularity Network with Structured Contrastive Ranking for Cross-Modal Retrieval Zihao Chen, Chenyang Bu, Shengwei Ji and Xindong Wu Less is More: Compact Clue Selection for Efficient Retrieval-Augmented Generation Reasoning Qianchi Zhang, Hainan Zhang, Liang Pang, Yongxin Tong, Hongwei Zheng and Zhiming Zheng Déjà Vu of Strange Stickers! Enhancing Out-of-Distribution Robustness in Sticker Retrieval via Cross-Modal Intent Alignment Yu-An Liu, Ruqing Zhang, Jiafeng Guo, Changjiang Zhou, Fan Zhang and Yinhu Zhao SQL-Checker: Error Detection and Labeling for Text-to-SQL with Interpretability Analysis Xingyu Ma, Xin Tian, Lingxiang Wu, Xuepeng Wang, Xueming Tang and Jinqiao Wang To Search or Not to Search: Aligning the Decision Boundary of Deep Search Agents via Causal Intervention Wenlin Zhang, Kuicai Dong, Junyi Li, Yingyi Zhang, Xiaopeng Li, Pengyue Jia, Yi Wen, Derong Xu, Maolin Wang, Yichao Wang, Yong Liu and Xiangyu Zhao XR: Cross-Modal Agents for Composed Image Retrieval Zhongyu Yang, Wei Pang and Yingfang Yuan | G35: =IFERROR(__xludf.DUMMYFUNCTION("TEXTJOIN(CHAR(10), TRUE,FILTER('Research assignment'!$D:$D,'Research assignment'!$G:$G=G34))"),"Lifting Manifolds to Mitigate Pseudo-Alignment in LLM4TS Liangwei Nathan Zheng, Wenhao Liang, Wei Emma Zhang, Miao Xu, Olaf Maennel and Weitong Chen MePe: Rethinking Multimodal Chinese Idiom Reading Comprehension from a Metaphorical Perspective Tongguan "&"Wang, Junkai Li, Feiyue Xue, Hui Liu, Dongyu Su, Wangjun Huang and Ying Sha PLIKD: Prompt Learning with Instance-aware Knowledge Distillation for Web-scale Semantic Image Classification Jianye Xie, Chunhua Hu, Lianyong Qi, Fan Wang, Xiaolong Xu, Haolong "&"Xiang, Xuyun Zhang, Shichao Pei, Amin Beheshti, Wanchun Dou and Xiaokang Zhou Neuro-Sym Supporter: A Thoughtful Emotion Support Agent Integrating Neural and Symbolic Policy Learning Minghui Ma, Bin Guo, Mengqi Chen, Jingqi Liu, Yasan Ding, Yan Liu and Ha"&"n Wang LoSemB: Logic-Guided Semantic Bridging for Inductive Tool Retrieval Luyao Zhuang, Qinggang Zhang, Huachi Zhou, Yujing Zhang and Xiao Huang Beyond Factual Queries: A Novel Predictive Retrieval-Augmented Generation Debo Cheng, Jianfeng Deng, Qingfe"&"ng Chen, Jinyi Jie and Jiangzhang Gan Generalized Incremental Learning under Concept Drift across Evolving Data Streams En Yu, Jie Lu and Guangquan Zhang ") -> Lifting Manifolds to Mitigate Pseudo-Alignment in LLM4TS Liangwei Nathan Zheng, Wenhao Liang, Wei Emma Zhang, Miao Xu, Olaf Maennel and Weitong Chen MePe: Rethinking Multimodal Chinese Idiom Reading Comprehension from a Metaphorical Perspective Tongguan Wang, Junkai Li, Feiyue Xue, Hui Liu, Dongyu Su, Wangjun Huang and Ying Sha PLIKD: Prompt Learning with Instance-aware Knowledge Distillation for Web-scale Semantic Image Classification Jianye Xie, Chunhua Hu, Lianyong Qi, Fan Wang, Xiaolong Xu, Haolong Xiang, Xuyun Zhang, Shichao Pei, Amin Beheshti, Wanchun Dou and Xiaokang Zhou Neuro-Sym Supporter: A Thoughtful Emotion Support Agent Integrating Neural and Symbolic Policy Learning Minghui Ma, Bin Guo, Mengqi Chen, Jingqi Liu, Yasan Ding, Yan Liu and Han Wang LoSemB: Logic-Guided Semantic Bridging for Inductive Tool Retrieval Luyao Zhuang, Qinggang Zhang, Huachi Zhou, Yujing Zhang and Xiao Huang Beyond Factual Queries: A Novel Predictive Retrieval-Augmented Generation Debo Cheng, Jianfeng Deng, Qingfeng Chen, Jinyi Jie and Jiangzhang Gan Generalized Incremental Learning under Concept Drift across Evolving Data Streams En Yu, Jie Lu and Guangquan Zhang | H35: =IFERROR(__xludf.DUMMYFUNCTION("TEXTJOIN(CHAR(10), TRUE,FILTER('Research assignment'!$D:$D,'Research assignment'!$G:$G=H34))"),"Red-Teaming Privacy-Protective Perturbations: Blind Face Restoration as an Attack Strategy Zelin Li, Yifan Liu, Huimin Zeng, Yaokun Liu, Ruichen Yao, Yang Zhang and Dong Wang LLMQuA: Practical Backdoor Injection on Large Language Model Quantization Xiang"&"xiang Chen, Peixin Zhang, Jun Sun, Jin Song Dong, Wenhai Wang and Jingyi Wang Unveiling the Vulnerability of Graph-LLMs: An Interpretable Multi-Dimensional Adversarial Attack on TAGs Bowen Fan, Zhilin Guo, Xunkai Li, Yihan Zhou, Bing Zhou, Zhenjun Li, Ro"&"ng-Hua Li and Guoren Wang Robust LLM-Based Website Fingerprinting under Dynamic Real-World Conditions Xiyuan Zhao, Xinhao Deng, Tianyu Cui, Yixiang Zhang, Ke Xu and Qi Li Breaking Cross-modal Alignment in Embodied Intelligence: A Multimodal Adversarial "&"Attack Framework for Vision-Language-Action Models Zhihui Zhao, Xiaorong Dong, Yaowen Zheng, Xiaohui Chen, Yimo Ren, Hangbei Cheng, Yongle Chen and Limin Sun TGweaver: Synthesizing Transaction Graphs for De-anonymization Analysis Fajie Wu, Jiajing Wu, Zh"&"iying Wu, Jun Chen, Tao Wang, Longjian He, Bowen Song and Weiqiang Wang Towards Practical LLM Unlearning: Efficient, Modular, and Retain-Free Peng Liu, Peng-Fei Zhang, Jianfeng Qu, Ximing Li, Zhixu Li and Pengpeng Zhao The Promise vs. Reality of NFT Dec"&"entralization: An Empirical Study of Storage Strategies and Defects Yufang Wu, Siwen Chen, Chao Li, Yuan Weng and Wei Wang PWAVEP: Purifying Imperceptible Adversarial Perturbations in 3D Point Clouds via Spectral Graph Wavelets Li Haoran, Renyang Liu, Ho"&"ngjia Liu, Chen Wang, Long Yin and Jian Xu Zelda: Feedback-driven Closed-box Fuzzing for Identifying Web Application Vulnerabilities Soyoung Lee, Sunnyeo Park, Yonghwi Kwon and Sooel Son ") -> Red-Teaming Privacy-Protective Perturbations: Blind Face Restoration as an Attack Strategy Zelin Li, Yifan Liu, Huimin Zeng, Yaokun Liu, Ruichen Yao, Yang Zhang and Dong Wang LLMQuA: Practical Backdoor Injection on Large Language Model Quantization Xiangxiang Chen, Peixin Zhang, Jun Sun, Jin Song Dong, Wenhai Wang and Jingyi Wang Unveiling the Vulnerability of Graph-LLMs: An Interpretable Multi-Dimensional Adversarial Attack on TAGs Bowen Fan, Zhilin Guo, Xunkai Li, Yihan Zhou, Bing Zhou, Zhenjun Li, Rong-Hua Li and Guoren Wang Robust LLM-Based Website Fingerprinting under Dynamic Real-World Conditions Xiyuan Zhao, Xinhao Deng, Tianyu Cui, Yixiang Zhang, Ke Xu and Qi Li Breaking Cross-modal Alignment in Embodied Intelligence: A Multimodal Adversarial Attack Framework for Vision-Language-Action Models Zhihui Zhao, Xiaorong Dong, Yaowen Zheng, Xiaohui Chen, Yimo Ren, Hangbei Cheng, Yongle Chen and Limin Sun TGweaver: Synthesizing Transaction Graphs for De-anonymization Analysis Fajie Wu, Jiajing Wu, Zhiying Wu, Jun Chen, Tao Wang, Longjian He, Bowen Song and Weiqiang Wang Towards Practical LLM Unlearning: Efficient, Modular, and Retain-Free Peng Liu, Peng-Fei Zhang, Jianfeng Qu, Ximing Li, Zhixu Li and Pengpeng Zhao The Promise vs. Reality of NFT Decentralization: An Empirical Study of Storage Strategies and Defects Yufang Wu, Siwen Chen, Chao Li, Yuan Weng and Wei Wang PWAVEP: Purifying Imperceptible Adversarial Perturbations in 3D Point Clouds via Spectral Graph Wavelets Li Haoran, Renyang Liu, Hongjia Liu, Chen Wang, Long Yin and Jian Xu Zelda: Feedback-driven Closed-box Fuzzing for Identifying Web Application Vulnerabilities Soyoung Lee, Sunnyeo Park, Yonghwi Kwon and Sooel Son | I35: =IFERROR(__xludf.DUMMYFUNCTION("TEXTJOIN(CHAR(10), TRUE,FILTER('Research assignment'!$D:$D,'Research assignment'!$G:$G=I34))"),"Social Event Prediction via Fourier Graph Learning Mingjie Qiu, Zhiyi Tan and Bing-Kun Bao FS_GPlib: Breaking the Web-Scale Barrier — A Unified Acceleration Framework for Graph Propagation Models Chang Guo, Juyuan Zhang, Chang Su, Tianlong Fan and Linyua"&"n Lü Source Localization in Continuous-Time Propagation via Spectral ODE Modeling Dongpeng Hou, Yuchen Wang, Giulio Cimini, Roberto Benzi, Huixiang Zhang, Zhen Wang and Chao Gao TFWaveFormer: Temporal-Frequency Collaborative Multi-level Wavelet Transfor"&"mer for Dynamic Link Prediction Hantong Feng, Yonggang Wu, Duxin Chen and Wenwu Yu CIFAD: Causal-Invariant Subspace Learning for Few-Shot Anomaly Detection on Dynamic Relational Graphs Xiao Yu, Haolong Xiang, Xiaolong Xu, Qi Lianyong, Zhang Xuyun, Fan We"&"i and Dou Wanchun Fair k-Center Clustering on Massive Social Network Data Streams Longkun Guo, Chaoqi Jia and Chao Chen ") -> Social Event Prediction via Fourier Graph Learning Mingjie Qiu, Zhiyi Tan and Bing-Kun Bao FS_GPlib: Breaking the Web-Scale Barrier — A Unified Acceleration Framework for Graph Propagation Models Chang Guo, Juyuan Zhang, Chang Su, Tianlong Fan and Linyuan Lü Source Localization in Continuous-Time Propagation via Spectral ODE Modeling Dongpeng Hou, Yuchen Wang, Giulio Cimini, Roberto Benzi, Huixiang Zhang, Zhen Wang and Chao Gao TFWaveFormer: Temporal-Frequency Collaborative Multi-level Wavelet Transformer for Dynamic Link Prediction Hantong Feng, Yonggang Wu, Duxin Chen and Wenwu Yu CIFAD: Causal-Invariant Subspace Learning for Few-Shot Anomaly Detection on Dynamic Relational Graphs Xiao Yu, Haolong Xiang, Xiaolong Xu, Qi Lianyong, Zhang Xuyun, Fan Wei and Dou Wanchun Fair k-Center Clustering on Massive Social Network Data Streams Longkun Guo, Chaoqi Jia and Chao Chen | J35: =IFERROR(__xludf.DUMMYFUNCTION("TEXTJOIN(CHAR(10), TRUE,FILTER('Research assignment'!$D:$D,'Research assignment'!$G:$G=J34))"),"TraceLLM: Evaluating and Exploring Large Language Models on Trace Analysis in Microservice-based Web Applications Tong Zhou, Xin Peng, Jie Zhang, Chaofeng Sha, Chenxi Zhang, Zicheng Yuan and Senyu Xie Broken Promise: Differential Analysis of Functional D"&"iscrepancies Between WebAssembly and Native Binaries Xiao Wu, Alan Romano, Liyan Huang, Qiwen Yan, Cai Fu and Weihang Wang Self-Speculative Decoding for On-device MoE Acceleration Peirong Zheng, Wenchao Xu and Haozhao Wang HeteroSim: Towards High-Fideli"&"ty Heterogeneous LLM Training Simulation on GPUs Xiaofei Yue, Fangming Zhao, Fulun Ye, Jiongchi Yu, Zhaoxuan Li, Tingting Li, Ziming Zhao and Jianwei Yin Curiosity Driven Knowledge Retrieval for Mobile Agents Sijia Li, Xiaoyu Tan, Shahir Ali, Niels Schmi"&"dt, Gengchen Ma and Xihe Qiu Prototype Augmentation-based Edge-end Heterogeneous Collaborative Learning Enze Yu, Penghuan Cheng, Haipeng Dai, Haihan Zhang, Sujin Hou, Meng Li, Zhenzhe Zheng, Qiang He and Guihai Chen Octopus: Vehicle-to-Road Collaborativ"&"e Perception for Autonomous Driving with Closed-Loop Fusion Ruikun Luo, Jiadong Zhao, Peize Su, Jieming Yang, Jing Yang, Yuan Gao, Minhui Xue and Xiaoyu Xia ") -> TraceLLM: Evaluating and Exploring Large Language Models on Trace Analysis in Microservice-based Web Applications Tong Zhou, Xin Peng, Jie Zhang, Chaofeng Sha, Chenxi Zhang, Zicheng Yuan and Senyu Xie Broken Promise: Differential Analysis of Functional Discrepancies Between WebAssembly and Native Binaries Xiao Wu, Alan Romano, Liyan Huang, Qiwen Yan, Cai Fu and Weihang Wang Self-Speculative Decoding for On-device MoE Acceleration Peirong Zheng, Wenchao Xu and Haozhao Wang HeteroSim: Towards High-Fidelity Heterogeneous LLM Training Simulation on GPUs Xiaofei Yue, Fangming Zhao, Fulun Ye, Jiongchi Yu, Zhaoxuan Li, Tingting Li, Ziming Zhao and Jianwei Yin Curiosity Driven Knowledge Retrieval for Mobile Agents Sijia Li, Xiaoyu Tan, Shahir Ali, Niels Schmidt, Gengchen Ma and Xihe Qiu Prototype Augmentation-based Edge-end Heterogeneous Collaborative Learning Enze Yu, Penghuan Cheng, Haipeng Dai, Haihan Zhang, Sujin Hou, Meng Li, Zhenzhe Zheng, Qiang He and Guihai Chen Octopus: Vehicle-to-Road Collaborative Perception for Autonomous Driving with Closed-Loop Fusion Ruikun Luo, Jiadong Zhao, Peize Su, Jieming Yang, Jing Yang, Yuan Gao, Minhui Xue and Xiaoyu Xia | K35: =IFERROR(__xludf.DUMMYFUNCTION("TEXTJOIN(CHAR(10), TRUE,FILTER('Research assignment'!$D:$D,'Research assignment'!$G:$G=K34))"),"Optimizing Multi-Turn Interactive Recommendation Agents via Generative Intrinsic Motivation Xueyang Feng, Jiakai Tang, Xu Chen, Quanyu Dai and Zhenhua Dong Unveiling and Simulating Short-Video Addiction Behaviors via Economic Addiction Theory Chen Xu, Zh"&"ipeng Yi, Ruizi Wang, Wenjie Wang, Jun Xu and Maarten de Rijke PRISM: Personalized Recommendation via Information Synergy Module Yutong Li, Xinyi Zhang, Peijie Sun, Letian Sha and Zhongxuan Han Learning on Adaptive Manifolds for Graph Collaborative Filt"&"ering Guangzhi Qi, Guojun Liu and Qi Zhou Room Matters: Dynamic Room-level Collaboration Information Modeling for Live Streaming Recommendation Ke Guo, Changle Qu, Xiao Zhang, Liqin Zhao, Shijun Wang, Yanan Niu and Jun Xu ONE-PASS: Single Forward Pass D"&"ecoding for Listwise Reranking Yingpeng Du, Zhu Sun, Tianjun Wei and Jie Zhang Personalized Learning Path Planning through Goal-Driven Learner State Modeling Joy Jia Yin Lim, Ye He, Jifan Yu, Xin Cong, Daniel Zhang-Li, Zhiyuan Liu, Huiqin Liu, Lei Hou, J"&"uanzi Li and Bin Xu Bridging Time and Domains: A Time-aware Framework for Cross-Domain Sequential Recommendation Zemu Liu, Zhida Qin, Pengzhan Zhou, Tianyu Huang and Gangyi Ding CC-OR-Net: A Unified Framework for LTV Prediction through Structural Decoup"&"ling Mingyu Zhao, Haoran Bai, Yu Tian, Bing Zhu and Hengliang Luo KE-FedRS: Tackling Data Sparsity in Federated Recommendation via Knowledge Enhancement Jiayu Bao, Hongjian Shi, Guanyu Zhang, Rui Zhou, Haozhao Wang and Yuan Liu Long Story Short: Auditin"&"g U.S. Political Polarization in Recommendations for Long- vs. Short-form Videos on YouTube Shaokang Jiang, Arshia Arya, Seoyoung Kweon, Ivan Liang, Deepak Kumar and Kristen Vaccaro ") -> Optimizing Multi-Turn Interactive Recommendation Agents via Generative Intrinsic Motivation Xueyang Feng, Jiakai Tang, Xu Chen, Quanyu Dai and Zhenhua Dong Unveiling and Simulating Short-Video Addiction Behaviors via Economic Addiction Theory Chen Xu, Zhipeng Yi, Ruizi Wang, Wenjie Wang, Jun Xu and Maarten de Rijke PRISM: Personalized Recommendation via Information Synergy Module Yutong Li, Xinyi Zhang, Peijie Sun, Letian Sha and Zhongxuan Han Learning on Adaptive Manifolds for Graph Collaborative Filtering Guangzhi Qi, Guojun Liu and Qi Zhou Room Matters: Dynamic Room-level Collaboration Information Modeling for Live Streaming Recommendation Ke Guo, Changle Qu, Xiao Zhang, Liqin Zhao, Shijun Wang, Yanan Niu and Jun Xu ONE-PASS: Single Forward Pass Decoding for Listwise Reranking Yingpeng Du, Zhu Sun, Tianjun Wei and Jie Zhang Personalized Learning Path Planning through Goal-Driven Learner State Modeling Joy Jia Yin Lim, Ye He, Jifan Yu, Xin Cong, Daniel Zhang-Li, Zhiyuan Liu, Huiqin Liu, Lei Hou, Juanzi Li and Bin Xu Bridging Time and Domains: A Time-aware Framework for Cross-Domain Sequential Recommendation Zemu Liu, Zhida Qin, Pengzhan Zhou, Tianyu Huang and Gangyi Ding CC-OR-Net: A Unified Framework for LTV Prediction through Structural Decoupling Mingyu Zhao, Haoran Bai, Yu Tian, Bing Zhu and Hengliang Luo KE-FedRS: Tackling Data Sparsity in Federated Recommendation via Knowledge Enhancement Jiayu Bao, Hongjian Shi, Guanyu Zhang, Rui Zhou, Haozhao Wang and Yuan Liu Long Story Short: Auditing U.S. Political Polarization in Recommendations for Long- vs. Short-form Videos on YouTube Shaokang Jiang, Arshia Arya, Seoyoung Kweon, Ivan Liang, Deepak Kumar and Kristen Vaccaro | L35: =IFERROR(__xludf.DUMMYFUNCTION("TEXTJOIN(CHAR(10), TRUE,FILTER('Research assignment'!$D:$D,'Research assignment'!$G:$G=L34))"),"Thinking Bidirectionally: A Reasoning and Self-Correction Approach for Text-Based Event Prediction with Large Language Models Liwei Qian, Hang Zhang, Yiheng Wu, Yanmin Li, Mengna Zhu, Lihua Liu and Jibing Wu Hyperbolic Multimodal Generative Representatio"&"n Learning for Generalized Zero-Shot Multimodal Information Extraction Baohang Zhou, Kehui Song, Rize Jin, Yu Zhao, Xuhui Sui, Xinying Qian, Xingyue Guo and Ying Zhang MIDE: Multimodal Dialogue Emotion Recognition via Mutual Information Enhancement and D"&"ynamic Modality Selection Zhibo Zhang, Jianjun Li and Zhiyuan Ma GFMixer: Decoupled Temporal Gradient and Fourier-Aware Attention for Time Series Forecasting Lin Zhang, Qing Li and Jingmei Zhao MIGC-CMamba: Cross-Domain Mamba with Multi-Scale Imaging an"&"d Granular-Ball Computing for Traffic Flow Prediction Wenxia Chang, Chao Zhang, Wentao Li and Deyu Li STaR: Towards Effective and Stable Table Reasoning via Slow-Thinking Large Language Models Huajian Zhang, Mingyue Cheng, Yucong Luo and Xiaoyu Tao Enha"&"ncing Large Language Models for Time-Series Forecasting via Vector-Injected In-Context Learning Jianqi Zhang, Jingyao Wang, Wenwen Qiang, Fanjiang Xu and Changwen Zheng ") -> Thinking Bidirectionally: A Reasoning and Self-Correction Approach for Text-Based Event Prediction with Large Language Models Liwei Qian, Hang Zhang, Yiheng Wu, Yanmin Li, Mengna Zhu, Lihua Liu and Jibing Wu Hyperbolic Multimodal Generative Representation Learning for Generalized Zero-Shot Multimodal Information Extraction Baohang Zhou, Kehui Song, Rize Jin, Yu Zhao, Xuhui Sui, Xinying Qian, Xingyue Guo and Ying Zhang MIDE: Multimodal Dialogue Emotion Recognition via Mutual Information Enhancement and Dynamic Modality Selection Zhibo Zhang, Jianjun Li and Zhiyuan Ma GFMixer: Decoupled Temporal Gradient and Fourier-Aware Attention for Time Series Forecasting Lin Zhang, Qing Li and Jingmei Zhao MIGC-CMamba: Cross-Domain Mamba with Multi-Scale Imaging and Granular-Ball Computing for Traffic Flow Prediction Wenxia Chang, Chao Zhang, Wentao Li and Deyu Li STaR: Towards Effective and Stable Table Reasoning via Slow-Thinking Large Language Models Huajian Zhang, Mingyue Cheng, Yucong Luo and Xiaoyu Tao Enhancing Large Language Models for Time-Series Forecasting via Vector-Injected In-Context Learning Jianqi Zhang, Jingyao Wang, Wenwen Qiang, Fanjiang Xu and Changwen Zheng | M35: =IFERROR(__xludf.DUMMYFUNCTION("TEXTJOIN(CHAR(10), TRUE,FILTER('Industry assignment'!$D:$D,'Industry assignment'!$G:$G=M34))"),"GPU-accelerated Multi-relational Parallel Graph Retrieval for Web-scale Recommendations Zhuoning Guo, Guangxing Chen, Qian Gao, Xiaochao Liao, Jianjia Zheng, Lu Shen and Hao Liu Accurate and Efficient Personalized Query Rewriting in Baidu Search Xu Chu, "&"Angela Li, Jiaming Zhang, Wei Li, Zhijie Tan, Dawei Yin, Shuaiqiang Wang and Daiting Shi PLUM: Adapting Pre-trained Language Models for Industrial-scale Generative Recommendations Ruining He, Lukasz Heldt, Lichan Hong, Raghunandan Keshavan, Shifan Mao, N"&"ikhil Mehta, Zhengyang Su, Alicia Tsai, Yueqi Wang, Shao-Chuan Wang, Xinyang Yi, Lexi Baugher, Baykal Cakici, Ed Chi, Cristos Goodrow, Ningren Han, He Ma, Romer Rosales, Abby Van Soest, Devansh Tandon, Su-Lin Wu, Weilong Yang and Yilin Zheng A Creator-Aw"&"are Recommendation System for Content Platforms Wenjing Li, Jiang Rong, Yao Hu, Zhenzhe Zheng and Fan Wu ") -> GPU-accelerated Multi-relational Parallel Graph Retrieval for Web-scale Recommendations Zhuoning Guo, Guangxing Chen, Qian Gao, Xiaochao Liao, Jianjia Zheng, Lu Shen and Hao Liu Accurate and Efficient Personalized Query Rewriting in Baidu Search Xu Chu, Angela Li, Jiaming Zhang, Wei Li, Zhijie Tan, Dawei Yin, Shuaiqiang Wang and Daiting Shi PLUM: Adapting Pre-trained Language Models for Industrial-scale Generative Recommendations Ruining He, Lukasz Heldt, Lichan Hong, Raghunandan Keshavan, Shifan Mao, Nikhil Mehta, Zhengyang Su, Alicia Tsai, Yueqi Wang, Shao-Chuan Wang, Xinyang Yi, Lexi Baugher, Baykal Cakici, Ed Chi, Cristos Goodrow, Ningren Han, He Ma, Romer Rosales, Abby Van Soest, Devansh Tandon, Su-Lin Wu, Weilong Yang and Yilin Zheng A Creator-Aware Recommendation System for Content Platforms Wenjing Li, Jiang Rong, Yao Hu, Zhenzhe Zheng and Fan Wu | N35: =IFERROR(__xludf.DUMMYFUNCTION("TEXTJOIN(CHAR(10), TRUE,FILTER('Web4Good assignment'!$D:$D,'Web4Good assignment'!$G:$G=N34))"),"Spiking Graph Predictive Coding for Reliable OOD Generalization Jing Ren, Jiapeng Du, Bowen Li, Ziqi Xu, Xin Zheng, Hong Jia, Suyu Ma, Xiwei Xu and Feng Xia Boosting Large Language Models for Mental Manipulation Detection via Data Augmentation and Distil"&"lation Yuansheng Gao, Peng Gao, Han Bao, Bin Li, Jixiang Luo, Zonghui Wang and Wenzhi Chen ReRule: Temporal Rule-Augmented Language Modeling for Causal Event Chain Completion Wei Zhang, Shufeng Hao, Chongyang Shi, Usman Naseem, Jinyan Liu and Ziyu Li In"&"dicAG: An Explainable Agentic Framework for Indic-Multilingual Multidimensional Aggression Detection Swapnil Mane, Rajesh Sharma and Suman Kundu GRAND: A Robust Diffusion Framework for Multi-Granularity Graph Anomaly Detection in Web Platforms Maolin Wan"&"g, Beining Bao, Hongyu Chen, Zichun Liu, Lang Fu, Jun Chu, Langzhang Liang and Zenglin Xu Accurate Trajectory Recovery in Underserved Areas via Location Inference from Web Crowdsourced Data Tangwei Ye, Liang Hu, Zhongyuan Lai, Qi Zhang, Yiming Wu, Jiaxin"&"g Miao, Yijun Yang and Kun Yi Modeling Multimodal Information Cascade on Social Media with Interpretable Mixture of Experts Xin Jing, Zeyu Shi, Zhangtao Cheng, Yichen Jing, Yuhuan Lu, Bangchao Deng and Dingqi Yang TheraMind: A Strategic and Adaptive Age"&"nt for Longitudinal Psychological Counseling He Hu, Chiyuan Ma, Qianning Wang, Liu Lin, Yucheng Zhou, Laizhong Cui, Fei Ma and Qi Tian When Ads Become Profiles: Uncovering the Invisible Risk of Web Advertising at Scale with LLMs Baiyu Chen, Benjamin Tag,"&" Hao Xue, Daniel Angus and Flora Salim TravelReasoner: Leveraging Large Reasoning Models to Address Mobility Data Gap Peijie Liu, Fengli Xu and Yong Li Longitudinal Trends in Global Climate Change Discourse on Facebook Md. Rafiul Biswas, Mabrouka Bessgh"&"aier, Shimaa Ibrahim, George Mikros and Wajdi Zaghouani Bowling with ChatGPT: On the Evolving User Interactions with Conversational AI Systems Sai Keerthana Karnam, Abhisek Dash, Krishna Gummadi, Animesh Mukherjee, Ingmar Weber and Savvas Zannettou Invi"&"sible Walls in Cities: Designing LLM Agent to Predict Urban Segregation Experience with Social Media Content Bingbing Fan, Lin Chen, Songwei Li, Jian Yuan, Fengli Xu, Pan Hui and Yong Li How Green Is Your Login? A Cross-Protocol Benchmark of Authenticati"&"on Energy & Latency Weizheng Wang, Qipeng Xie, Shiyu Wang, Qingqing Ye, Kaishun Wu and Haibo Hu MultiCheck: Strengthening Web Trust with Unified Multimodal Fact Verification Aditya Kishore, Gaurav Kumar and Jasabanta Patro ") -> Spiking Graph Predictive Coding for Reliable OOD Generalization Jing Ren, Jiapeng Du, Bowen Li, Ziqi Xu, Xin Zheng, Hong Jia, Suyu Ma, Xiwei Xu and Feng Xia Boosting Large Language Models for Mental Manipulation Detection via Data Augmentation and Distillation Yuansheng Gao, Peng Gao, Han Bao, Bin Li, Jixiang Luo, Zonghui Wang and Wenzhi Chen ReRule: Temporal Rule-Augmented Language Modeling for Causal Event Chain Completion Wei Zhang, Shufeng Hao, Chongyang Shi, Usman Naseem, Jinyan Liu and Ziyu Li IndicAG: An Explainable Agentic Framework for Indic-Multilingual Multidimensional Aggression Detection Swapnil Mane, Rajesh Sharma and Suman Kundu GRAND: A Robust Diffusion Framework for Multi-Granularity Graph Anomaly Detection in Web Platforms Maolin Wang, Beining Bao, Hongyu Chen, Zichun Liu, Lang Fu, Jun Chu, Langzhang Liang and Zenglin Xu Accurate Trajectory Recovery in Underserved Areas via Location Inference from Web Crowdsourced Data Tangwei Ye, Liang Hu, Zhongyuan Lai, Qi Zhang, Yiming Wu, Jiaxing Miao, Yijun Yang and Kun Yi Modeling Multimodal Information Cascade on Social Media with Interpretable Mixture of Experts Xin Jing, Zeyu Shi, Zhangtao Cheng, Yichen Jing, Yuhuan Lu, Bangchao Deng and Dingqi Yang TheraMind: A Strategic and Adaptive Agent for Longitudinal Psychological Counseling He Hu, Chiyuan Ma, Qianning Wang, Liu Lin, Yucheng Zhou, Laizhong Cui, Fei Ma and Qi Tian When Ads Become Profiles: Uncovering the Invisible Risk of Web Advertising at Scale with LLMs Baiyu Chen, Benjamin Tag, Hao Xue, Daniel Angus and Flora Salim TravelReasoner: Leveraging Large Reasoning Models to Address Mobility Data Gap Peijie Liu, Fengli Xu and Yong Li Longitudinal Trends in Global Climate Change Discourse on Facebook Md. Rafiul Biswas, Mabrouka Bessghaier, Shimaa Ibrahim, George Mikros and Wajdi Zaghouani Bowling with ChatGPT: On the Evolving User Interactions with Conversational AI Systems Sai Keerthana Karnam, Abhisek Dash, Krishna Gummadi, Animesh Mukherjee, Ingmar Weber and Savvas Zannettou Invisible Walls in Cities: Designing LLM Agent to Predict Urban Segregation Experience with Social Media Content Bingbing Fan, Lin Chen, Songwei Li, Jian Yuan, Fengli Xu, Pan Hui and Yong Li How Green Is Your Login? A Cross-Protocol Benchmark of Authentication Energy & Latency Weizheng Wang, Qipeng Xie, Shiyu Wang, Qingqing Ye, Kaishun Wu and Haibo Hu MultiCheck: Strengthening Web Trust with Unified Multimodal Fact Verification Aditya Kishore, Gaurav Kumar and Jasabanta Patro
A36: 46205
A37: 10:00 - 11:00 | B37: Keynote #3: Alistair Moffat
A38: 11:00 - 11:30 | B38: Break
A39: 11:30 - 13:00 | B39: Econ3 | C39: Graph3 | D39: Graph9 | E39: Search3 | F39: Semantics7 | G39: Social3 | H39: Systems3 | I39: Security5 | J39: Mining3 | K39: RecSys3 | L39: Industry4 | M39: Industry5 | N39: Web4Good1
B40: =IFERROR(__xludf.DUMMYFUNCTION("TEXTJOIN(CHAR(10), TRUE,FILTER('Sessions Counts'!$B:$B,'Sessions Counts'!$A:$A=B39))"),"Economics of Generative AI") -> Economics of Generative AI | C40: =IFERROR(__xludf.DUMMYFUNCTION("TEXTJOIN(CHAR(10), TRUE,FILTER('Sessions Counts'!$B:$B,'Sessions Counts'!$A:$A=C39))"),"Graph Neural Networks 1") -> Graph Neural Networks 1 | D40: =IFERROR(__xludf.DUMMYFUNCTION("TEXTJOIN(CHAR(10), TRUE,FILTER('Sessions Counts'!$B:$B,'Sessions Counts'!$A:$A=D39))"),"Graph Foundation Models 2") -> Graph Foundation Models 2 | E40: =IFERROR(__xludf.DUMMYFUNCTION("TEXTJOIN(CHAR(10), TRUE,FILTER('Sessions Counts'!$B:$B,'Sessions Counts'!$A:$A=E39))"),"Question Answering & Knowledge Graphs") -> Question Answering & Knowledge Graphs | F40: =IFERROR(__xludf.DUMMYFUNCTION("TEXTJOIN(CHAR(10), TRUE,FILTER('Sessions Counts'!$B:$B,'Sessions Counts'!$A:$A=F39))"),"Multimodal Knowledge Graphs") -> Multimodal Knowledge Graphs | G40: =IFERROR(__xludf.DUMMYFUNCTION("TEXTJOIN(CHAR(10), TRUE,FILTER('Sessions Counts'!$B:$B,'Sessions Counts'!$A:$A=G39))"),"Trust, Safety, and Content Moderation") -> Trust, Safety, and Content Moderation | H40: =IFERROR(__xludf.DUMMYFUNCTION("TEXTJOIN(CHAR(10), TRUE,FILTER('Sessions Counts'!$B:$B,'Sessions Counts'!$A:$A=H39))"),"Cloud–Edge AI Systems") -> Cloud–Edge AI Systems | I40: =IFERROR(__xludf.DUMMYFUNCTION("TEXTJOIN(CHAR(10), TRUE,FILTER('Sessions Counts'!$B:$B,'Sessions Counts'!$A:$A=I39))"),"Security & Privacy for LLM I") -> Security & Privacy for LLM I | J40: =IFERROR(__xludf.DUMMYFUNCTION("TEXTJOIN(CHAR(10), TRUE,FILTER('Sessions Counts'!$B:$B,'Sessions Counts'!$A:$A=J39))"),"Misinformation, Content Authenticity, and Social Mining") -> Misinformation, Content Authenticity, and Social Mining | K40: =IFERROR(__xludf.DUMMYFUNCTION("TEXTJOIN(CHAR(10), TRUE,FILTER('Sessions Counts'!$B:$B,'Sessions Counts'!$A:$A=K39))"),"Graph-Based Collaborative Filtering") -> Graph-Based Collaborative Filtering | L40: =IFERROR(__xludf.DUMMYFUNCTION("TEXTJOIN(CHAR(10), TRUE,FILTER('Industry assignment'!$B:$B,'Industry assignment'!$A:$A=L39))"),"LLM Efficiency, Reasoning & System Logs") -> LLM Efficiency, Reasoning & System Logs | M40: =IFERROR(__xludf.DUMMYFUNCTION("TEXTJOIN(CHAR(10), TRUE,FILTER('Sessions Counts'!$B:$B,'Sessions Counts'!$A:$A=M39))"),"Logistics, Travel & Geospatial Services") -> Logistics, Travel & Geospatial Services | N40: =IFERROR(__xludf.DUMMYFUNCTION("TEXTJOIN(CHAR(10), TRUE,FILTER('Sessions Counts'!$B:$B,'Sessions Counts'!$A:$A=N39))"),"Trustworthy, Fair & Safe Web AI") -> Trustworthy, Fair & Safe Web AI
B41: =IFERROR(__xludf.DUMMYFUNCTION("TEXTJOIN(CHAR(10), TRUE,FILTER('Research assignment'!$D:$D,'Research assignment'!$F:$F=B39))"),"PMIScore: An Unsupervised Approach to Quantify Dialogue Engagement Yongkang Guo, Yuqing Kong and Zhihuan Huang Strategic Content Creation with GenAI: To Share or Not to Share? Gur Keinan and Omer Ben-Porat Pay for The Second-Best Service: A Game-Theoret"&"ic Approach against Dishonest LLM Providers Yuhan Cao, Yu Wang, Sitong Liu, Miao Li, Yixin Tao and Tianxing He Position Auctions in AI-Generated Content Santiago Balseiro, Kshipra Bhawalkar, Yuan Deng, Zhe Feng, Jieming Mao, Aranyak Mehta, Vahab Mirrokni"&", Renato Paes Leme, Di Wang and Song Zuo How to Strategize Human Content Creation in the Era of GenAI? Seyed Esmaeili, Kevin Lim, Kshipra Bhawalkar, Zhe Feng, Di Wang and Haifeng Xu ") -> PMIScore: An Unsupervised Approach to Quantify Dialogue Engagement Yongkang Guo, Yuqing Kong and Zhihuan Huang Strategic Content Creation with GenAI: To Share or Not to Share? Gur Keinan and Omer Ben-Porat Pay for The Second-Best Service: A Game-Theoretic Approach against Dishonest LLM Providers Yuhan Cao, Yu Wang, Sitong Liu, Miao Li, Yixin Tao and Tianxing He Position Auctions in AI-Generated Content Santiago Balseiro, Kshipra Bhawalkar, Yuan Deng, Zhe Feng, Jieming Mao, Aranyak Mehta, Vahab Mirrokni, Renato Paes Leme, Di Wang and Song Zuo How to Strategize Human Content Creation in the Era of GenAI? Seyed Esmaeili, Kevin Lim, Kshipra Bhawalkar, Zhe Feng, Di Wang and Haifeng Xu | C41: =IFERROR(__xludf.DUMMYFUNCTION("TEXTJOIN(CHAR(10), TRUE,FILTER('Research assignment'!$D:$D,'Research assignment'!$F:$F=C39))"),"Heterophily-Agnostic Hypergraph Neural Networks with Riemannian Local Exchanger Li Sun, Ming Zhang, Wenxin Jin, Zhongtian Sun, Zhenhao Huang, Hao Peng, Sen Su and Philip Yu IVQ-GNN: Mitigating Performance Gaps from Graph Connection Pattern Inconsistency "&"via Vector Quantization Di Jin, Yixuan Du, Cuiying Huo, Xiaotong Huang, Ruqiong Zhang, Xiaobao Wang and Yawen Li Frequency-Corrupt Based Graph Self-Supervised Learning Haojie Li, Mengjiao Zhang, Guanfeng Liu, Qiang Hu, Yan Wang and Junwei Du Discrete Di"&"ffusion-Based Model-Level Explanation of Heterogeneous GNNs with Node Features Pallabee Das and Stefan Heindorf SliceGX: Layer-wise GNN Explanation with Model-slicing Cibo Yu, Tingting Zhu, Tingyang Chen, Yinghui Wu, Arijit Khan and Xiangyu Ke ") -> Heterophily-Agnostic Hypergraph Neural Networks with Riemannian Local Exchanger Li Sun, Ming Zhang, Wenxin Jin, Zhongtian Sun, Zhenhao Huang, Hao Peng, Sen Su and Philip Yu IVQ-GNN: Mitigating Performance Gaps from Graph Connection Pattern Inconsistency via Vector Quantization Di Jin, Yixuan Du, Cuiying Huo, Xiaotong Huang, Ruqiong Zhang, Xiaobao Wang and Yawen Li Frequency-Corrupt Based Graph Self-Supervised Learning Haojie Li, Mengjiao Zhang, Guanfeng Liu, Qiang Hu, Yan Wang and Junwei Du Discrete Diffusion-Based Model-Level Explanation of Heterogeneous GNNs with Node Features Pallabee Das and Stefan Heindorf SliceGX: Layer-wise GNN Explanation with Model-slicing Cibo Yu, Tingting Zhu, Tingyang Chen, Yinghui Wu, Arijit Khan and Xiangyu Ke | D41: =IFERROR(__xludf.DUMMYFUNCTION("TEXTJOIN(CHAR(10), TRUE,FILTER('Research assignment'!$D:$D,'Research assignment'!$F:$F=D39))"),"Toward Graph-Tokenizing Large Language Models with Reconstructive Graph Instruction Tuning Zhongjian Zhang, Xiao Wang, Mengmei Zhang, Jiarui Tan and Chuan Shi Beyond Single-Granularity Prompts: A Multi-Scale Chain-of-Thought Prompt Learning for Graph Ziy"&"u Zheng, Yaming Yang, Ziyu Guan, Wei Zhao, Xinyan Huang and Weigang Lu Riemannian Graph Tokenizer for Structural Knowledge Transfer Qimin Zhou, Haibo Liu, Yujie Wang, Li Sun and Chuan Shi LEDA: Latent Semantic Distribution Alignment for Multi-domain Gra"&"ph Pre-training Lianze Shan, Jitao Zhao, Dongxiao He, Siqi Liu, Jiaxu Cui and Weixiong Zhang Towards A Universal Graph Structural Encoder Jialin Chen, Haolan Zuo, Haoyu Wang, Siqi Miao, Pan Li and Rex Ying ") -> Toward Graph-Tokenizing Large Language Models with Reconstructive Graph Instruction Tuning Zhongjian Zhang, Xiao Wang, Mengmei Zhang, Jiarui Tan and Chuan Shi Beyond Single-Granularity Prompts: A Multi-Scale Chain-of-Thought Prompt Learning for Graph Ziyu Zheng, Yaming Yang, Ziyu Guan, Wei Zhao, Xinyan Huang and Weigang Lu Riemannian Graph Tokenizer for Structural Knowledge Transfer Qimin Zhou, Haibo Liu, Yujie Wang, Li Sun and Chuan Shi LEDA: Latent Semantic Distribution Alignment for Multi-domain Graph Pre-training Lianze Shan, Jitao Zhao, Dongxiao He, Siqi Liu, Jiaxu Cui and Weixiong Zhang Towards A Universal Graph Structural Encoder Jialin Chen, Haolan Zuo, Haoyu Wang, Siqi Miao, Pan Li and Rex Ying | E41: =IFERROR(__xludf.DUMMYFUNCTION("TEXTJOIN(CHAR(10), TRUE,FILTER('Research assignment'!$D:$D,'Research assignment'!$F:$F=E39))"),"CompactRAG: Reducing LLM Calls and Token Overhead in Multi-Hop Question Answering Hao Yang, Zhiyu Yang, Xvpeng Zhang, Wei Wei, Yunjie Zhang and Lin Yang KEPo: Knowledge Evolution Poison on Graph-based Retrieval-Augmented Generation Qizhi Chen, Chao Qi, Y"&"ihong Huang, Muquan Li, Rongzheng Wang, Dongyang Zhang, Ke Qin and Shuang Liang Inferential Question Answering Jamshid Mozafari, Hamed Zamani, Guido Zuccon and Adam Jatowt RPO-RAG: Aligning Small LLMs with Relation-aware Preference Optimization for Know"&"ledge Graph Question Answering Kaehyun Um, Kyuhwan Yeom, Haerim Yang, Minyoung Choi, Hyeongjun Yang and Kyong-Ho Lee ") -> CompactRAG: Reducing LLM Calls and Token Overhead in Multi-Hop Question Answering Hao Yang, Zhiyu Yang, Xvpeng Zhang, Wei Wei, Yunjie Zhang and Lin Yang KEPo: Knowledge Evolution Poison on Graph-based Retrieval-Augmented Generation Qizhi Chen, Chao Qi, Yihong Huang, Muquan Li, Rongzheng Wang, Dongyang Zhang, Ke Qin and Shuang Liang Inferential Question Answering Jamshid Mozafari, Hamed Zamani, Guido Zuccon and Adam Jatowt RPO-RAG: Aligning Small LLMs with Relation-aware Preference Optimization for Knowledge Graph Question Answering Kaehyun Um, Kyuhwan Yeom, Haerim Yang, Minyoung Choi, Hyeongjun Yang and Kyong-Ho Lee | F41: =IFERROR(__xludf.DUMMYFUNCTION("TEXTJOIN(CHAR(10), TRUE,FILTER('Research assignment'!$D:$D,'Research assignment'!$F:$F=F39))"),"Multi-Granularity Multi-Modal Knowledge Graph Representation Learning via Subgraph-Aware Adaptive Fusion and Hierarchical Relation Modeling Peining Li, Meiyu Liang, Wei Huang, Junping Du, Zhe Xue, Guanhua Ye, Wu Liu and Lei Shi Grasp: Refining Semantic G"&"raphs into Purified Knowledge for Cross-Modal Communication Liang Chen, Xiaoding Wang, Limei Lin, Dajin Wang, Zhiquan Liu and Jie Wu Enhancing Multi-Modal Entity Alignment via Multi-Grained Decision Fusion Yu Xing, Qizhuo Xie, You Lv, Ziyang Zhou, Qianzi"&" Hou, Qing Gu, Bin Chong and Tieke He Relation-Aware Multimodal Analogical Reasoning with Modality Fingerprints and Adaptive Gating Ruofan Wang, Zijian Huang, Qiqi Wang, Yuchen Su, Robert Amor, Kaiqi Zhao and Meng-Fen Chiang DyMRL: Dynamic Multispace Re"&"presentation Learning for Multimodal Event Forecasting in Knowledge Graph Feng Zhao, Kangzheng Liu, Teng Peng, Yu Yang and Guandong Xu ") -> Multi-Granularity Multi-Modal Knowledge Graph Representation Learning via Subgraph-Aware Adaptive Fusion and Hierarchical Relation Modeling Peining Li, Meiyu Liang, Wei Huang, Junping Du, Zhe Xue, Guanhua Ye, Wu Liu and Lei Shi Grasp: Refining Semantic Graphs into Purified Knowledge for Cross-Modal Communication Liang Chen, Xiaoding Wang, Limei Lin, Dajin Wang, Zhiquan Liu and Jie Wu Enhancing Multi-Modal Entity Alignment via Multi-Grained Decision Fusion Yu Xing, Qizhuo Xie, You Lv, Ziyang Zhou, Qianzi Hou, Qing Gu, Bin Chong and Tieke He Relation-Aware Multimodal Analogical Reasoning with Modality Fingerprints and Adaptive Gating Ruofan Wang, Zijian Huang, Qiqi Wang, Yuchen Su, Robert Amor, Kaiqi Zhao and Meng-Fen Chiang DyMRL: Dynamic Multispace Representation Learning for Multimodal Event Forecasting in Knowledge Graph Feng Zhao, Kangzheng Liu, Teng Peng, Yu Yang and Guandong Xu | G41: =IFERROR(__xludf.DUMMYFUNCTION("TEXTJOIN(CHAR(10), TRUE,FILTER('Research assignment'!$D:$D,'Research assignment'!$F:$F=G39))"),"Open or Blocked Skies? Community Moderation Practices in Bluesky Saidu Sokoto, Leonhard Balduf, Onur Ascigil, Gareth Tyson, Ignacio Castro, Björn Scheuermann, Andrea Baronchelli and Michał Król Pattern-aware Illicit Account Detection based on User Behavi"&"or Sequences Zehao Wang, Lanjun Wang, Fuxia Guo and Yanjie Dong Unmasking Bots in Higher Dimensions: Message Passing over Simplexes for Bot Detection Fangfang Li, Huihui Zhang, Xin Zhang and Wei Wu ContiGuard: A Framework for Continual Toxicity Detectio"&"n Against Evolving Evasive Perturbations Hankun Kang, Xin Miao, Jianhao Chen, Jintao Wen, Mayi Xu, Weiyu Zhang, Wenpeng Lu and Tieyun Qian They Said Memes Were Harmless --- We Found the Ones That Hurt: Decoding Jokes, Symbols, and Cultural References Sah"&"il Tripathi, Gautam Siddharth Kashyap, Mehwish Nasim, Jian Yang, Jiechao Gao and Usman Naseem ") -> Open or Blocked Skies? Community Moderation Practices in Bluesky Saidu Sokoto, Leonhard Balduf, Onur Ascigil, Gareth Tyson, Ignacio Castro, Björn Scheuermann, Andrea Baronchelli and Michał Król Pattern-aware Illicit Account Detection based on User Behavior Sequences Zehao Wang, Lanjun Wang, Fuxia Guo and Yanjie Dong Unmasking Bots in Higher Dimensions: Message Passing over Simplexes for Bot Detection Fangfang Li, Huihui Zhang, Xin Zhang and Wei Wu ContiGuard: A Framework for Continual Toxicity Detection Against Evolving Evasive Perturbations Hankun Kang, Xin Miao, Jianhao Chen, Jintao Wen, Mayi Xu, Weiyu Zhang, Wenpeng Lu and Tieyun Qian They Said Memes Were Harmless --- We Found the Ones That Hurt: Decoding Jokes, Symbols, and Cultural References Sahil Tripathi, Gautam Siddharth Kashyap, Mehwish Nasim, Jian Yang, Jiechao Gao and Usman Naseem | H41: =IFERROR(__xludf.DUMMYFUNCTION("TEXTJOIN(CHAR(10), TRUE,FILTER('Research assignment'!$D:$D,'Research assignment'!$F:$F=H39))"),"Wiseswap: Elastic Datacenter Network-Aware Disaggregated Memory for Multi-Tenant Cloud Mingxuan Liu, Jianhua Gu, Tianhai Zhao and Dong Sun LaTune: Lightweight and Adaptive Configuration Tuning for LLM Inference on Edge Devices Siqi Zhong, Mugeng Liu, Hai"&"yang Shen, Chongyang Pan and Yun Ma EdgeGen: Efficient LLM-Empowered Model Generation with Quantization-Aware NAS Yingqi Peng, Wenhao Zhou, Kaijie Gong, Yang Liu, Yi Gao and Wei Dong BeeQoS: A Cloud-Native QoS System for Adaptive and Scalable Multi-Prio"&"rity Bandwidth Guarantees Jinyao Liu, Si Wu, Haoyuan Ma, Chaoqun Li, Hongjing Yu, Dingyi Jia, Feng Li and Pengfei Hu A Structure-Agnostic Co-Tuning Framework for LLMs and SLMs in Cloud-Edge Systems Yuze Liu, Yunhan Wang, Tiehua Zhang, Zhishu Shen, Cheng "&"Peng, Libing Wu, Feng Xia and Jiong Jin ") -> Wiseswap: Elastic Datacenter Network-Aware Disaggregated Memory for Multi-Tenant Cloud Mingxuan Liu, Jianhua Gu, Tianhai Zhao and Dong Sun LaTune: Lightweight and Adaptive Configuration Tuning for LLM Inference on Edge Devices Siqi Zhong, Mugeng Liu, Haiyang Shen, Chongyang Pan and Yun Ma EdgeGen: Efficient LLM-Empowered Model Generation with Quantization-Aware NAS Yingqi Peng, Wenhao Zhou, Kaijie Gong, Yang Liu, Yi Gao and Wei Dong BeeQoS: A Cloud-Native QoS System for Adaptive and Scalable Multi-Priority Bandwidth Guarantees Jinyao Liu, Si Wu, Haoyuan Ma, Chaoqun Li, Hongjing Yu, Dingyi Jia, Feng Li and Pengfei Hu A Structure-Agnostic Co-Tuning Framework for LLMs and SLMs in Cloud-Edge Systems Yuze Liu, Yunhan Wang, Tiehua Zhang, Zhishu Shen, Cheng Peng, Libing Wu, Feng Xia and Jiong Jin | I41: =IFERROR(__xludf.DUMMYFUNCTION("TEXTJOIN(CHAR(10), TRUE,FILTER('Research assignment'!$D:$D,'Research assignment'!$F:$F=I39))"),"ProvGuard: Logic-Aware Multi-View Contrastive Learning for Robust and Efficient Host Threat Detection Anyuan Sang, Li Yang, Lu Zhou, Cheng Zhou, Junbo Jia and Huipeng Yang Re-understanding Graph Unlearning through Memorization Pengfei Ding, Yan Wang and "&"Guanfeng Liu Towards Robust Detection of Chinese Toxic Variants via Dynamic Knowledge Graph–LLM Reasoning Shaochen Yang, Kefei Zhou and Wei Xu When Reasoning Leaks Membership: Membership Inference Attack on Black-box Large Reasoning Models Ruihan Hu, Yu"&"-Ming Shang, Wei Luo, Ye Tao and Xi Zhang Unequal Vulnerability: The Differential Impact of Label Flipping Attacks Across Classes Pinlong Zhao, Mengyang Li, Pengfei Jiao, Huijun Tang and Ou Wu ") -> ProvGuard: Logic-Aware Multi-View Contrastive Learning for Robust and Efficient Host Threat Detection Anyuan Sang, Li Yang, Lu Zhou, Cheng Zhou, Junbo Jia and Huipeng Yang Re-understanding Graph Unlearning through Memorization Pengfei Ding, Yan Wang and Guanfeng Liu Towards Robust Detection of Chinese Toxic Variants via Dynamic Knowledge Graph–LLM Reasoning Shaochen Yang, Kefei Zhou and Wei Xu When Reasoning Leaks Membership: Membership Inference Attack on Black-box Large Reasoning Models Ruihan Hu, Yu-Ming Shang, Wei Luo, Ye Tao and Xi Zhang Unequal Vulnerability: The Differential Impact of Label Flipping Attacks Across Classes Pinlong Zhao, Mengyang Li, Pengfei Jiao, Huijun Tang and Ou Wu | J41: =IFERROR(__xludf.DUMMYFUNCTION("TEXTJOIN(CHAR(10), TRUE,FILTER('Research assignment'!$D:$D,'Research assignment'!$F:$F=J39))"),"PAMAS: Self-Adaptive Multi-Agent System with Perspective Aggregation for Misinformation Detection Zongwei Wang, Min Gao, Junliang Yu, Tong Chen and Chenghua Lin TrueLens: Video Fake News Detection with Dual Level Evidence Gathering and Consolidation Juny"&"i Chen, Qian Liu, Jing Sun and Yi Zhang Is Misinformation More Open? A Study of robots.txt Gatekeeping on the Web Nicolas Steinacker-Olsztyn, Devashish Gosain and Ha Dao From Manipulation to Mistrust: Explaining Diverse Micro-Video Misinformation for Ro"&"bust Debunking in the Wild Zhi Zeng, Yifei Yang, Jiaying Wu, Xulang Zhang, Xiangzheng Kong, Herun Wan, Zihan Ma and Minnan Luo ") -> PAMAS: Self-Adaptive Multi-Agent System with Perspective Aggregation for Misinformation Detection Zongwei Wang, Min Gao, Junliang Yu, Tong Chen and Chenghua Lin TrueLens: Video Fake News Detection with Dual Level Evidence Gathering and Consolidation Junyi Chen, Qian Liu, Jing Sun and Yi Zhang Is Misinformation More Open? A Study of robots.txt Gatekeeping on the Web Nicolas Steinacker-Olsztyn, Devashish Gosain and Ha Dao From Manipulation to Mistrust: Explaining Diverse Micro-Video Misinformation for Robust Debunking in the Wild Zhi Zeng, Yifei Yang, Jiaying Wu, Xulang Zhang, Xiangzheng Kong, Herun Wan, Zihan Ma and Minnan Luo | K41: =IFERROR(__xludf.DUMMYFUNCTION("TEXTJOIN(CHAR(10), TRUE,FILTER('Research assignment'!$D:$D,'Research assignment'!$F:$F=K39))"),"Adaptive Graph Reweighting for Collaborative Filtering Yijun Sheng, Ximing Chen, Pui Ieng Lei, Yanyan Liu and Zhiguo Gong IACLR: Intention Alignment via Contrastive Learning for Bipartite Graph Recommendation Huiying Hu, Tuo Wang, Yixiao Zhou and Xiaoqin"&"g Lyu PULSE: Socially-Aware User Representation Modeling Toward Parameter-Efficient Graph Collaborative Filtering Doyun Choi, Cheonwoo Lee, Biniyam Aschalew Tolera, Taewook Ham, Chanyoung Park and Jaemin Yoo Line Graphs Are Here! Unlock a Simple Solutio"&"n for Data Sparsity and Class Imbalance in Recommender System Junming Zhou, Hao Zhong, Shupeng Li, Zhengyang Wu, Yong Tang and Ronghua Lin Multi-modal Bipartite Graph Structure Learning with Information Bottleneck for Micro-video Recommendation Ying He, "&"Desheng Cai, Shengsheng Qian, Quan Fang, Yinwei Wei and Changsheng Xu ") -> Adaptive Graph Reweighting for Collaborative Filtering Yijun Sheng, Ximing Chen, Pui Ieng Lei, Yanyan Liu and Zhiguo Gong IACLR: Intention Alignment via Contrastive Learning for Bipartite Graph Recommendation Huiying Hu, Tuo Wang, Yixiao Zhou and Xiaoqing Lyu PULSE: Socially-Aware User Representation Modeling Toward Parameter-Efficient Graph Collaborative Filtering Doyun Choi, Cheonwoo Lee, Biniyam Aschalew Tolera, Taewook Ham, Chanyoung Park and Jaemin Yoo Line Graphs Are Here! Unlock a Simple Solution for Data Sparsity and Class Imbalance in Recommender System Junming Zhou, Hao Zhong, Shupeng Li, Zhengyang Wu, Yong Tang and Ronghua Lin Multi-modal Bipartite Graph Structure Learning with Information Bottleneck for Micro-video Recommendation Ying He, Desheng Cai, Shengsheng Qian, Quan Fang, Yinwei Wei and Changsheng Xu | L41: =IFERROR(__xludf.DUMMYFUNCTION("TEXTJOIN(CHAR(10), TRUE,FILTER('Industry assignment'!$D:$D,'Industry assignment'!$F:$F=L39))"),"Self-Evolving LLMs via Continual Instruction Tuning Jiazheng Kang, Le Huang, Cheng Hou, Zhe Zhao, ZhenXiang Yan and Ting Bai Large Reasoning Embedding Models: Towards Next-Generation Dense Retrieval Paradigm Jianting Tang, Dongshuai Li, Tao Wen, Fuyu Lv,"&" Dan Ou and Linli Xu Probe-and-Fetch: Dynamic KV Cache Pruning for Accelerated Long-Context Inference in Web-Scale AI Search Yuchen Li, Rui Kong, Xinran Chen, Chengzhe Zhang, Jiamin Chen, Cheng Deng, Xinyu Ma, Haojie Zhang, Tianhao Peng, Hengyi Cai, Shua"&"iqiang Wang, Jiashu Zhao, Yongqi Zhang, Haoyi Xiong, Jimmy Xiangji Huang, Lei Chen, Jun Wang and Dawei Yin DG-MCTS: Dual-Guidance Monte Carlo Tree Search for Adaptive Emotional Support Dialogue Planning Benshuo Lin, Jiayu Ding, Yuelei Li, Peng Wu, Yun Xu"&"e and Yiping Song LaV-CoT: Language-Aware Visual CoT with Multi-Aspect Reward Optimization for Multilingual Text-Centric VQA Jing Huang, Zhiya Tan, Shutao Gong, Fanwei Zeng, Joey Tianyi Zhou, Changtao Miao, Huazhe Tan, Weibin Yao and Jianshu Li ") -> Self-Evolving LLMs via Continual Instruction Tuning Jiazheng Kang, Le Huang, Cheng Hou, Zhe Zhao, ZhenXiang Yan and Ting Bai Large Reasoning Embedding Models: Towards Next-Generation Dense Retrieval Paradigm Jianting Tang, Dongshuai Li, Tao Wen, Fuyu Lv, Dan Ou and Linli Xu Probe-and-Fetch: Dynamic KV Cache Pruning for Accelerated Long-Context Inference in Web-Scale AI Search Yuchen Li, Rui Kong, Xinran Chen, Chengzhe Zhang, Jiamin Chen, Cheng Deng, Xinyu Ma, Haojie Zhang, Tianhao Peng, Hengyi Cai, Shuaiqiang Wang, Jiashu Zhao, Yongqi Zhang, Haoyi Xiong, Jimmy Xiangji Huang, Lei Chen, Jun Wang and Dawei Yin DG-MCTS: Dual-Guidance Monte Carlo Tree Search for Adaptive Emotional Support Dialogue Planning Benshuo Lin, Jiayu Ding, Yuelei Li, Peng Wu, Yun Xue and Yiping Song LaV-CoT: Language-Aware Visual CoT with Multi-Aspect Reward Optimization for Multilingual Text-Centric VQA Jing Huang, Zhiya Tan, Shutao Gong, Fanwei Zeng, Joey Tianyi Zhou, Changtao Miao, Huazhe Tan, Weibin Yao and Jianshu Li | M41: =IFERROR(__xludf.DUMMYFUNCTION("TEXTJOIN(CHAR(10), TRUE,FILTER('Industry assignment'!$D:$D,'Industry assignment'!$F:$F=M39))"),"A Generative Contextual Comprehension Paradigm for Takeout Ranking Model Ziheng Ni, Congcong Liu, Cai Shang, Yiming Sun, Junjie Li, Zhiwei Fang, Guangpeng Chen, Li Jian, Zehua Zhang, Changping Peng, Zhangang Lin, Ching Law and Jingping Shao ARADD: An Aut"&"omatic Real-World API Discovery and Deployment Framework for AI Guide Service in Baidu Map Fuling Wang, Le Zhang, Jingbo Zhou, Jindong Han, Ying Sun, Chuan Qin, Hengshu Zhu and Hui Xiong TRABL: A Unified Framework for Travel Domain Aspect-Based Sentiment"&" Analysis Applications of Large Language Models Omer Madmon, Shiran Golan, Eran Fainman, Ofri Kleinfeld and Moran Beladev From Sold-Out to Sales Uplift: Causal Inference for Intelligent Inventory Management on Online Travel Platforms Fanwei Zhu, Zhuoran "&"Zhuang, Detao Lv, Manwei Li and Yao Yu Enhancing Ride-Hailing Forecasting at DiDi with Multi-View Geospatial Representation Learning from the Web Xixuan Hao, Guicheng Li, Daiqiang Wu, Xusen Guo, Yumeng Zhu, Zhichao Zou, Peng Zhen, Yao Yao and Yuxuan Lian"&"g ") -> A Generative Contextual Comprehension Paradigm for Takeout Ranking Model Ziheng Ni, Congcong Liu, Cai Shang, Yiming Sun, Junjie Li, Zhiwei Fang, Guangpeng Chen, Li Jian, Zehua Zhang, Changping Peng, Zhangang Lin, Ching Law and Jingping Shao ARADD: An Automatic Real-World API Discovery and Deployment Framework for AI Guide Service in Baidu Map Fuling Wang, Le Zhang, Jingbo Zhou, Jindong Han, Ying Sun, Chuan Qin, Hengshu Zhu and Hui Xiong TRABL: A Unified Framework for Travel Domain Aspect-Based Sentiment Analysis Applications of Large Language Models Omer Madmon, Shiran Golan, Eran Fainman, Ofri Kleinfeld and Moran Beladev From Sold-Out to Sales Uplift: Causal Inference for Intelligent Inventory Management on Online Travel Platforms Fanwei Zhu, Zhuoran Zhuang, Detao Lv, Manwei Li and Yao Yu Enhancing Ride-Hailing Forecasting at DiDi with Multi-View Geospatial Representation Learning from the Web Xixuan Hao, Guicheng Li, Daiqiang Wu, Xusen Guo, Yumeng Zhu, Zhichao Zou, Peng Zhen, Yao Yao and Yuxuan Liang | N41: =IFERROR(__xludf.DUMMYFUNCTION("TEXTJOIN(CHAR(10), TRUE,FILTER('Web4Good assignment'!$D:$D,'Web4Good assignment'!$F:$F=N39))"),"When to Invoke: Refining LLM Fairness with Toxicity Assessment Jing Ren, Bowen Li, Ziqi Xu, Renqiang Luo, Shuo Yu, Xin Ye, Haytham Fayek, Xiaodong Li and Feng Xia Trust in One Round: Confidence Estimation for Large Language Models via Structural Signals "&"Pengyue Yang, Jiawen Wen, Haolin Jin, Linghan Huang, Huaming Chen and Ling Chen BalDRO: A Distributionally Robust Optimization based Framework for Large Language Model Unlearning Pengyang Shao, Naixin Zhai, Lei Chen, Yonghui Yang, Fengbin Zhu, Xun Yang a"&"nd Meng Wang SEP-Attack: A Simple and Effective Paradigm for Transfer-Based Textual Adversarial Attack Han Liu, Zhi Xu, Xiaotong Zhang, Feng Zhang, Xiaoming Xu, Wei Wang, Fenglong Ma and Hong Yu Fine-Grained Traceability for Transparent ML Pipelines Lip"&"ing Chen, Mujie Liu and Haytham Fayek ") -> When to Invoke: Refining LLM Fairness with Toxicity Assessment Jing Ren, Bowen Li, Ziqi Xu, Renqiang Luo, Shuo Yu, Xin Ye, Haytham Fayek, Xiaodong Li and Feng Xia Trust in One Round: Confidence Estimation for Large Language Models via Structural Signals Pengyue Yang, Jiawen Wen, Haolin Jin, Linghan Huang, Huaming Chen and Ling Chen BalDRO: A Distributionally Robust Optimization based Framework for Large Language Model Unlearning Pengyang Shao, Naixin Zhai, Lei Chen, Yonghui Yang, Fengbin Zhu, Xun Yang and Meng Wang SEP-Attack: A Simple and Effective Paradigm for Transfer-Based Textual Adversarial Attack Han Liu, Zhi Xu, Xiaotong Zhang, Feng Zhang, Xiaoming Xu, Wei Wang, Fenglong Ma and Hong Yu Fine-Grained Traceability for Transparent ML Pipelines Liping Chen, Mujie Liu and Haytham Fayek
A42: 13:00 - 14:00 | B42: Posters and Demos Session 3
B43: Demos3 | C43: ShortPapers3 | D43: =IFERROR(__xludf.DUMMYFUNCTION("TRANSPOSE(FILTER('All Counts'!B:B, RIGHT('All Counts'!B:B, 1)=""3""))"),"EconPoster3") -> EconPoster3 | E43: =IFERROR(__xludf.DUMMYFUNCTION("""COMPUTED_VALUE"""),"GraphPoster3") -> GraphPoster3 | F43: =IFERROR(__xludf.DUMMYFUNCTION("""COMPUTED_VALUE"""),"SearchPoster3") -> SearchPoster3 | G43: =IFERROR(__xludf.DUMMYFUNCTION("""COMPUTED_VALUE"""),"SemanticsPoster3") -> SemanticsPoster3 | H43: =IFERROR(__xludf.DUMMYFUNCTION("""COMPUTED_VALUE"""),"SecurityPoster3") -> SecurityPoster3 | I43: =IFERROR(__xludf.DUMMYFUNCTION("""COMPUTED_VALUE"""),"SocialPoster3") -> SocialPoster3 | J43: =IFERROR(__xludf.DUMMYFUNCTION("""COMPUTED_VALUE"""),"SystemsPoster3") -> SystemsPoster3 | K43: =IFERROR(__xludf.DUMMYFUNCTION("""COMPUTED_VALUE"""),"RecSysPoster3") -> RecSysPoster3 | L43: =IFERROR(__xludf.DUMMYFUNCTION("""COMPUTED_VALUE"""),"MiningPoster3") -> MiningPoster3 | M43: =IFERROR(__xludf.DUMMYFUNCTION("""COMPUTED_VALUE"""),"IndustryPoster3") -> IndustryPoster3 | N43: =IFERROR(__xludf.DUMMYFUNCTION("""COMPUTED_VALUE"""),"Web4GoodPoster3") -> Web4GoodPoster3
